{
    "Stats": {
        "Categorised": "40 notes (65.57%)",
        "Notes’ total": 61,
        "Profiles": [
            "པེ་=སྡེ་ སྣར་: 3.28% (2 notes)",
            "པེ་=སྣར་ སྡེ་: 80.33% (49 notes)",
            "པེ་ སྡེ་=སྣར་: 14.75% (9 notes)",
            "པེ་=སྡེ་=སྣར་: 1.64% (1 notes)"
        ],
        "automatic_categorisation": {
            "min_mod": {
                "min_mod_groups": 5,
                "particle_groups": 10
            },
            "particle_issues": {
                "different_particles": 2
            },
            "spelling_mistake": {
                "non_word": {
                    "well_formed": 1
                }
            },
            "sskrt": 4,
            "verb_difference": {
                "diff_tense": 13,
                "diff_verb": 4
            }
        },
        "dunno": {
            "no_diff": 21
        },
        "empty_notes": 1,
        "manual_categorisation": {
            "long_difference": {},
            "manual_evaluation": {
                "meaning_difference": {}
            }
        },
        "ngram_freq": {},
        "profile": {}
    },
    "automatic_categorisation": {
        "min_mod": {
            "min_mod_groups": [
                {
                    "11": [
                        [
                            [
                                "ལས",
                                "ལ"
                            ]
                        ],
                        {
                            "པེ་": [
                                "མ་ ཡིན་ ནོ །_། གང་",
                                "ལས་",
                                "རང་བཞིན་ ཡོད་ མིན་པ འི"
                            ],
                            "སྡེ་": [
                                "མ་ ཡིན་ ནོ །_། གང་",
                                "ལ་",
                                "རང་བཞིན་ ཡོད་ མིན་པ འི"
                            ],
                            "སྣར་": [
                                "མ་ ཡིན་ ནོ །_། གང་",
                                "ལས་",
                                "རང་བཞིན་ ཡོད་ མིན་པ འི"
                            ]
                        }
                    ]
                },
                {
                    "26": [
                        [
                            [
                                "ལས",
                                "ལ"
                            ]
                        ],
                        {
                            "པེ་": [
                                "གྲུབ །_། གཞལ་ བྱ་ རྣམས་",
                                "ལས་",
                                "མ་ ལྟོས་པ ར །_། ཁྱོད་"
                            ],
                            "སྡེ་": [
                                "གྲུབ །_། གཞལ་ བྱ་ རྣམས་",
                                "ལ་",
                                "མ་ ལྟོས་པ ར །_། ཁྱོད་"
                            ],
                            "སྣར་": [
                                "གྲུབ །_། གཞལ་ བྱ་ རྣམས་",
                                "ལས་",
                                "མ་ ལྟོས་པ ར །_། ཁྱོད་"
                            ]
                        }
                    ]
                },
                {
                    "27": [
                        [
                            [
                                "ལས",
                                "ལ"
                            ]
                        ],
                        {
                            "པེ་": [
                                "འདི །_། རང་ གྲུབ་ གཞན་",
                                "ལས་",
                                "ལྟོས་ མ་ ཡིན །_།"
                            ],
                            "སྡེ་": [
                                "འདི །_། རང་ གྲུབ་ གཞན་",
                                "ལ་",
                                "ལྟོས་ མ་ ཡིན །_།"
                            ],
                            "སྣར་": [
                                "འདི །_། རང་ གྲུབ་ གཞན་",
                                "ལས་",
                                "ལྟོས་ མ་ ཡིན །_།"
                            ]
                        }
                    ]
                },
                {
                    "29": [
                        [
                            [
                                "ལས",
                                "ལ"
                            ]
                        ],
                        {
                            "པེ་": [
                                "ཏེ་ ཡོང་ #ཡེ་ གཞལ་ བྱ་",
                                "ལས",
                                "།_། ལྟོས་ ནས་ ཚད་མ་"
                            ],
                            "སྡེ་": [
                                "ཏེ་ ཡོང་ #ཡེ་ གཞལ་ བྱ་",
                                "ལ",
                                "།_། ལྟོས་ ནས་ ཚད་མ་"
                            ],
                            "སྣར་": [
                                "ཏེ་ ཡོང་ #ཡེ་ གཞལ་ བྱ་",
                                "ལས",
                                "།_། ལྟོས་ ནས་ ཚད་མ་"
                            ]
                        }
                    ]
                },
                {
                    "58": [
                        [
                            [
                                "ལས",
                                "ལ"
                            ]
                        ],
                        {
                            "པེ་": [
                                "དཔལ་ བརྩེགས་ ཀྱིས་ བསྒྱུར་བ་",
                                "ལས",
                                "།_ སླད་ ཀྱིས་ ཁ་ ཆེ འི་"
                            ],
                            "སྡེ་": [
                                "དཔལ་ བརྩེགས་ ཀྱིས་ བསྒྱུར་བ་",
                                "ལ",
                                "།_ སླད་ ཀྱིས་ ཁ་ ཆེ འི་"
                            ],
                            "སྣར་": [
                                "དཔལ་ བརྩེགས་ ཀྱིས་ བསྒྱུར་བ་",
                                "ལས",
                                "།_ སླད་ ཀྱིས་ ཁ་ ཆེ འི་"
                            ]
                        }
                    ]
                }
            ],
            "particle_groups": [
                {
                    "2": [
                        [
                            "dreldra",
                            "jedra"
                        ],
                        {
                            "པེ་": [
                                "ཞིག་ གལ་ཏེ་ མངོན་སུམ་",
                                "གྱི",
                                "།_། དངོས་ རྣམས་ དམིགས་ ནས་"
                            ],
                            "སྡེ་": [
                                "ཞིག་ གལ་ཏེ་ མངོན་སུམ་",
                                "གྱིས",
                                "།_། དངོས་ རྣམས་ དམིགས་ ནས་"
                            ],
                            "སྣར་": [
                                "ཞིག་ གལ་ཏེ་ མངོན་སུམ་",
                                "གྱི",
                                "།_། དངོས་ རྣམས་ དམིགས་ ནས་"
                            ]
                        }
                    ]
                },
                {
                    "8": [
                        [
                            "dreldra",
                            "jedra"
                        ],
                        {
                            "པེ་": [
                                "ལྟར །_། དེ་ བཞིན་ ཁྱོད་",
                                "ཀྱི་",
                                "ཡོད་ མིན་ ལ །_། ལོག་"
                            ],
                            "སྡེ་": [
                                "ལྟར །_། དེ་ བཞིན་ ཁྱོད་",
                                "ཀྱིས་",
                                "ཡོད་ མིན་ ལ །_། ལོག་"
                            ],
                            "སྣར་": [
                                "ལྟར །_། དེ་ བཞིན་ ཁྱོད་",
                                "ཀྱི་",
                                "ཡོད་ མིན་ ལ །_། ལོག་"
                            ]
                        }
                    ]
                },
                {
                    "20": [
                        [
                            "dreldra",
                            "jedra"
                        ],
                        {
                            "པེ་": [
                                "འཛིན་ འབྱུང་ ལ་ སྤྲུལ་པ་",
                                "ཡི",
                                "།_། འགོག་ བྱེད་ དེ་ ནི་"
                            ],
                            "སྡེ་": [
                                "འཛིན་ འབྱུང་ ལ་ སྤྲུལ་པ་",
                                "ཡིས",
                                "།_། འགོག་ བྱེད་ དེ་ ནི་"
                            ],
                            "སྣར་": [
                                "འཛིན་ འབྱུང་ ལ་ སྤྲུལ་པ་",
                                "ཡི",
                                "།_། འགོག་ བྱེད་ དེ་ ནི་"
                            ]
                        }
                    ]
                },
                {
                    "22": [
                        [
                            "dreldra",
                            "jedra"
                        ],
                        {
                            "པེ་": [
                                "ཉིད་ ཀྱིས་ རབ་ བསྒྲུབས་ ན །_། ཁྱོད་",
                                "ཀྱི་",
                                "ཚད་མ་ དེ་ རྣམས་ ཀྱང་"
                            ],
                            "སྡེ་": [
                                "ཉིད་ ཀྱིས་ རབ་ བསྒྲུབས་ ན །_། ཁྱོད་",
                                "ཀྱིས་",
                                "ཚད་མ་ དེ་ རྣམས་ ཀྱང་"
                            ],
                            "སྣར་": [
                                "ཉིད་ ཀྱིས་ རབ་ བསྒྲུབས་ ན །_། ཁྱོད་",
                                "ཀྱི་",
                                "ཚད་མ་ དེ་ རྣམས་ ཀྱང་"
                            ]
                        }
                    ]
                },
                {
                    "25": [
                        [
                            "dreldra",
                            "jedra"
                        ],
                        {
                            "པེ་": [
                                "འགྱུར །_། གལ་ཏེ་ ཁྱོད་",
                                "ཀྱིས་",
                                "ཚིག་ གིས་ ནི །_། མེ་"
                            ],
                            "སྡེ་": [
                                "འགྱུར །_། གལ་ཏེ་ ཁྱོད་",
                                "ཀྱི་",
                                "ཚིག་ གིས་ ནི །_། མེ་"
                            ],
                            "སྣར་": [
                                "འགྱུར །_། གལ་ཏེ་ ཁྱོད་",
                                "ཀྱིས་",
                                "ཚིག་ གིས་ ནི །_། མེ་"
                            ]
                        }
                    ]
                },
                {
                    "33": [
                        [
                            "dreldra",
                            "jedra"
                        ],
                        {
                            "པེ་": [
                                "འགྱུར །_། འོན་ཏེ་ ཁྱོད་",
                                "ཀྱི་",
                                "ཚད་ གྲུབ་པ ས །_། གཞལ་"
                            ],
                            "སྡེ་": [
                                "འགྱུར །_། འོན་ཏེ་ ཁྱོད་",
                                "ཀྱིས་",
                                "ཚད་ གྲུབ་པ ས །_། གཞལ་"
                            ],
                            "སྣར་": [
                                "འགྱུར །_། འོན་ཏེ་ ཁྱོད་",
                                "ཀྱི་",
                                "ཚད་ གྲུབ་པ ས །_། གཞལ་"
                            ]
                        }
                    ]
                },
                {
                    "43": [
                        [
                            "dreldra",
                            "jedra"
                        ],
                        {
                            "པེ་": [
                                "བ་ ཡིས་ ནི་ ཆོས་ རྣམས་",
                                "ཀྱིས",
                                "།_། དགེ་བ འི་ ཆོས་ རྣམས་ རང་བཞིན་ གང་"
                            ],
                            "སྡེ་": [
                                "བ་ ཡིས་ ནི་ ཆོས་ རྣམས་",
                                "ཀྱི",
                                "།_། དགེ་བ འི་ ཆོས་ རྣམས་ རང་བཞིན་ གང་"
                            ],
                            "སྣར་": [
                                "བ་ ཡིས་ ནི་ ཆོས་ རྣམས་",
                                "ཀྱིས",
                                "།_། དགེ་བ འི་ ཆོས་ རྣམས་ རང་བཞིན་ གང་"
                            ]
                        }
                    ]
                },
                {
                    "45": [
                        [
                            "dreldra",
                            "jedra"
                        ],
                        {
                            "པེ་": [
                                "ཏེ་ དགེ་བ འི་ ཆོས་ རྣམས་",
                                "ཀྱི",
                                "།_། རང་ གི་ ངོ་བོ་"
                            ],
                            "སྡེ་": [
                                "ཏེ་ དགེ་བ འི་ ཆོས་ རྣམས་",
                                "ཀྱིས",
                                "།_། རང་ གི་ ངོ་བོ་"
                            ],
                            "སྣར་": [
                                "ཏེ་ དགེ་བ འི་ ཆོས་ རྣམས་",
                                "ཀྱི",
                                "།_། རང་ གི་ ངོ་བོ་"
                            ]
                        }
                    ]
                },
                {
                    "48": [
                        [
                            "dreldra",
                            "jedra"
                        ],
                        {
                            "པེ་": [
                                "ལྟར་ ཁྱོད་ ཀྱིས་ ལན་ བཏབ་",
                                "ཀྱིས",
                                "།_། ང་ ཡི་ མིང་ ཡོད་"
                            ],
                            "སྡེ་": [
                                "ལྟར་ ཁྱོད་ ཀྱིས་ ལན་ བཏབ་",
                                "ཀྱི",
                                "།_། ང་ ཡི་ མིང་ ཡོད་"
                            ],
                            "སྣར་": [
                                "ལྟར་ ཁྱོད་ ཀྱིས་ ལན་ བཏབ་",
                                "ཀྱིས",
                                "།_། ང་ ཡི་ མིང་ ཡོད་"
                            ]
                        }
                    ]
                },
                {
                    "51": [
                        [
                            "ladon"
                        ],
                        {
                            "པེ་": [
                                "པོ་ སྨྲས་པ་ གང་  །_།",
                                "དེ ར་ ཡང་",
                                "ཅི་ ནས་ དཔེ་ དེ་"
                            ],
                            "སྡེ་": [
                                "པོ་ སྨྲས་པ་ གང་  །_།",
                                "དེ་ཡང་",
                                "ཅི་ ནས་ དཔེ་ དེ་"
                            ],
                            "སྣར་": [
                                "པོ་ སྨྲས་པ་ གང་  །_།",
                                "དེ ར་ ཡང་",
                                "ཅི་ ནས་ དཔེ་ དེ་"
                            ]
                        }
                    ]
                }
            ]
        },
        "particle_issues": {
            "added_particle": [],
            "agreement_issue": [],
            "different_particles": [
                {
                    "5": [
                        "dagdra_pa",
                        {
                            "པེ་": [
                                "སུམ་ གྱིས་ ནི་ ལན་",
                                "བཏབ་པོ",
                                "།_། སྐྱེ་བོ་ ཆོས་ ཀྱི་"
                            ],
                            "སྡེ་": [
                                "སུམ་ གྱིས་ ནི་ ལན་",
                                "བཏབ་པོ",
                                "།_། སྐྱེ་བོ་ ཆོས་ ཀྱི་"
                            ],
                            "སྣར་": [
                                "སུམ་ གྱིས་ ནི་ ལན་",
                                "བཏབ་པ",
                                "།_། སྐྱེ་བོ་ ཆོས་ ཀྱི་"
                            ]
                        }
                    ]
                },
                {
                    "7": [
                        "lhakce",
                        {
                            "པེ་": [
                                "ཡང་ དེ་ བཞིན་ མེད་ འགྱུར་",
                                "ཏེ",
                                "།_། གཞི་ མེད་ མིང་ ནི་"
                            ],
                            "སྡེ་": [
                                "ཡང་ དེ་ བཞིན་ མེད་ འགྱུར་",
                                "ཞིང་ ",
                                "།_། གཞི་ མེད་ མིང་ ནི་"
                            ],
                            "སྣར་": [
                                "ཡང་ དེ་ བཞིན་ མེད་ འགྱུར་",
                                "ཏེ",
                                "།_། གཞི་ མེད་ མིང་ ནི་"
                            ]
                        }
                    ]
                }
            ],
            "other": [],
            "po-bo-pa-ba": []
        },
        "spelling_mistake": {
            "missing_vowel": [],
            "nga_da": [],
            "non_word": {
                "ill_formed": [],
                "well_formed": [
                    {
                        "56": [
                            {
                                "པེ་": [
                                    "ལ་ ཕྱག་ འཚལ་ ལོ །_།",
                                    "#བརྩོད་པ་",
                                    "བཟློག་པ འི་ ཚིག་ ལེའུ ར་"
                                ],
                                "སྡེ་": [
                                    "ལ་ ཕྱག་ འཚལ་ ལོ །_།",
                                    "རྩོད་པ་",
                                    "བཟློག་པ འི་ ཚིག་ ལེའུ ར་"
                                ],
                                "སྣར་": [
                                    "ལ་ ཕྱག་ འཚལ་ ལོ །_།",
                                    "#བརྩོད་པ་",
                                    "བཟློག་པ འི་ ཚིག་ ལེའུ ར་"
                                ]
                            }
                        ]
                    }
                ]
            }
        },
        "sskrt": [
            {
                "1": [
                    {
                        "པེ་": [
                            "རྒྱ་གར་ སྐད་ དུ །_",
                            "#ལྱེ་ #ཀྲ་",
                            "#ཧ་ བྱ་ བརྟ་ ནི་"
                        ],
                        "སྡེ་": [
                            "རྒྱ་གར་ སྐད་ དུ །_",
                            "#བི་ #གྲ་",
                            "#ཧ་ བྱ་ བརྟ་ ནི་"
                        ],
                        "སྣར་": [
                            "རྒྱ་གར་ སྐད་ དུ །_",
                            "#ལྱེ་ #ཀྲ་",
                            "#ཧ་ བྱ་ བརྟ་ ནི་"
                        ]
                    }
                ]
            },
            {
                "57": [
                    {
                        "པེ་": [
                            "དང་  །_ བོད་ ཀྱི་",
                            "ལོ་ཙཱ་བ་",
                            "ཀ་བ་ དཔལ་ བརྩེགས་"
                        ],
                        "སྡེ་": [
                            "དང་  །_ བོད་ ཀྱི་",
                            "#ལོཙྪ་བ་",
                            "ཀ་བ་ དཔལ་ བརྩེགས་"
                        ],
                        "སྣར་": [
                            "དང་  །_ བོད་ ཀྱི་",
                            "ལོ་ཙཱ་བ་",
                            "ཀ་བ་ དཔལ་ བརྩེགས་"
                        ]
                    }
                ]
            },
            {
                "59": [
                    {
                        "པེ་": [
                            "ཆེ འི་ #པཎྜི་ #ཏ་ #ཛ་ #ཡ་",
                            "#ཨཱ་",
                            "#ནནྟ་ དང་  །_"
                        ],
                        "སྡེ་": [
                            "ཆེ འི་ #པཎྜི་ #ཏ་ #ཛ་ #ཡ་",
                            "ཨ་",
                            "#ནནྟ་ དང་  །_"
                        ],
                        "སྣར་": [
                            "ཆེ འི་ #པཎྜི་ #ཏ་ #ཛ་ #ཡ་",
                            "#ཨཱ་",
                            "#ནནྟ་ དང་  །_"
                        ]
                    }
                ]
            },
            {
                "60": [
                    {
                        "པེ་": [
                            "ཨ་ #ནནྟ་ དང་  །_",
                            "ལོ་ཙཱ་བ་",
                            "ཁུ་ མདོ་སྡེ་ དཔལ་"
                        ],
                        "སྡེ་": [
                            "ཨ་ #ནནྟ་ དང་  །_",
                            "#ལོཙྪ་བ་",
                            "ཁུ་ མདོ་སྡེ་ དཔལ་"
                        ],
                        "སྣར་": [
                            "ཨ་ #ནནྟ་ དང་  །_",
                            "ལོ་ཙཱ་བ་",
                            "ཁུ་ མདོ་སྡེ་ དཔལ་"
                        ]
                    }
                ]
            }
        ],
        "verb_difference": {
            "diff_tense": [
                {
                    "3": [
                        [
                            "《ཟློག》ཞེས་པ།【〈ཟློག〉གི་ ད་ལྟ་བ།】【〈ཟློག〉གི་ ད་ལྟ་བ། ཐ་དད་པ།】",
                            "《བཟློག》ཞེས་པ།【〈ཟློག〉གི་ མ་འོངས་པ།】【〈ཟློག〉གི་ མ་འོངས་པ། ཐ་དད་པ།】"
                        ],
                        {
                            "པེ་": [
                                " །_། དངོས་ རྣམས་ དམིགས་ ནས་",
                                "བཟློག་",
                                "བྱེད་པ །_། གང་ གིས་"
                            ],
                            "སྡེ་": [
                                " །_། དངོས་ རྣམས་ དམིགས་ ནས་",
                                "ཟློག་",
                                "བྱེད་པ །_། གང་ གིས་"
                            ],
                            "སྣར་": [
                                " །_། དངོས་ རྣམས་ དམིགས་ ནས་",
                                "བཟློག་",
                                "བྱེད་པ །_། གང་ གིས་"
                            ]
                        }
                    ]
                },
                {
                    "9": [
                        [
                            "《འགོག》ཞེས་པ།【〈འགོག〉གི་ ད་ལྟ་བ།】【〈འགོག〉གི་ ད་ལྟ་བ། ཐ་དད་པ།】",
                            "《དགག》ཞེས་པ།【〈འགོག〉གི་ མ་འོངས་པ།】【〈འགོག〉གི་ མ་འོངས་པ། ཐ་དད་པ།】"
                        ],
                        {
                            "པེ་": [
                                "པོ་ དང་  །_། འགོག་ དང་",
                                "དགག་",
                                "བྱ་ འགོག་པ་པོ །_། "
                            ],
                            "སྡེ་": [
                                "པོ་ དང་  །_། འགོག་ དང་",
                                "འགོག་",
                                "བྱ་ འགོག་པ་པོ །_། "
                            ],
                            "སྣར་": [
                                "པོ་ དང་  །_། འགོག་ དང་",
                                "དགག་",
                                "བྱ་ འགོག་པ་པོ །_། "
                            ]
                        }
                    ]
                },
                {
                    "19": [
                        [
                            "《གྲུབ》ཞེས་པ།【〈འགྲུབ〉གི་ འདས་པ། ཐ་མི་དད་པ།】",
                            "《འགྲུབ》ཞེས་པ།【〈འགྲུབ〉གི་ ད་ལྟ་བ། ཐ་མི་དད་པ།】【〈འགྲུབ〉གི་ མ་འོངས་པ། ཐ་མི་དད་པ།】"
                        ],
                        {
                            "པེ་": [
                                "རང་བཞིན་ ཉིད་ དུ་ རབ་",
                                "གྲུབ་",
                                "འགྱུར །_། ཡང་ན་ ཁ་"
                            ],
                            "སྡེ་": [
                                "རང་བཞིན་ ཉིད་ དུ་ རབ་",
                                "འགྲུབ་",
                                "འགྱུར །_། ཡང་ན་ ཁ་"
                            ],
                            "སྣར་": [
                                "རང་བཞིན་ ཉིད་ དུ་ རབ་",
                                "གྲུབ་",
                                "འགྱུར །_། ཡང་ན་ ཁ་"
                            ]
                        }
                    ]
                },
                {
                    "30": [
                        [
                            "《གྲུབ》ཞེས་པ།【〈འགྲུབ〉གི་ འདས་པ། ཐ་མི་དད་པ།】",
                            "《འགྲུབ》ཞེས་པ།【〈འགྲུབ〉གི་ ད་ལྟ་བ། ཐ་མི་དད་པ།】【〈འགྲུབ〉གི་ མ་འོངས་པ། ཐ་མི་དད་པ།】"
                        ],
                        {
                            "པེ་": [
                                " །_། ལྟོས་ ནས་ ཚད་མ་",
                                "གྲུབ་",
                                "ཡིན་ ན །_། ཚད་མ་"
                            ],
                            "སྡེ་": [
                                " །_། ལྟོས་ ནས་ ཚད་མ་",
                                "འགྲུབ་",
                                "ཡིན་ ན །_། ཚད་མ་"
                            ],
                            "སྣར་": [
                                " །_། ལྟོས་ ནས་ ཚད་མ་",
                                "འགྲུབ་",
                                "ཡིན་ ན །_། ཚད་མ་"
                            ]
                        }
                    ]
                },
                {
                    "32": [
                        [
                            "《གྲུབ》ཞེས་པ།【〈འགྲུབ〉གི་ འདས་པ། ཐ་མི་དད་པ།】",
                            "《འགྲུབ》ཞེས་པ།【〈འགྲུབ〉གི་ ད་ལྟ་བ། ཐ་མི་དད་པ།】【〈འགྲུབ〉གི་ མ་འོངས་པ། ཐ་མི་དད་པ།】"
                        ],
                        {
                            "པེ་": [
                                " །_། ཁྱོད་ ཀྱི་ ཚད་མ་",
                                "གྲུབ་པ ས་",
                                "ཅི །_། ཅི་སྟེ་"
                            ],
                            "སྡེ་": [
                                " །_། ཁྱོད་ ཀྱི་ ཚད་མ་",
                                "འགྲུབ་པ ས་",
                                "ཅི །_། ཅི་སྟེ་"
                            ],
                            "སྣར་": [
                                " །_། ཁྱོད་ ཀྱི་ ཚད་མ་",
                                "གྲུབ་པ ས་",
                                "ཅི །_། ཅི་སྟེ་"
                            ]
                        }
                    ]
                },
                {
                    "34": [
                        [
                            "《སྒྲུབ》ཞེས་པ།【〈སྒྲུབ〉གི་ ད་ལྟ་བ།】【〈སྒྲུབ〉གི་ ད་ལྟ་བ། ཐ་དད་པ།】",
                            "《བསྒྲུབས》ཞེས་པ།【〈སྒྲུབ〉གི་ འདས་པ།】【〈སྒྲུབ〉གི་ འདས་པ། ཐ་དད་པ།】"
                        ],
                        {
                            "པེ་": [
                                "གཞལ་ བྱ་ གྲུབ་པ ས་ ཚད་",
                                "སྒྲུབ་",
                                "ན །_། ཁྱོད་ ཀྱིས་ གཉིས་"
                            ],
                            "སྡེ་": [
                                "གཞལ་ བྱ་ གྲུབ་པ ས་ ཚད་",
                                "བསྒྲུབས་",
                                "ན །_། ཁྱོད་ ཀྱིས་ གཉིས་"
                            ],
                            "སྣར་": [
                                "གཞལ་ བྱ་ གྲུབ་པ ས་ ཚད་",
                                "བསྒྲུབས་",
                                "ན །_། ཁྱོད་ ཀྱིས་ གཉིས་"
                            ]
                        }
                    ]
                },
                {
                    "35": [
                        [
                            "《བསྒྲུབ》ཞེས་པ།【〈སྒྲུབ〉གི་ མ་འོངས་པ།】【〈སྒྲུབ〉གི་ མ་འོངས་པ། ཐ་དད་པ།】",
                            "《སྒྲུབ》ཞེས་པ།【〈སྒྲུབ〉གི་ ད་ལྟ་བ།】【〈སྒྲུབ〉གི་ ད་ལྟ་བ། ཐ་དད་པ།】"
                        ],
                        {
                            "པེ་": [
                                " །_། དེ་དག་ ཇི་ལྟར་",
                                "སྒྲུབ་པ ར་",
                                "འགྱུར །_། གལ་ཏེ་"
                            ],
                            "སྡེ་": [
                                " །_། དེ་དག་ ཇི་ལྟར་",
                                "བསྒྲུབ་པ ར་",
                                "འགྱུར །_། གལ་ཏེ་"
                            ],
                            "སྣར་": [
                                " །_། དེ་དག་ ཇི་ལྟར་",
                                "སྒྲུབ་པ ར་",
                                "འགྱུར །_། གལ་ཏེ་"
                            ]
                        }
                    ]
                },
                {
                    "36": [
                        [
                            "《གྲུབ》ཞེས་པ།【〈འགྲུབ〉གི་ འདས་པ། ཐ་མི་དད་པ།】",
                            "《འགྲུབ》ཞེས་པ།【〈འགྲུབ〉གི་ ད་ལྟ་བ། ཐ་མི་དད་པ།】【〈འགྲུབ〉གི་ མ་འོངས་པ། ཐ་མི་དད་པ།】"
                        ],
                        {
                            "པེ་": [
                                "ཏེ་ གཞལ་ བྱས་ ཚད་མ་",
                                "འགྲུབ",
                                "།_། ཚད་མ་ དེ་དག་"
                            ],
                            "སྡེ་": [
                                "ཏེ་ གཞལ་ བྱས་ ཚད་མ་",
                                "གྲུབ",
                                "།_། ཚད་མ་ དེ་དག་"
                            ],
                            "སྣར་": [
                                "ཏེ་ གཞལ་ བྱས་ ཚད་མ་",
                                "འགྲུབ",
                                "།_། ཚད་མ་ དེ་དག་"
                            ]
                        }
                    ]
                },
                {
                    "38": [
                        [
                            "《བསྒྲུབ》ཞེས་པ།【〈སྒྲུབ〉གི་ མ་འོངས་པ།】【〈སྒྲུབ〉གི་ མ་འོངས་པ། ཐ་དད་པ།】",
                            "《སྒྲུབ》ཞེས་པ།【〈སྒྲུབ〉གི་ ད་ལྟ་བ།】【〈སྒྲུབ〉གི་ ད་ལྟ་བ། ཐ་དད་པ།】"
                        ],
                        {
                            "པེ་": [
                                "ཀྱིས་ ཀྱང་  །_། དེ་དག་",
                                "སྒྲུབ་པ ར་",
                                "བྱ་ ཡིན་ ན །_། "
                            ],
                            "སྡེ་": [
                                "ཀྱིས་ ཀྱང་  །_། དེ་དག་",
                                "བསྒྲུབ་པ ར་",
                                "བྱ་ ཡིན་ ན །_། "
                            ],
                            "སྣར་": [
                                "ཀྱིས་ ཀྱང་  །_། དེ་དག་",
                                "སྒྲུབ་པ ར་",
                                "བྱ་ ཡིན་ ན །_། "
                            ]
                        }
                    ]
                },
                {
                    "39": [
                        [
                            "《བསྒྲུབ》ཞེས་པ།【〈སྒྲུབ〉གི་ མ་འོངས་པ།】【〈སྒྲུབ〉གི་ མ་འོངས་པ། ཐ་དད་པ།】",
                            "《སྒྲུབ》ཞེས་པ།【〈སྒྲུབ〉གི་ ད་ལྟ་བ།】【〈སྒྲུབ〉གི་ ད་ལྟ་བ། ཐ་དད་པ།】"
                        ],
                        {
                            "པེ་": [
                                " །_། དེ་དག་ ཇི་ལྟར་",
                                "སྒྲུབ་པ ར་",
                                "འགྱུར །_། གལ་ཏེ་"
                            ],
                            "སྡེ་": [
                                " །_། དེ་དག་ ཇི་ལྟར་",
                                "བསྒྲུབ་པ ར་",
                                "འགྱུར །_། གལ་ཏེ་"
                            ],
                            "སྣར་": [
                                " །_། དེ་དག་ ཇི་ལྟར་",
                                "སྒྲུབ་པ ར་",
                                "འགྱུར །_། གལ་ཏེ་"
                            ]
                        }
                    ]
                },
                {
                    "41": [
                        [
                            "《གྱུར》ཞེས་པ།【〈འགྱུར〉གི་ འདས་པ། ཐ་མི་དད་པ།】",
                            "《འགྱུར》ཞེས་པ།【གཟུགས་མི་འགྱུར་བ།】【〈འགྱུར〉གི་ ད་ལྟ་བ། ཐ་མི་དད་པ།】【〈འགྱུར〉གི་ མ་འོངས་པ། ཐ་མི་དད་པ།】"
                        ],
                        {
                            "པེ་": [
                                "ལ་ ཁོ་བོ་ ཐེ་ ཚོམ་",
                                "འགྱུར",
                                "།_། དེ་ ལས་ ཕ་ གང་"
                            ],
                            "སྡེ་": [
                                "ལ་ ཁོ་བོ་ ཐེ་ ཚོམ་",
                                "གྱུར",
                                "།_། དེ་ ལས་ ཕ་ གང་"
                            ],
                            "སྣར་": [
                                "ལ་ ཁོ་བོ་ ཐེ་ ཚོམ་",
                                "གྱུར",
                                "།_། དེ་ ལས་ ཕ་ གང་"
                            ]
                        }
                    ]
                },
                {
                    "49": [
                        [
                            "《འགོག》ཞེས་པ།【〈འགོག〉གི་ ད་ལྟ་བ།】【〈འགོག〉གི་ ད་ལྟ་བ། ཐ་དད་པ།】",
                            "《དགོག》ཞེས་པ།【〈འགོག〉གི་ མ་འོངས་པ། འབྲི་ཚུལ་གཞན།】"
                        ],
                        {
                            "པེ་": [
                                " །_། གལ་ཏེ་ ཡོད་ ཉིད་",
                                "འགོག་",
                                "ཡིན་ ན །_། འོ་ན་"
                            ],
                            "སྡེ་": [
                                " །_། གལ་ཏེ་ ཡོད་ ཉིད་",
                                "འགོག་",
                                "ཡིན་ ན །_། འོ་ན་"
                            ],
                            "སྣར་": [
                                " །_། གལ་ཏེ་ ཡོད་ ཉིད་",
                                "དགོག་",
                                "ཡིན་ ན །_། འོ་ན་"
                            ]
                        }
                    ]
                },
                {
                    "50": [
                        [
                            "《སྐྱེས》ཞེས་པ།【〈སྐྱེ〉གི་ འདས་པ། ཐ་མི་དད་པ།】",
                            "《སྐྱེ》ཞེས་པ།【〈སྐྱེ〉གི་ ད་ལྟ་བ། ཐ་མི་དད་པ།】【〈སྐྱེ〉གི་ མ་འོངས་པ། ཐ་མི་དད་པ།】"
                        ],
                        {
                            "པེ་": [
                                " །_། གོ་བ ར་ བྱེད་ ཀྱི་",
                                "སྐྱེས་",
                                "སེལ་ མིན །_། #སྨིག་ རྒྱུ་"
                            ],
                            "སྡེ་": [
                                " །_། གོ་བ ར་ བྱེད་ ཀྱི་",
                                "སྐྱེ་",
                                "སེལ་ མིན །_། #སྨིག་ རྒྱུ་"
                            ],
                            "སྣར་": [
                                " །_། གོ་བ ར་ བྱེད་ ཀྱི་",
                                "སྐྱེས་",
                                "སེལ་ མིན །_། #སྨིག་ རྒྱུ་"
                            ]
                        }
                    ]
                }
            ],
            "diff_verb": [
                {
                    "12": [
                        [
                            "《འཕྱི》ཞེས་པ།【〈འཕྱི〉གི་ ད་ལྟ་བ། ཐ་མི་དད་པ།】【〈འཕྱི〉གི་ མ་འོངས་པ། ཐ་མི་དད་པ།】",
                            "《ཕྱི》ཞེས་པ།【〈འབྱིད〉གི་ འདས་པ།】【〈འབྱིད〉གི་ འདས་པ། ཐ་དད་པ།】"
                        ],
                        {
                            "པེ་": [
                                "འགྱུར་ ཞིང་  །_། དགག་ བྱ་",
                                "འཕྱི་",
                                "ཞེས་ འཐད་ མིན་ ལ །_། "
                            ],
                            "སྡེ་": [
                                "འགྱུར་ ཞིང་  །_། དགག་ བྱ་",
                                "ཕྱི་",
                                "ཞེས་ འཐད་ མིན་ ལ །_། "
                            ],
                            "སྣར་": [
                                "འགྱུར་ ཞིང་  །_། དགག་ བྱ་",
                                "འཕྱི་",
                                "ཞེས་ འཐད་ མིན་ ལ །_། "
                            ]
                        }
                    ]
                },
                {
                    "15": [
                        [
                            "《རྟེན》ཞེས་པ།【〈བརྟེན〉གི་ ད་ལྟ་བ། ཐ་དད་པ།】【〈བརྟེན〉གི་ སྐུལ་ཚིག ཐ་དད་པ།】【〈རྟེན〉གི་ ད་ལྟ་བ། ཐ་མི་དད་པ།】【〈རྟེན〉གི་ སྐུལ་ཚིག ཐ་མི་དད་པ།】",
                            "《བརྟེན》ཞེས་པ།【〈བརྟེན〉གི་ མ་འོངས་པ། ཐ་དད་པ།】【〈བརྟེན〉གི་ འདས་པ། ཐ་དད་པ།】【〈རྟེན〉གི་ མ་འོངས་པ། ཐ་མི་དད་པ།】【〈རྟེན〉གི་ འདས་པ། ཐ་མི་དད་པ།】"
                        ],
                        {
                            "པེ་": [
                                "བརྗོད་ དེ །_། གང་ཞིག་",
                                "བརྟེན་",
                                "ནས་ འབྱུང་བ་ དེ །_། "
                            ],
                            "སྡེ་": [
                                "བརྗོད་ དེ །_། གང་ཞིག་",
                                "རྟེན་",
                                "ནས་ འབྱུང་བ་ དེ །_། "
                            ],
                            "སྣར་": [
                                "བརྗོད་ དེ །_། གང་ཞིག་",
                                "བརྟེན་",
                                "ནས་ འབྱུང་བ་ དེ །_། "
                            ]
                        }
                    ]
                },
                {
                    "23": [
                        [
                            "《སྒྲུབ》ཞེས་པ།【〈སྒྲུབ〉གི་ ད་ལྟ་བ།】【〈སྒྲུབ〉གི་ ད་ལྟ་བ། ཐ་དད་པ།】",
                            "《གྲུབ》ཞེས་པ།【〈འགྲུབ〉གི་ འདས་པ། ཐ་མི་དད་པ།】"
                        ],
                        {
                            "པེ་": [
                                "པ ར་ ཡང་  །_། དེ་ རྣམས་",
                                "སྒྲུབ་",
                                "ན་ སྨྲ་བ་ ཉམས །_། "
                            ],
                            "སྡེ་": [
                                "པ ར་ ཡང་  །_། དེ་ རྣམས་",
                                "གྲུབ་",
                                "ན་ སྨྲ་བ་ ཉམས །_། "
                            ],
                            "སྣར་": [
                                "པ ར་ ཡང་  །_། དེ་ རྣམས་",
                                "སྒྲུབ་",
                                "ན་ སྨྲ་བ་ ཉམས །_། "
                            ]
                        }
                    ]
                },
                {
                    "52": [
                        [
                            "《རྟེན》ཞེས་པ།【〈བརྟེན〉གི་ ད་ལྟ་བ། ཐ་དད་པ།】【〈བརྟེན〉གི་ སྐུལ་ཚིག ཐ་དད་པ།】【〈རྟེན〉གི་ ད་ལྟ་བ། ཐ་མི་དད་པ།】【〈རྟེན〉གི་ སྐུལ་ཚིག ཐ་མི་དད་པ།】",
                            "《བརྟེན》ཞེས་པ།【〈བརྟེན〉གི་ མ་འོངས་པ། ཐ་དད་པ།】【〈བརྟེན〉གི་ འདས་པ། ཐ་དད་པ།】【〈རྟེན〉གི་ མ་འོངས་པ། ཐ་མི་དད་པ།】【〈རྟེན〉གི་ འདས་པ། ཐ་མི་དད་པ།】"
                        ],
                        {
                            "པེ་": [
                                "དེ་ རང་བཞིན་ ཡོད །_།",
                                "རྟེན་",
                                "ནས་ འབྱུང་བ ར་ མི་ འགྱུར་"
                            ],
                            "སྡེ་": [
                                "དེ་ རང་བཞིན་ ཡོད །_།",
                                "བརྟེན་",
                                "ནས་ འབྱུང་བ ར་ མི་ འགྱུར་"
                            ],
                            "སྣར་": [
                                "དེ་ རང་བཞིན་ ཡོད །_།",
                                "བརྟེན་",
                                "ནས་ འབྱུང་བ ར་ མི་ འགྱུར་"
                            ]
                        }
                    ]
                }
            ],
            "not_sure": []
        }
    },
    "dunno": {
        "long_diff": [],
        "no_diff": [
            {
                "4": [
                    {
                        "པེ་": [
                            " །_། རྗེས་ དཔག་ ལུང་ དང་",
                            "ཉེར་",
                            "འཇལ་ དང་  །_། རྗེས་ དཔག་"
                        ],
                        "སྡེ་": [
                            " །_། རྗེས་ དཔག་ ལུང་ དང་",
                            "དཔེ ར་",
                            "འཇལ་ དང་  །_། རྗེས་ དཔག་"
                        ],
                        "སྣར་": [
                            " །_། རྗེས་ དཔག་ ལུང་ དང་",
                            "ཉེར་",
                            "འཇལ་ དང་  །_། རྗེས་ དཔག་"
                        ]
                    }
                ]
            },
            {
                "6": [
                    {
                        "པེ་": [
                            "བཞིན་ མེད་ ཅེས་བྱ་བ་",
                            "ཡི",
                            "།_། མིང་ ཡང་ དེ་ བཞིན་"
                        ],
                        "སྡེ་": [
                            "བཞིན་ མེད་ ཅེས་བྱ་བ་",
                            "ཡིན",
                            "།_། མིང་ ཡང་ དེ་ བཞིན་"
                        ],
                        "སྣར་": [
                            "བཞིན་ མེད་ ཅེས་བྱ་བ་",
                            "ཡི",
                            "།_། མིང་ ཡང་ དེ་ བཞིན་"
                        ]
                    }
                ]
            },
            {
                "10": [
                    {
                        "པེ་": [
                            "ཕྱིར་ ཁྱོད་ ཀྱི་ རྟགས །_།",
                            "ག་ ལ་",
                            "ཡོད་ དེ་ ཁྱོད་ དོན་ དེ"
                        ],
                        "སྡེ་": [
                            "ཕྱིར་ ཁྱོད་ ཀྱི་ རྟགས །_།",
                            "གལ་ཏེ་",
                            "ཡོད་ དེ་ ཁྱོད་ དོན་ དེ"
                        ],
                        "སྣར་": [
                            "ཕྱིར་ ཁྱོད་ ཀྱི་ རྟགས །_།",
                            "ག་ ལ་",
                            "ཡོད་ དེ་ ཁྱོད་ དོན་ དེ"
                        ]
                    }
                ]
            },
            {
                "13": [
                    {
                        "པེ་": [
                            "ཡང་ མི་ འཐད །_།",
                            "ང་ ཡི་ ཚིག་ ནི་",
                            "རྒྱུ་ རྐྱེན་ དང་  །_། ཚོགས་"
                        ],
                        "སྡེ་": [
                            "ཡང་ མི་ འཐད །_།",
                            "གལ་ཏེ་ ང འི་ ཚིག་",
                            "རྒྱུ་ རྐྱེན་ དང་  །_། ཚོགས་"
                        ],
                        "སྣར་": [
                            "ཡང་ མི་ འཐད །_།",
                            "ང་ ཡི་ ཚིག་ ནི་",
                            "རྒྱུ་ རྐྱེན་ དང་  །_། ཚོགས་"
                        ]
                    }
                ]
            },
            {
                "14": [
                    {
                        "པེ་": [
                            "ཉིད་ ཕྱིར་ རོ །_། རྟེན་",
                            "ནས་",
                            "འབྱུང་བ འི་ དངོས་ རྣམས་ གང་"
                        ],
                        "སྡེ་": [
                            "ཉིད་ ཕྱིར་ རོ །_། རྟེན་",
                            "རྣམས་",
                            "འབྱུང་བ འི་ དངོས་ རྣམས་ གང་"
                        ],
                        "སྣར་": [
                            "ཉིད་ ཕྱིར་ རོ །_། རྟེན་",
                            "ནས་",
                            "འབྱུང་བ འི་ དངོས་ རྣམས་ གང་"
                        ]
                    }
                ]
            },
            {
                "16": [
                    {
                        "པེ་": [
                            "འགྱུར །_། ང་ ཡི་ ཚིག་",
                            "ནི་ དེ་ བཞིན་",
                            "མེད །_། དེ་ ཕྱིར་"
                        ],
                        "སྡེ་": [
                            "འགྱུར །_། ང་ ཡི་ ཚིག་",
                            "དེ་ རང་བཞིན་",
                            "མེད །_། དེ་ ཕྱིར་"
                        ],
                        "སྣར་": [
                            "འགྱུར །_། ང་ ཡི་ ཚིག་",
                            "ནི་ དེ་ བཞིན་",
                            "མེད །_། དེ་ ཕྱིར་"
                        ]
                    }
                ]
            },
            {
                "17": [
                    {
                        "པེ་": [
                            "མེད །_། དེ་ ཕྱིར་ ང་",
                            "ཕྱོགས་ མ་ ཉམས་",
                            "ལ །_། མི་ འདྲ་ ཉིད་"
                        ],
                        "སྡེ་": [
                            "མེད །_། དེ་ ཕྱིར་ ང་",
                            "ཡི་ ཕྱོགས་ མཉམ་",
                            "ལ །_། མི་ འདྲ་ ཉིད་"
                        ],
                        "སྣར་": [
                            "མེད །_། དེ་ ཕྱིར་ ང་",
                            "ཕྱོགས་ མ་ ཉམས་",
                            "ལ །_། མི་ འདྲ་ ཉིད་"
                        ]
                    }
                ]
            },
            {
                "18": [
                    {
                        "པེ་": [
                            "བརྗོད་ མི་ བྱ །_། སྒྲ་",
                            "མི་",
                            "འབྱིན་ བྱ་ བཞིན་ ཞེ་ན"
                        ],
                        "སྡེ་": [
                            "བརྗོད་ མི་ བྱ །_། སྒྲ་",
                            "མ་",
                            "འབྱིན་ བྱ་ བཞིན་ ཞེ་ན"
                        ],
                        "སྣར་": [
                            "བརྗོད་ མི་ བྱ །_། སྒྲ་",
                            "མི་",
                            "འབྱིན་ བྱ་ བཞིན་ ཞེ་ན"
                        ]
                    }
                ]
            },
            {
                "21": [
                    {
                        "པེ་": [
                            "རྣམས །_། ཚད་མ་ ཉིད་",
                            "ཀྱི་ རབ་ བསྒྲུབ་",
                            "ན །_། ཁྱོད་ ཀྱིས་ ཚད་"
                        ],
                        "སྡེ་": [
                            "རྣམས །_། ཚད་མ་ ཉིད་",
                            "ཀྱིས་ རབ་ བསྒྲུབས་",
                            "ན །_། ཁྱོད་ ཀྱིས་ ཚད་"
                        ],
                        "སྣར་": [
                            "རྣམས །_། ཚད་མ་ ཉིད་",
                            "ཀྱི་ རབ་ བསྒྲུབ་",
                            "ན །_། ཁྱོད་ ཀྱིས་ ཚད་"
                        ]
                    }
                ]
            },
            {
                "24": [
                    {
                        "པེ་": [
                            " །_། དེ་ ལ་ མི་ དམིགས་",
                            "མཐོང་བ ས་ ན",
                            "།_། མེ་ ནི་ རང་ཉིད་"
                        ],
                        "སྡེ་": [
                            " །_། དེ་ ལ་ མི་ དམིགས་",
                            "མ་ མཐོང་བ ས",
                            "།_། མེ་ ནི་ རང་ཉིད་"
                        ],
                        "སྣར་": [
                            " །_། དེ་ ལ་ མི་ དམིགས་",
                            "མ་ མཐོང་བ ས",
                            "།_། མེ་ ནི་ རང་ཉིད་"
                        ]
                    }
                ]
            },
            {
                "28": [
                    {
                        "པེ་": [
                            "པ་ ཡིན །_། གལ་ཏེ་",
                            "ཡོངས་",
                            "#ཡེ་ གཞལ་ བྱ་ ལ །_། "
                        ],
                        "སྡེ་": [
                            "པ་ ཡིན །_། གལ་ཏེ་",
                            "ཡོང་",
                            "#ཡེ་ གཞལ་ བྱ་ ལ །_། "
                        ],
                        "སྣར་": [
                            "པ་ ཡིན །_། གལ་ཏེ་",
                            "ཡོངས་",
                            "#ཡེ་ གཞལ་ བྱ་ ལ །_། "
                        ]
                    }
                ]
            },
            {
                "31": [
                    {
                        "པེ་": [
                            "མ་ ལྟོས་པ ར །_། གཞལ་",
                            "བྱ ར་",
                            "བྱ་བ་ འགྲུབ་པ ར་ འགྱུར"
                        ],
                        "སྡེ་": [
                            "མ་ ལྟོས་པ ར །_། གཞལ་",
                            "བར་",
                            "བྱ་བ་ འགྲུབ་པ ར་ འགྱུར"
                        ],
                        "སྣར་": [
                            "མ་ ལྟོས་པ ར །_། གཞལ་",
                            "བྱ ར་",
                            "བྱ་བ་ འགྲུབ་པ ར་ འགྱུར"
                        ]
                    }
                ]
            },
            {
                "37": [
                    {
                        "པེ་": [
                            "ཚད་མ་",
                            "དེ་ རྣམས་ སྒྲུབ་",
                            "ཀྱིས་ ཀྱང་  །_། དེ་དག་"
                        ],
                        "སྡེ་": [
                            "ཚད་མ་",
                            "དེ་དག་ རྣམས་",
                            "ཀྱིས་ ཀྱང་  །_། དེ་དག་"
                        ],
                        "སྣར་": [
                            "ཚད་མ་",
                            "དེ་དག་ རྣམས་",
                            "ཀྱིས་ ཀྱང་  །_། དེ་དག་"
                        ]
                    }
                ]
            },
            {
                "40": [
                    {
                        "པེ་": [
                            "ན་ གང་ གིས་ གང་ བསྐྱེད་",
                            "སྨོས",
                            "།_། དེ་དག་ གཉིས་ཀ འང་"
                        ],
                        "སྡེ་": [
                            "ན་ གང་ གིས་ གང་ བསྐྱེད་",
                            "སྨྲོས",
                            "།_། དེ་དག་ གཉིས་ཀ འང་"
                        ],
                        "སྣར་": [
                            "ན་ གང་ གིས་ གང་ བསྐྱེད་",
                            "སྨོས",
                            "།_། དེ་དག་ གཉིས་ཀ འང་"
                        ]
                    }
                ]
            },
            {
                "42": [
                    {
                        "པེ་": [
                            "སྨྲོས །_། ཚད་མ་ རྣམས་",
                            "ཀྱི་",
                            "རང་ཉིད་ ཀྱིས །_། འགྲུབ་"
                        ],
                        "སྡེ་": [
                            "སྨྲོས །_། ཚད་མ་ རྣམས་",
                            "ནི་",
                            "རང་ཉིད་ ཀྱིས །_། འགྲུབ་"
                        ],
                        "སྣར་": [
                            "སྨྲོས །_། ཚད་མ་ རྣམས་",
                            "ཀྱི་",
                            "རང་ཉིད་ ཀྱིས །_། འགྲུབ་"
                        ]
                    }
                ]
            },
            {
                "44": [
                    {
                        "པེ་": [
                            "རྣམས་ ཀྱི །_། དགེ་བ འི་",
                            "རང་བཞིན་ ཆོས་ རྣམས་",
                            "གང་  །_། དེ་ལྟར་ རབ་"
                        ],
                        "སྡེ་": [
                            "རྣམས་ ཀྱི །_། དགེ་བ འི་",
                            "ཆོས་ རྣམས་ རང་བཞིན་",
                            "གང་  །_། དེ་ལྟར་ རབ་"
                        ],
                        "སྣར་": [
                            "རྣམས་ ཀྱི །_། དགེ་བ འི་",
                            "རང་བཞིན་ ཆོས་ རྣམས་",
                            "གང་  །_། དེ་ལྟར་ རབ་"
                        ]
                    }
                ]
            },
            {
                "46": [
                    {
                        "པེ་": [
                            " །_། ཆོས་ རྣམས་ ཐམས་ཅད་",
                            "བརྟག་པ ར་",
                            "འགྱུར །_། ཆོས་ དང་"
                        ],
                        "སྡེ་": [
                            " །_། ཆོས་ རྣམས་ ཐམས་ཅད་",
                            "རྟག་པ ར་",
                            "འགྱུར །_། ཆོས་ དང་"
                        ],
                        "སྣར་": [
                            " །_། ཆོས་ རྣམས་ ཐམས་ཅད་",
                            "བརྟག་པ ར་",
                            "འགྱུར །_། ཆོས་ དང་"
                        ]
                    }
                ]
            },
            {
                "47": [
                    {
                        "པེ་": [
                            "བཞིན་ བཅས་པ་ ཞེས །_།",
                            "མིང་ ནི་",
                            "ཡོད་པ ར་ སྨྲ་བ་ ལ"
                        ],
                        "སྡེ་": [
                            "བཞིན་ བཅས་པ་ ཞེས །_།",
                            "མི་ དེ་",
                            "ཡོད་པ ར་ སྨྲ་བ་ ལ"
                        ],
                        "སྣར་": [
                            "བཞིན་ བཅས་པ་ ཞེས །_།",
                            "མིང་ ནི་",
                            "ཡོད་པ ར་ སྨྲ་བ་ ལ"
                        ]
                    }
                ]
            },
            {
                "53": [
                    {
                        "པེ་": [
                            "བཟློག་ བསྒྲུབ་པ འི་ ཚེ །_།",
                            "སྨྲས་ གང་ ཡིན་པ་",
                            "དེ་ དང་ ནི །_།"
                        ],
                        "སྡེ་": [
                            "བཟློག་ བསྒྲུབ་པ འི་ ཚེ །_།",
                            "སྔར་ སྨྲས་ གང་ ཡིན་",
                            "དེ་ དང་ ནི །_།"
                        ],
                        "སྣར་": [
                            "བཟློག་ བསྒྲུབ་པ འི་ ཚེ །_།",
                            "སྔར་ སྨྲས་ གང་ ཡིན་",
                            "དེ་ དང་ ནི །_།"
                        ]
                    }
                ]
            },
            {
                "54": [
                    {
                        "པེ་": [
                            "གསུམ་ གཏན་ ཚིགས་ གང་",
                            "ཡིན་པ",
                            "།_། ལན་ བཏབ་ ཉིད་ དུ་"
                        ],
                        "སྡེ་": [
                            "གསུམ་ གཏན་ ཚིགས་ གང་",
                            "ཡིན་ སྔར",
                            "།_། ལན་ བཏབ་ ཉིད་ དུ་"
                        ],
                        "སྣར་": [
                            "གསུམ་ གཏན་ ཚིགས་ གང་",
                            "ཡིན་ སྔར",
                            "།_། ལན་ བཏབ་ ཉིད་ དུ་"
                        ]
                    }
                ]
            },
            {
                "55": [
                    {
                        "པེ་": [
                            "ཕྱིར་ རོ །_། དུས་ གསུམ་",
                            "མེད་",
                            "ཀྱི་ གཏན་ ཚིགས་ ནི །_། "
                        ],
                        "སྡེ་": [
                            "ཕྱིར་ རོ །_། དུས་ གསུམ་",
                            "ཆེད་",
                            "ཀྱི་ གཏན་ ཚིགས་ ནི །_། "
                        ],
                        "སྣར་": [
                            "ཕྱིར་ རོ །_། དུས་ གསུམ་",
                            "ཆེད་",
                            "ཀྱི་ གཏན་ ཚིགས་ ནི །_། "
                        ]
                    }
                ]
            }
        ],
        "short_diff": []
    },
    "empty_notes": [
        {
            "61": [
                {
                    "པེ་": [
                        "དཔལ་ གྱིས་ བསྒྱུར་བ འོ །།__།། ",
                        "",
                        "དཔལ་ གྱིས་ བསྒྱུར་བ འོ །།__།། "
                    ],
                    "སྡེ་": [
                        "དཔལ་ གྱིས་ བསྒྱུར་བ འོ །།__།། ",
                        "",
                        "དཔལ་ གྱིས་ བསྒྱུར་བ འོ །།__།། "
                    ],
                    "སྣར་": [
                        "དཔལ་ གྱིས་ བསྒྱུར་བ འོ །།__།། ",
                        "",
                        "དཔལ་ གྱིས་ བསྒྱུར་བ འོ །།__།། "
                    ]
                }
            ]
        }
    ],
    "manual_categorisation": {
        "long_difference": {
            "differing_formulation": [],
            "major_modification": []
        },
        "manual_evaluation": {
            "derge_correct": [],
            "meaning_difference": {
                "great_diff": [],
                "medium_diff": [],
                "small_diff": []
            }
        }
    },
    "ngram_freq": {
        "1": {
            "པེ་": [],
            "སྡེ་": [],
            "སྣར་": []
        },
        "10": {
            "པེ་": [
                [
                    "ག་ལ",
                    "60"
                ],
                [
                    "ག་ལ་ཡོད",
                    "231"
                ]
            ],
            "སྡེ་": [
                [
                    "གལ་ཏེ",
                    "17205"
                ],
                [
                    "།_།གལ་ཏེ",
                    "6176"
                ]
            ],
            "སྣར་": [
                [
                    "ག་ལ",
                    "60"
                ],
                [
                    "ག་ལ་ཡོད",
                    "231"
                ]
            ]
        },
        "11": {
            "པེ་": [
                [
                    "ལས",
                    "5885"
                ],
                [
                    "གང་ལས",
                    "600"
                ]
            ],
            "སྡེ་": [
                [
                    "ལ",
                    "33965"
                ],
                [
                    "གང་ལ",
                    "85"
                ],
                [
                    "ལ་རང་བཞིན",
                    "813"
                ],
                [
                    "གང་ལ་རང་བཞིན",
                    "239"
                ],
                [
                    "།_།གང་ལ་རང་བཞིན",
                    "104"
                ]
            ],
            "སྣར་": [
                [
                    "ལས",
                    "5885"
                ],
                [
                    "གང་ལས",
                    "600"
                ]
            ]
        },
        "12": {
            "པེ་": [
                [
                    "འཕྱི",
                    "5"
                ]
            ],
            "སྡེ་": [
                [
                    "ཕྱི",
                    "6"
                ]
            ],
            "སྣར་": [
                [
                    "འཕྱི",
                    "5"
                ]
            ]
        },
        "13": {
            "པེ་": [],
            "སྡེ་": [],
            "སྣར་": []
        },
        "14": {
            "པེ་": [
                [
                    "ནས",
                    "35333"
                ],
                [
                    "རྟེན་ནས",
                    "113"
                ],
                [
                    "ནས་འབྱུང་བ",
                    "300"
                ]
            ],
            "སྡེ་": [
                [
                    "རྣམས",
                    "5469"
                ],
                [
                    "རྟེན་རྣམས",
                    "331"
                ],
                [
                    "རྣམས་འབྱུང་བ",
                    "135"
                ]
            ],
            "སྣར་": [
                [
                    "ནས",
                    "35333"
                ],
                [
                    "རྟེན་ནས",
                    "113"
                ],
                [
                    "ནས་འབྱུང་བ",
                    "300"
                ]
            ]
        },
        "15": {
            "པེ་": [
                [
                    "བརྟེན",
                    "256"
                ],
                [
                    "བརྟེན་ནས",
                    "1090"
                ]
            ],
            "སྡེ་": [
                [
                    "རྟེན",
                    "218"
                ],
                [
                    "རྟེན་ནས",
                    "113"
                ]
            ],
            "སྣར་": [
                [
                    "བརྟེན",
                    "256"
                ],
                [
                    "བརྟེན་ནས",
                    "1090"
                ]
            ]
        },
        "16": {
            "པེ་": [
                [
                    "ནི་དེ་བཞིན",
                    "4241"
                ]
            ],
            "སྡེ་": [
                [
                    "དེ་རང་བཞིན",
                    "70"
                ]
            ],
            "སྣར་": [
                [
                    "ནི་དེ་བཞིན",
                    "4241"
                ]
            ]
        },
        "17": {
            "པེ་": [],
            "སྡེ་": [],
            "སྣར་": []
        },
        "18": {
            "པེ་": [
                [
                    "མི",
                    "406"
                ],
                [
                    "སྒྲ་མི",
                    "460"
                ],
                [
                    "མི་འབྱིན",
                    "85"
                ]
            ],
            "སྡེ་": [
                [
                    "མ",
                    "4286"
                ],
                [
                    "སྒྲ་མ",
                    "119"
                ]
            ],
            "སྣར་": [
                [
                    "མི",
                    "406"
                ],
                [
                    "སྒྲ་མི",
                    "460"
                ],
                [
                    "མི་འབྱིན",
                    "85"
                ]
            ]
        },
        "19": {
            "པེ་": [
                [
                    "གྲུབ",
                    "316"
                ],
                [
                    "རབ་གྲུབ",
                    "71"
                ],
                [
                    "གྲུབ་འགྱུར",
                    "94"
                ]
            ],
            "སྡེ་": [
                [
                    "འགྲུབ",
                    "916"
                ],
                [
                    "འགྲུབ་འགྱུར",
                    "94"
                ]
            ],
            "སྣར་": [
                [
                    "གྲུབ",
                    "316"
                ],
                [
                    "རབ་གྲུབ",
                    "71"
                ],
                [
                    "གྲུབ་འགྱུར",
                    "94"
                ]
            ]
        },
        "2": {
            "པེ་": [
                [
                    "གྱི",
                    "3024"
                ],
                [
                    "གྱི།_།",
                    "1099"
                ]
            ],
            "སྡེ་": [
                [
                    "གྱིས",
                    "7492"
                ],
                [
                    "གྱིས།_།",
                    "3730"
                ]
            ],
            "སྣར་": [
                [
                    "གྱི",
                    "3024"
                ],
                [
                    "གྱི།_།",
                    "1099"
                ]
            ]
        },
        "20": {
            "པེ་": [
                [
                    "ཡི",
                    "8322"
                ],
                [
                    "ཡི།_།",
                    "8252"
                ]
            ],
            "སྡེ་": [
                [
                    "ཡིས",
                    "7433"
                ],
                [
                    "ཡིས།_།",
                    "7321"
                ]
            ],
            "སྣར་": [
                [
                    "ཡི",
                    "8322"
                ],
                [
                    "ཡི།_།",
                    "8252"
                ]
            ]
        },
        "21": {
            "པེ་": [],
            "སྡེ་": [],
            "སྣར་": []
        },
        "22": {
            "པེ་": [
                [
                    "ཀྱི",
                    "5256"
                ],
                [
                    "ཁྱོད་ཀྱི",
                    "3668"
                ]
            ],
            "སྡེ་": [
                [
                    "ཀྱིས",
                    "6156"
                ],
                [
                    "ཁྱོད་ཀྱིས",
                    "55"
                ]
            ],
            "སྣར་": [
                [
                    "ཀྱི",
                    "5256"
                ],
                [
                    "ཁྱོད་ཀྱི",
                    "3668"
                ]
            ]
        },
        "23": {
            "པེ་": [
                [
                    "སྒྲུབ",
                    "176"
                ],
                [
                    "རྣམས་སྒྲུབ",
                    "122"
                ]
            ],
            "སྡེ་": [
                [
                    "གྲུབ",
                    "316"
                ],
                [
                    "གྲུབ་ན",
                    "428"
                ],
                [
                    "རྣམས་གྲུབ",
                    "118"
                ]
            ],
            "སྣར་": [
                [
                    "སྒྲུབ",
                    "176"
                ],
                [
                    "རྣམས་སྒྲུབ",
                    "122"
                ]
            ]
        },
        "24": {
            "པེ་": [
                [
                    "མཐོང་བས་ན",
                    "60"
                ],
                [
                    "མཐོང་བས་ན།_།",
                    "48"
                ]
            ],
            "སྡེ་": [
                [
                    "མ་མཐོང་བས",
                    "209"
                ]
            ],
            "སྣར་": [
                [
                    "མ་མཐོང་བས",
                    "209"
                ]
            ]
        },
        "25": {
            "པེ་": [
                [
                    "ཀྱིས",
                    "6156"
                ],
                [
                    "ཀྱིས་ཚིག",
                    "136"
                ],
                [
                    "ཁྱོད་ཀྱིས",
                    "55"
                ]
            ],
            "སྡེ་": [
                [
                    "ཀྱི",
                    "5256"
                ],
                [
                    "ཀྱི་ཚིག",
                    "1461"
                ],
                [
                    "ཁྱོད་ཀྱི",
                    "3668"
                ]
            ],
            "སྣར་": [
                [
                    "ཀྱིས",
                    "6156"
                ],
                [
                    "ཀྱིས་ཚིག",
                    "136"
                ],
                [
                    "ཁྱོད་ཀྱིས",
                    "55"
                ]
            ]
        },
        "26": {
            "པེ་": [
                [
                    "ལས",
                    "5885"
                ],
                [
                    "ལས་མ",
                    "1189"
                ],
                [
                    "རྣམས་ལས",
                    "2222"
                ]
            ],
            "སྡེ་": [
                [
                    "ལ",
                    "33965"
                ],
                [
                    "ལ་མ",
                    "3490"
                ],
                [
                    "རྣམས་ལ",
                    "895"
                ],
                [
                    "རྣམས་ལ་མ",
                    "183"
                ]
            ],
            "སྣར་": [
                [
                    "ལས",
                    "5885"
                ],
                [
                    "ལས་མ",
                    "1189"
                ],
                [
                    "རྣམས་ལས",
                    "2222"
                ]
            ]
        },
        "27": {
            "པེ་": [
                [
                    "ལས",
                    "5885"
                ],
                [
                    "གཞན་ལས",
                    "268"
                ]
            ],
            "སྡེ་": [
                [
                    "ལ",
                    "33965"
                ],
                [
                    "གཞན་ལ",
                    "773"
                ],
                [
                    "ལ་ལྟོས",
                    "367"
                ]
            ],
            "སྣར་": [
                [
                    "ལས",
                    "5885"
                ],
                [
                    "གཞན་ལས",
                    "268"
                ]
            ]
        },
        "28": {
            "པེ་": [
                [
                    "ཡོངས",
                    "82397"
                ]
            ],
            "སྡེ་": [
                [
                    "ཡོང",
                    "650"
                ]
            ],
            "སྣར་": [
                [
                    "ཡོངས",
                    "82397"
                ]
            ]
        },
        "29": {
            "པེ་": [
                [
                    "ལས",
                    "5885"
                ],
                [
                    "ལས།_།",
                    "3638"
                ]
            ],
            "སྡེ་": [
                [
                    "ལ",
                    "33965"
                ],
                [
                    "ལ།_།",
                    "14361"
                ],
                [
                    "བྱ་ལ",
                    "114"
                ]
            ],
            "སྣར་": [
                [
                    "ལས",
                    "5885"
                ],
                [
                    "ལས།_།",
                    "3638"
                ]
            ]
        },
        "3": {
            "པེ་": [
                [
                    "བཟློག",
                    "194"
                ]
            ],
            "སྡེ་": [
                [
                    "ཟློག",
                    "34"
                ]
            ],
            "སྣར་": [
                [
                    "བཟློག",
                    "194"
                ]
            ]
        },
        "30": {
            "པེ་": [
                [
                    "གྲུབ",
                    "316"
                ]
            ],
            "སྡེ་": [
                [
                    "འགྲུབ",
                    "916"
                ]
            ],
            "སྣར་": [
                [
                    "འགྲུབ",
                    "916"
                ]
            ]
        },
        "31": {
            "པེ་": [
                [
                    "བྱར",
                    "3"
                ]
            ],
            "སྡེ་": [
                [
                    "བར",
                    "1385"
                ],
                [
                    "གཞལ་བར",
                    "62"
                ],
                [
                    "བར་བྱ་བ",
                    "2838"
                ]
            ],
            "སྣར་": [
                [
                    "བྱར",
                    "3"
                ]
            ]
        },
        "32": {
            "པེ་": [
                [
                    "གྲུབ་པས",
                    "44"
                ]
            ],
            "སྡེ་": [],
            "སྣར་": [
                [
                    "གྲུབ་པས",
                    "44"
                ]
            ]
        },
        "33": {
            "པེ་": [
                [
                    "ཀྱི",
                    "5256"
                ],
                [
                    "ཀྱི་ཚད",
                    "338"
                ],
                [
                    "ཁྱོད་ཀྱི",
                    "3668"
                ]
            ],
            "སྡེ་": [
                [
                    "ཀྱིས",
                    "6156"
                ],
                [
                    "ཀྱིས་ཚད",
                    "46"
                ],
                [
                    "ཁྱོད་ཀྱིས",
                    "55"
                ]
            ],
            "སྣར་": [
                [
                    "ཀྱི",
                    "5256"
                ],
                [
                    "ཀྱི་ཚད",
                    "338"
                ],
                [
                    "ཁྱོད་ཀྱི",
                    "3668"
                ]
            ]
        },
        "34": {
            "པེ་": [
                [
                    "སྒྲུབ",
                    "176"
                ]
            ],
            "སྡེ་": [
                [
                    "བསྒྲུབས",
                    "107"
                ],
                [
                    "བསྒྲུབས་ན",
                    "170"
                ]
            ],
            "སྣར་": [
                [
                    "བསྒྲུབས",
                    "107"
                ],
                [
                    "བསྒྲུབས་ན",
                    "170"
                ]
            ]
        },
        "35": {
            "པེ་": [
                [
                    "སྒྲུབ་པར",
                    "1384"
                ],
                [
                    "སྒྲུབ་པར་འགྱུར",
                    "112"
                ]
            ],
            "སྡེ་": [
                [
                    "བསྒྲུབ་པར",
                    "3518"
                ],
                [
                    "བསྒྲུབ་པར་འགྱུར",
                    "48"
                ],
                [
                    "ཇི་ལྟར་བསྒྲུབ་པར",
                    "137"
                ]
            ],
            "སྣར་": [
                [
                    "སྒྲུབ་པར",
                    "1384"
                ],
                [
                    "སྒྲུབ་པར་འགྱུར",
                    "112"
                ]
            ]
        },
        "36": {
            "པེ་": [
                [
                    "འགྲུབ",
                    "916"
                ],
                [
                    "འགྲུབ།_།",
                    "895"
                ]
            ],
            "སྡེ་": [
                [
                    "གྲུབ",
                    "316"
                ],
                [
                    "གྲུབ།_།",
                    "289"
                ]
            ],
            "སྣར་": [
                [
                    "འགྲུབ",
                    "916"
                ],
                [
                    "འགྲུབ།_།",
                    "895"
                ]
            ]
        },
        "37": {
            "པེ་": [],
            "སྡེ་": [
                [
                    "དེ་དག་རྣམས",
                    "2383"
                ],
                [
                    "དེ་དག་རྣམས་ཀྱིས",
                    "270"
                ]
            ],
            "སྣར་": [
                [
                    "དེ་དག་རྣམས",
                    "2383"
                ],
                [
                    "དེ་དག་རྣམས་ཀྱིས",
                    "270"
                ]
            ]
        },
        "38": {
            "པེ་": [
                [
                    "སྒྲུབ་པར",
                    "1384"
                ]
            ],
            "སྡེ་": [
                [
                    "བསྒྲུབ་པར",
                    "3518"
                ],
                [
                    "བསྒྲུབ་པར་བྱ",
                    "399"
                ]
            ],
            "སྣར་": [
                [
                    "སྒྲུབ་པར",
                    "1384"
                ]
            ]
        },
        "39": {
            "པེ་": [
                [
                    "སྒྲུབ་པར",
                    "1384"
                ],
                [
                    "སྒྲུབ་པར་འགྱུར",
                    "112"
                ]
            ],
            "སྡེ་": [
                [
                    "བསྒྲུབ་པར",
                    "3518"
                ],
                [
                    "བསྒྲུབ་པར་འགྱུར",
                    "48"
                ],
                [
                    "ཇི་ལྟར་བསྒྲུབ་པར",
                    "137"
                ]
            ],
            "སྣར་": [
                [
                    "སྒྲུབ་པར",
                    "1384"
                ],
                [
                    "སྒྲུབ་པར་འགྱུར",
                    "112"
                ]
            ]
        },
        "4": {
            "པེ་": [
                [
                    "ཉེར",
                    "730"
                ]
            ],
            "སྡེ་": [
                [
                    "དཔེར",
                    "5"
                ]
            ],
            "སྣར་": [
                [
                    "ཉེར",
                    "730"
                ]
            ]
        },
        "40": {
            "པེ་": [
                [
                    "སྨོས",
                    "946"
                ],
                [
                    "སྨོས།_།",
                    "94"
                ]
            ],
            "སྡེ་": [
                [
                    "སྨྲོས",
                    "79"
                ],
                [
                    "སྨྲོས།_།",
                    "76"
                ]
            ],
            "སྣར་": [
                [
                    "སྨོས",
                    "946"
                ],
                [
                    "སྨོས།_།",
                    "94"
                ]
            ]
        },
        "41": {
            "པེ་": [
                [
                    "འགྱུར",
                    "31151"
                ],
                [
                    "འགྱུར།_།",
                    "18273"
                ]
            ],
            "སྡེ་": [
                [
                    "གྱུར",
                    "4361"
                ],
                [
                    "གྱུར།_།",
                    "2615"
                ]
            ],
            "སྣར་": [
                [
                    "གྱུར",
                    "4361"
                ],
                [
                    "གྱུར།_།",
                    "2615"
                ]
            ]
        },
        "42": {
            "པེ་": [
                [
                    "ཀྱི",
                    "5256"
                ],
                [
                    "རྣམས་ཀྱི",
                    "571"
                ]
            ],
            "སྡེ་": [
                [
                    "ནི",
                    "44237"
                ],
                [
                    "རྣམས་ནི",
                    "8962"
                ]
            ],
            "སྣར་": [
                [
                    "ཀྱི",
                    "5256"
                ],
                [
                    "རྣམས་ཀྱི",
                    "571"
                ]
            ]
        },
        "43": {
            "པེ་": [
                [
                    "ཀྱིས",
                    "6156"
                ],
                [
                    "ཀྱིས།_།",
                    "3361"
                ],
                [
                    "རྣམས་ཀྱིས",
                    "952"
                ],
                [
                    "རྣམས་ཀྱིས།_།",
                    "763"
                ]
            ],
            "སྡེ་": [
                [
                    "ཀྱི",
                    "5256"
                ],
                [
                    "ཀྱི།_།",
                    "2371"
                ],
                [
                    "རྣམས་ཀྱི",
                    "571"
                ],
                [
                    "རྣམས་ཀྱི།_།",
                    "509"
                ]
            ],
            "སྣར་": [
                [
                    "ཀྱིས",
                    "6156"
                ],
                [
                    "ཀྱིས།_།",
                    "3361"
                ],
                [
                    "རྣམས་ཀྱིས",
                    "952"
                ],
                [
                    "རྣམས་ཀྱིས།_།",
                    "763"
                ]
            ]
        },
        "44": {
            "པེ་": [],
            "སྡེ་": [
                [
                    "ཆོས་རྣམས་རང་བཞིན",
                    "61"
                ]
            ],
            "སྣར་": []
        },
        "45": {
            "པེ་": [
                [
                    "ཀྱི",
                    "5256"
                ],
                [
                    "ཀྱི།_།",
                    "2371"
                ],
                [
                    "རྣམས་ཀྱི",
                    "571"
                ],
                [
                    "རྣམས་ཀྱི།_།",
                    "509"
                ]
            ],
            "སྡེ་": [
                [
                    "ཀྱིས",
                    "6156"
                ],
                [
                    "ཀྱིས།_།",
                    "3361"
                ],
                [
                    "རྣམས་ཀྱིས",
                    "952"
                ],
                [
                    "རྣམས་ཀྱིས།_།",
                    "763"
                ]
            ],
            "སྣར་": [
                [
                    "ཀྱི",
                    "5256"
                ],
                [
                    "ཀྱི།_།",
                    "2371"
                ],
                [
                    "རྣམས་ཀྱི",
                    "571"
                ],
                [
                    "རྣམས་ཀྱི།_།",
                    "509"
                ]
            ]
        },
        "46": {
            "པེ་": [
                [
                    "བརྟག་པར",
                    "1458"
                ]
            ],
            "སྡེ་": [
                [
                    "རྟག་པར",
                    "2614"
                ],
                [
                    "རྟག་པར་འགྱུར",
                    "58"
                ]
            ],
            "སྣར་": [
                [
                    "བརྟག་པར",
                    "1458"
                ]
            ]
        },
        "47": {
            "པེ་": [
                [
                    "མིང་ནི",
                    "800"
                ],
                [
                    "།_།མིང་ནི",
                    "139"
                ]
            ],
            "སྡེ་": [
                [
                    "མི་དེ",
                    "1184"
                ],
                [
                    "།_།མི་དེ",
                    "143"
                ]
            ],
            "སྣར་": [
                [
                    "མིང་ནི",
                    "800"
                ],
                [
                    "།_།མིང་ནི",
                    "139"
                ]
            ]
        },
        "48": {
            "པེ་": [
                [
                    "ཀྱིས",
                    "6156"
                ],
                [
                    "ཀྱིས།_།",
                    "3361"
                ]
            ],
            "སྡེ་": [
                [
                    "ཀྱི",
                    "5256"
                ],
                [
                    "ཀྱི།_།",
                    "2371"
                ]
            ],
            "སྣར་": [
                [
                    "ཀྱིས",
                    "6156"
                ],
                [
                    "ཀྱིས།_།",
                    "3361"
                ]
            ]
        },
        "49": {
            "པེ་": [
                [
                    "འགོག",
                    "39"
                ]
            ],
            "སྡེ་": [
                [
                    "འགོག",
                    "39"
                ]
            ],
            "སྣར་": [
                [
                    "དགོག",
                    "23"
                ]
            ]
        },
        "5": {
            "པེ་": [],
            "སྡེ་": [],
            "སྣར་": [
                [
                    "བཏབ་པ",
                    "444"
                ],
                [
                    "བཏབ་པ།_།",
                    "40"
                ],
                [
                    "ལན་བཏབ་པ",
                    "45"
                ]
            ]
        },
        "50": {
            "པེ་": [
                [
                    "སྐྱེས",
                    "1030"
                ],
                [
                    "ཀྱི་སྐྱེས",
                    "67"
                ]
            ],
            "སྡེ་": [
                [
                    "སྐྱེ",
                    "779"
                ],
                [
                    "ཀྱི་སྐྱེ",
                    "1181"
                ]
            ],
            "སྣར་": [
                [
                    "སྐྱེས",
                    "1030"
                ],
                [
                    "ཀྱི་སྐྱེས",
                    "67"
                ]
            ]
        },
        "51": {
            "པེ་": [
                [
                    "དེར་ཡང",
                    "593"
                ],
                [
                    "།_།དེར་ཡང",
                    "142"
                ]
            ],
            "སྡེ་": [
                [
                    "དེ་ཡང",
                    "10377"
                ],
                [
                    "།_།དེ་ཡང",
                    "1410"
                ]
            ],
            "སྣར་": [
                [
                    "དེར་ཡང",
                    "593"
                ],
                [
                    "།_།དེར་ཡང",
                    "142"
                ]
            ]
        },
        "52": {
            "པེ་": [
                [
                    "རྟེན",
                    "218"
                ],
                [
                    "།_།རྟེན",
                    "393"
                ],
                [
                    "རྟེན་ནས",
                    "113"
                ]
            ],
            "སྡེ་": [
                [
                    "བརྟེན",
                    "256"
                ],
                [
                    "།_།བརྟེན",
                    "75"
                ],
                [
                    "བརྟེན་ནས",
                    "1090"
                ]
            ],
            "སྣར་": [
                [
                    "བརྟེན",
                    "256"
                ],
                [
                    "།_།བརྟེན",
                    "75"
                ],
                [
                    "བརྟེན་ནས",
                    "1090"
                ]
            ]
        },
        "53": {
            "པེ་": [],
            "སྡེ་": [],
            "སྣར་": []
        },
        "54": {
            "པེ་": [
                [
                    "ཡིན་པ",
                    "1695"
                ],
                [
                    "ཡིན་པ།_།",
                    "790"
                ],
                [
                    "གང་ཡིན་པ",
                    "733"
                ],
                [
                    "གང་ཡིན་པ།_།",
                    "699"
                ]
            ],
            "སྡེ་": [],
            "སྣར་": []
        },
        "55": {
            "པེ་": [
                [
                    "མེད",
                    "12565"
                ],
                [
                    "མེད་ཀྱི",
                    "107"
                ]
            ],
            "སྡེ་": [
                [
                    "ཆེད",
                    "6"
                ]
            ],
            "སྣར་": [
                [
                    "ཆེད",
                    "6"
                ]
            ]
        },
        "56": {
            "པེ་": [],
            "སྡེ་": [
                [
                    "རྩོད་པ",
                    "1637"
                ],
                [
                    "།_།རྩོད་པ",
                    "125"
                ]
            ],
            "སྣར་": []
        },
        "57": {
            "པེ་": [
                [
                    "ལོ་ཙཱ་བ",
                    "58"
                ]
            ],
            "སྡེ་": [
                [
                    "ལོཙྪ་བ",
                    "236"
                ]
            ],
            "སྣར་": [
                [
                    "ལོ་ཙཱ་བ",
                    "58"
                ]
            ]
        },
        "58": {
            "པེ་": [
                [
                    "ལས",
                    "5885"
                ],
                [
                    "ལས།_",
                    "2200"
                ]
            ],
            "སྡེ་": [
                [
                    "ལ",
                    "33965"
                ],
                [
                    "ལ།_",
                    "19029"
                ]
            ],
            "སྣར་": [
                [
                    "ལས",
                    "5885"
                ],
                [
                    "ལས།_",
                    "2200"
                ]
            ]
        },
        "59": {
            "པེ་": [
                [
                    "ཨཱ",
                    "89"
                ],
                [
                    "ཡ་ཨཱ",
                    "81"
                ]
            ],
            "སྡེ་": [
                [
                    "ཨ",
                    "188"
                ],
                [
                    "ཡ་ཨ",
                    "105"
                ],
                [
                    "ཨ་ནནྟ",
                    "78"
                ]
            ],
            "སྣར་": [
                [
                    "ཨཱ",
                    "89"
                ],
                [
                    "ཡ་ཨཱ",
                    "81"
                ]
            ]
        },
        "6": {
            "པེ་": [
                [
                    "ཡི",
                    "8322"
                ],
                [
                    "ཡི།_།",
                    "8252"
                ]
            ],
            "སྡེ་": [
                [
                    "ཡིན",
                    "32960"
                ],
                [
                    "ཡིན།_།",
                    "12284"
                ]
            ],
            "སྣར་": [
                [
                    "ཡི",
                    "8322"
                ],
                [
                    "ཡི།_།",
                    "8252"
                ]
            ]
        },
        "60": {
            "པེ་": [
                [
                    "ལོ་ཙཱ་བ",
                    "58"
                ]
            ],
            "སྡེ་": [
                [
                    "ལོཙྪ་བ",
                    "236"
                ],
                [
                    "།_ལོཙྪ་བ",
                    "49"
                ]
            ],
            "སྣར་": [
                [
                    "ལོ་ཙཱ་བ",
                    "58"
                ]
            ]
        },
        "61": {
            "པེ་": [
                [
                    "",
                    "1"
                ],
                [
                    "དཔལ",
                    "264"
                ],
                [
                    "དཔལ་གྱིས",
                    "78"
                ]
            ],
            "སྡེ་": [
                [
                    "",
                    "1"
                ],
                [
                    "དཔལ",
                    "264"
                ],
                [
                    "དཔལ་གྱིས",
                    "78"
                ]
            ],
            "སྣར་": [
                [
                    "",
                    "1"
                ],
                [
                    "དཔལ",
                    "264"
                ],
                [
                    "དཔལ་གྱིས",
                    "78"
                ]
            ]
        },
        "7": {
            "པེ་": [
                [
                    "ཏེ",
                    "80365"
                ],
                [
                    "ཏེ།_།",
                    "12767"
                ],
                [
                    "འགྱུར་ཏེ",
                    "1517"
                ],
                [
                    "འགྱུར་ཏེ།_།",
                    "1121"
                ]
            ],
            "སྡེ་": [
                [
                    "ཞིང",
                    "278"
                ],
                [
                    "ཞིང་།_།",
                    "4307"
                ],
                [
                    "འགྱུར་ཞིང",
                    "60"
                ],
                [
                    "འགྱུར་ཞིང་།_།",
                    "634"
                ]
            ],
            "སྣར་": [
                [
                    "ཏེ",
                    "80365"
                ],
                [
                    "ཏེ།_།",
                    "12767"
                ],
                [
                    "འགྱུར་ཏེ",
                    "1517"
                ],
                [
                    "འགྱུར་ཏེ།_།",
                    "1121"
                ]
            ]
        },
        "8": {
            "པེ་": [
                [
                    "ཀྱི",
                    "5256"
                ],
                [
                    "ཁྱོད་ཀྱི",
                    "3668"
                ]
            ],
            "སྡེ་": [
                [
                    "ཀྱིས",
                    "6156"
                ],
                [
                    "ཁྱོད་ཀྱིས",
                    "55"
                ]
            ],
            "སྣར་": [
                [
                    "ཀྱི",
                    "5256"
                ],
                [
                    "ཁྱོད་ཀྱི",
                    "3668"
                ]
            ]
        },
        "9": {
            "པེ་": [
                [
                    "དགག",
                    "12"
                ]
            ],
            "སྡེ་": [
                [
                    "འགོག",
                    "39"
                ],
                [
                    "དང་འགོག",
                    "110"
                ]
            ],
            "སྣར་": [
                [
                    "དགག",
                    "12"
                ]
            ]
        }
    },
    "non_standard_notes": [],
    "profile": {
        "1": [
            "པེ་=སྣར་ སྡེ་",
            "80.33%"
        ],
        "10": [
            "པེ་=སྣར་ སྡེ་",
            "80.33%"
        ],
        "11": [
            "པེ་=སྣར་ སྡེ་",
            "80.33%"
        ],
        "12": [
            "པེ་=སྣར་ སྡེ་",
            "80.33%"
        ],
        "13": [
            "པེ་=སྣར་ སྡེ་",
            "80.33%"
        ],
        "14": [
            "པེ་=སྣར་ སྡེ་",
            "80.33%"
        ],
        "15": [
            "པེ་=སྣར་ སྡེ་",
            "80.33%"
        ],
        "16": [
            "པེ་=སྣར་ སྡེ་",
            "80.33%"
        ],
        "17": [
            "པེ་=སྣར་ སྡེ་",
            "80.33%"
        ],
        "18": [
            "པེ་=སྣར་ སྡེ་",
            "80.33%"
        ],
        "19": [
            "པེ་=སྣར་ སྡེ་",
            "80.33%"
        ],
        "2": [
            "པེ་=སྣར་ སྡེ་",
            "80.33%"
        ],
        "20": [
            "པེ་=སྣར་ སྡེ་",
            "80.33%"
        ],
        "21": [
            "པེ་=སྣར་ སྡེ་",
            "80.33%"
        ],
        "22": [
            "པེ་=སྣར་ སྡེ་",
            "80.33%"
        ],
        "23": [
            "པེ་=སྣར་ སྡེ་",
            "80.33%"
        ],
        "24": [
            "པེ་ སྡེ་=སྣར་",
            "14.75%"
        ],
        "25": [
            "པེ་=སྣར་ སྡེ་",
            "80.33%"
        ],
        "26": [
            "པེ་=སྣར་ སྡེ་",
            "80.33%"
        ],
        "27": [
            "པེ་=སྣར་ སྡེ་",
            "80.33%"
        ],
        "28": [
            "པེ་=སྣར་ སྡེ་",
            "80.33%"
        ],
        "29": [
            "པེ་=སྣར་ སྡེ་",
            "80.33%"
        ],
        "3": [
            "པེ་=སྣར་ སྡེ་",
            "80.33%"
        ],
        "30": [
            "པེ་ སྡེ་=སྣར་",
            "14.75%"
        ],
        "31": [
            "པེ་=སྣར་ སྡེ་",
            "80.33%"
        ],
        "32": [
            "པེ་=སྣར་ སྡེ་",
            "80.33%"
        ],
        "33": [
            "པེ་=སྣར་ སྡེ་",
            "80.33%"
        ],
        "34": [
            "པེ་ སྡེ་=སྣར་",
            "14.75%"
        ],
        "35": [
            "པེ་=སྣར་ སྡེ་",
            "80.33%"
        ],
        "36": [
            "པེ་=སྣར་ སྡེ་",
            "80.33%"
        ],
        "37": [
            "པེ་ སྡེ་=སྣར་",
            "14.75%"
        ],
        "38": [
            "པེ་=སྣར་ སྡེ་",
            "80.33%"
        ],
        "39": [
            "པེ་=སྣར་ སྡེ་",
            "80.33%"
        ],
        "4": [
            "པེ་=སྣར་ སྡེ་",
            "80.33%"
        ],
        "40": [
            "པེ་=སྣར་ སྡེ་",
            "80.33%"
        ],
        "41": [
            "པེ་ སྡེ་=སྣར་",
            "14.75%"
        ],
        "42": [
            "པེ་=སྣར་ སྡེ་",
            "80.33%"
        ],
        "43": [
            "པེ་=སྣར་ སྡེ་",
            "80.33%"
        ],
        "44": [
            "པེ་=སྣར་ སྡེ་",
            "80.33%"
        ],
        "45": [
            "པེ་=སྣར་ སྡེ་",
            "80.33%"
        ],
        "46": [
            "པེ་=སྣར་ སྡེ་",
            "80.33%"
        ],
        "47": [
            "པེ་=སྣར་ སྡེ་",
            "80.33%"
        ],
        "48": [
            "པེ་=སྣར་ སྡེ་",
            "80.33%"
        ],
        "49": [
            "པེ་=སྡེ་ སྣར་",
            "3.28%"
        ],
        "5": [
            "པེ་=སྡེ་ སྣར་",
            "3.28%"
        ],
        "50": [
            "པེ་=སྣར་ སྡེ་",
            "80.33%"
        ],
        "51": [
            "པེ་=སྣར་ སྡེ་",
            "80.33%"
        ],
        "52": [
            "པེ་ སྡེ་=སྣར་",
            "14.75%"
        ],
        "53": [
            "པེ་ སྡེ་=སྣར་",
            "14.75%"
        ],
        "54": [
            "པེ་ སྡེ་=སྣར་",
            "14.75%"
        ],
        "55": [
            "པེ་ སྡེ་=སྣར་",
            "14.75%"
        ],
        "56": [
            "པེ་=སྣར་ སྡེ་",
            "80.33%"
        ],
        "57": [
            "པེ་=སྣར་ སྡེ་",
            "80.33%"
        ],
        "58": [
            "པེ་=སྣར་ སྡེ་",
            "80.33%"
        ],
        "59": [
            "པེ་=སྣར་ སྡེ་",
            "80.33%"
        ],
        "6": [
            "པེ་=སྣར་ སྡེ་",
            "80.33%"
        ],
        "60": [
            "པེ་=སྣར་ སྡེ་",
            "80.33%"
        ],
        "61": [
            "པེ་=སྡེ་=སྣར་",
            "1.64%"
        ],
        "7": [
            "པེ་=སྣར་ སྡེ་",
            "80.33%"
        ],
        "8": [
            "པེ་=སྣར་ སྡེ་",
            "80.33%"
        ],
        "9": [
            "པེ་=སྣར་ སྡེ་",
            "80.33%"
        ]
    }
}