{"Stats": {"Categorised": "25 notes (53.19%)", "Notes\u2019 total": 47, "Profiles": ["\u0f54\u0f7a\u0f0b=\u0f66\u0fa3\u0f62\u0f0b \u0f66\u0fa1\u0f7a\u0f0b: 93.18% (41 notes)", "\u0f54\u0f7a\u0f0b=\u0f66\u0fa1\u0f7a\u0f0b=\u0f66\u0fa3\u0f62\u0f0b: 4.55% (2 notes)", "\u0f54\u0f7a\u0f0b \u0f66\u0fa1\u0f7a\u0f0b=\u0f66\u0fa3\u0f62\u0f0b: 2.27% (1 notes)"], "automatic_categorisation": {"min_mod": {"min_mod_groups": 1, "particle_groups": 4}, "particle_issues": {"agreement_issue": 1, "po-bo-pa-ba": 3}, "spelling_mistake": {"non_word": {"well_formed": 3}}, "verb_difference": {"diff_tense": 8}}, "dunno": {"long_diff": 1, "no_diff": 14, "short_diff": 7}, "empty_notes": 5, "manual_categorisation": {"long_difference": {}, "manual_evaluation": {"meaning_difference": {}}}, "ngram_freq": {}, "profile": {}}, "automatic_categorisation": {"min_mod": {"min_mod_groups": [{"16": [[["\u0f63\u0f66", "\u0f63"]], {"\u0f54\u0f7a\u0f0b": ["\u0f60\u0f41\u0f7c\u0f62\u0f0b \u0f55\u0fb2\u0f7a\u0f44\u0f0b\u0f56\u0f0b", "\u0f63\u0f66\u0f0b", "\u0f58\u0f72\u0f0b \u0f63\u0f9f\u0f7c\u0f66\u0f0b\u0f54 \u0f60\u0f7c \u0f0d_\u0f0d \u0f51\u0f74\u0f66\u0f0b"], "\u0f66\u0fa1\u0f7a\u0f0b": ["\u0f60\u0f41\u0f7c\u0f62\u0f0b \u0f55\u0fb2\u0f7a\u0f44\u0f0b\u0f56\u0f0b", "\u0f63\u0f0b", "\u0f58\u0f72\u0f0b \u0f63\u0f9f\u0f7c\u0f66\u0f0b\u0f54 \u0f60\u0f7c \u0f0d_\u0f0d \u0f51\u0f74\u0f66\u0f0b"], "\u0f66\u0fa3\u0f62\u0f0b": ["\u0f60\u0f41\u0f7c\u0f62\u0f0b \u0f55\u0fb2\u0f7a\u0f44\u0f0b\u0f56\u0f0b", "\u0f63\u0f66\u0f0b", "\u0f58\u0f72\u0f0b \u0f63\u0f9f\u0f7c\u0f66\u0f0b\u0f54 \u0f60\u0f7c \u0f0d_\u0f0d \u0f51\u0f74\u0f66\u0f0b"]}]}], "particle_groups": [{"21": [["dreldra"], {"\u0f54\u0f7a\u0f0b": ["\u0f4f\u0f74\u0f0b \u0f55\u0f7a\u0f56\u0f66\u0f0b\u0f54 \u0f60\u0f7c \u0f0d_\u0f0d \u0f62\u0f44\u0f0b", "", "\u0f60\u0f42\u0fb1\u0f74\u0f62\u0f0b \u0f56\u0fb1\u0f7a\u0f51\u0f0b \u0f66\u0f92\u0fb2\u0f0b \u0f63\u0f0b \u0f42\u0f53\u0f66\u0f0b"], "\u0f66\u0fa1\u0f7a\u0f0b": ["\u0f4f\u0f74\u0f0b \u0f55\u0f7a\u0f56\u0f66\u0f0b\u0f54 \u0f60\u0f7c \u0f0d_\u0f0d \u0f62\u0f44\u0f0b", "\u0f42\u0f72\u0f0b", "\u0f60\u0f42\u0fb1\u0f74\u0f62\u0f0b \u0f56\u0fb1\u0f7a\u0f51\u0f0b \u0f66\u0f92\u0fb2\u0f0b \u0f63\u0f0b \u0f42\u0f53\u0f66\u0f0b"], "\u0f66\u0fa3\u0f62\u0f0b": ["\u0f4f\u0f74\u0f0b \u0f55\u0f7a\u0f56\u0f66\u0f0b\u0f54 \u0f60\u0f7c \u0f0d_\u0f0d \u0f62\u0f44\u0f0b", "", "\u0f60\u0f42\u0fb1\u0f74\u0f62\u0f0b \u0f56\u0fb1\u0f7a\u0f51\u0f0b \u0f66\u0f92\u0fb2\u0f0b \u0f63\u0f0b \u0f42\u0f53\u0f66\u0f0b"]}]}, {"27": [["dreldra"], {"\u0f54\u0f7a\u0f0b": ["\u0f66\u0f7c\u0f44\u0f0b\u0f56\u0f0b \u0f61\u0f44\u0f0b \u0f62\u0f44\u0f0b \u0f56\u0fb1\u0f74\u0f44\u0f0b", "", "\u0f51\u0f44\u0f0b \u0f63\u0f0b \u0f42\u0f53\u0f66\u0f0b\u0f54 \u0f66\u0f0b \u0f56\u0f74\u0f58\u0f0b"], "\u0f66\u0fa1\u0f7a\u0f0b": ["\u0f66\u0f7c\u0f44\u0f0b\u0f56\u0f0b \u0f61\u0f44\u0f0b \u0f62\u0f44\u0f0b \u0f56\u0fb1\u0f74\u0f44\u0f0b", "\u0f42\u0f72\u0f0b", "\u0f51\u0f44\u0f0b \u0f63\u0f0b \u0f42\u0f53\u0f66\u0f0b\u0f54 \u0f66\u0f0b \u0f56\u0f74\u0f58\u0f0b"], "\u0f66\u0fa3\u0f62\u0f0b": ["\u0f66\u0f7c\u0f44\u0f0b\u0f56\u0f0b \u0f61\u0f44\u0f0b \u0f62\u0f44\u0f0b \u0f56\u0fb1\u0f74\u0f44\u0f0b", "", "\u0f51\u0f44\u0f0b \u0f63\u0f0b \u0f42\u0f53\u0f66\u0f0b\u0f54 \u0f66\u0f0b \u0f56\u0f74\u0f58\u0f0b"]}]}, {"36": [["dreldra", "jedra"], {"\u0f54\u0f7a\u0f0b": ["\u0f54\u0f0b \u0f42\u0f5e\u0f53\u0f0b \u0f51\u0f7c\u0f53\u0f0b \u0f51\u0f74\u0f0b \u0f61\u0f72\u0f51\u0f0b", "\u0f40\u0fb1\u0f72\u0f66\u0f0b", "\u0f56\u0f62\u0f0b \u0f46\u0f7c\u0f51\u0f0b \u0f66\u0f7a\u0f63\u0f0b \u0f53\u0f74\u0f66\u0f0b\u0f54 \u0f60\u0f7c"], "\u0f66\u0fa1\u0f7a\u0f0b": ["\u0f54\u0f0b \u0f42\u0f5e\u0f53\u0f0b \u0f51\u0f7c\u0f53\u0f0b \u0f51\u0f74\u0f0b \u0f61\u0f72\u0f51\u0f0b", "\u0f40\u0fb1\u0f72\u0f0b", "\u0f56\u0f62\u0f0b \u0f46\u0f7c\u0f51\u0f0b \u0f66\u0f7a\u0f63\u0f0b \u0f53\u0f74\u0f66\u0f0b\u0f54 \u0f60\u0f7c"], "\u0f66\u0fa3\u0f62\u0f0b": ["\u0f54\u0f0b \u0f42\u0f5e\u0f53\u0f0b \u0f51\u0f7c\u0f53\u0f0b \u0f51\u0f74\u0f0b \u0f61\u0f72\u0f51\u0f0b", "\u0f40\u0fb1\u0f72\u0f66\u0f0b", "\u0f56\u0f62\u0f0b \u0f46\u0f7c\u0f51\u0f0b \u0f66\u0f7a\u0f63\u0f0b \u0f53\u0f74\u0f66\u0f0b\u0f54 \u0f60\u0f7c"]}]}, {"39": [["jedra"], {"\u0f54\u0f7a\u0f0b": ["\u0f55\u0fb2\u0f7a\u0f44\u0f0b\u0f56 \u0f66\u0f0b \u0f42\u0f61\u0f66\u0f0b \u0f66\u0f74\u0f0b", "\u0f56\u0f66\u0f90\u0f7c\u0f62\u0f0b\u0f56", "\u0f0d_ \u0f51\u0f7a \u0f60\u0f72\u0f0b \u0f55\u0fb1\u0f72\u0f0b \u0f62\u0f72\u0f58\u0f0b \u0f51\u0f74\u0f0b"], "\u0f66\u0fa1\u0f7a\u0f0b": ["\u0f55\u0fb2\u0f7a\u0f44\u0f0b\u0f56 \u0f66\u0f0b \u0f42\u0f61\u0f66\u0f0b \u0f66\u0f74\u0f0b", "\u0f56\u0f66\u0f90\u0f7c\u0f62\u0f0b\u0f56 \u0f66", "\u0f0d_ \u0f51\u0f7a \u0f60\u0f72\u0f0b \u0f55\u0fb1\u0f72\u0f0b \u0f62\u0f72\u0f58\u0f0b \u0f51\u0f74\u0f0b"], "\u0f66\u0fa3\u0f62\u0f0b": ["\u0f55\u0fb2\u0f7a\u0f44\u0f0b\u0f56 \u0f66\u0f0b \u0f42\u0f61\u0f66\u0f0b \u0f66\u0f74\u0f0b", "\u0f56\u0f66\u0f90\u0f7c\u0f62\u0f0b\u0f56", "\u0f0d_ \u0f51\u0f7a \u0f60\u0f72\u0f0b \u0f55\u0fb1\u0f72\u0f0b \u0f62\u0f72\u0f58\u0f0b \u0f51\u0f74\u0f0b"]}]}]}, "particle_issues": {"added_particle": [], "agreement_issue": [{"2": ["lhakce", {"\u0f54\u0f7a\u0f0b": ["\u0f66\u0f90\u0fb1\u0f7a\u0f0b\u0f56\u0f0b \u0f46\u0f7c\u0f0b\u0f60\u0f55\u0fb2\u0f74\u0f63\u0f0b \u0f51\u0f74\u0f0b", "\u0f56\u0f66\u0f9f\u0f53\u0f0b \u0f4f\u0f7a", "\u0f0d_ \u0f51\u0f7a\u0f0b\u0f61\u0f44\u0f0b \u0f66\u0f90\u0fb1\u0f7a\u0f0b\u0f56\u0f0b"], "\u0f66\u0fa1\u0f7a\u0f0b": ["\u0f66\u0f90\u0fb1\u0f7a\u0f0b\u0f56\u0f0b \u0f46\u0f7c\u0f0b\u0f60\u0f55\u0fb2\u0f74\u0f63\u0f0b \u0f51\u0f74\u0f0b", "\u0f56\u0f66\u0f9f\u0f53", "\u0f0d_ \u0f51\u0f7a\u0f0b\u0f61\u0f44\u0f0b \u0f66\u0f90\u0fb1\u0f7a\u0f0b\u0f56\u0f0b"], "\u0f66\u0fa3\u0f62\u0f0b": ["\u0f66\u0f90\u0fb1\u0f7a\u0f0b\u0f56\u0f0b \u0f46\u0f7c\u0f0b\u0f60\u0f55\u0fb2\u0f74\u0f63\u0f0b \u0f51\u0f74\u0f0b", "\u0f56\u0f66\u0f9f\u0f53\u0f0b \u0f4f\u0f7a", "\u0f0d_ \u0f51\u0f7a\u0f0b\u0f61\u0f44\u0f0b \u0f66\u0f90\u0fb1\u0f7a\u0f0b\u0f56\u0f0b"]}]}], "different_particles": [], "other": [], "po-bo-pa-ba": [{"11": ["dagdra_pa", {"\u0f54\u0f7a\u0f0b": ["\u0f42\u0f4f\u0f53\u0f0b \u0f53\u0f72 \u0f0d_ \u0f61\u0f74\u0f63\u0f0b", "\u0f56\u0fb1\u0f74\u0f44\u0f0b", "\u0f56\u0f4f\u0f56\u0f0b\u0f54 \u0f66\u0f0b \u0f66\u0f92\u0fb2\u0f0b \u0f42\u0f53\u0f66\u0f0b\u0f54\u0f0b"], "\u0f66\u0fa1\u0f7a\u0f0b": ["\u0f42\u0f4f\u0f53\u0f0b \u0f53\u0f72 \u0f0d_ \u0f61\u0f74\u0f63\u0f0b", "\u0f56\u0fb1\u0f74\u0f44\u0f0b\u0f56\u0f0b", "\u0f56\u0f4f\u0f56\u0f0b\u0f54 \u0f66\u0f0b \u0f66\u0f92\u0fb2\u0f0b \u0f42\u0f53\u0f66\u0f0b\u0f54\u0f0b"], "\u0f66\u0fa3\u0f62\u0f0b": ["\u0f42\u0f4f\u0f53\u0f0b \u0f53\u0f72 \u0f0d_ \u0f61\u0f74\u0f63\u0f0b", "\u0f56\u0fb1\u0f74\u0f44\u0f0b", "\u0f56\u0f4f\u0f56\u0f0b\u0f54 \u0f66\u0f0b \u0f66\u0f92\u0fb2\u0f0b \u0f42\u0f53\u0f66\u0f0b\u0f54\u0f0b"]}]}, {"33": ["dagdra_pa", {"\u0f54\u0f7a\u0f0b": ["\u0f56 \u0f66\u0f0b \u0f66\u0fa3\u0f44\u0f0b \u0f66\u0f9f\u0f7c\u0f44\u0f0b \u0f62\u0f97\u0f7a\u0f66\u0f0b", "\u0f60\u0f5b\u0f72\u0f53\u0f0b\u0f54\u0f0b", "\u0f58\u0f7a\u0f51\u0f0b\u0f54 \u0f66\u0f0b \u0f42\u0fb2\u0f7c\u0f63\u0f0b\u0f56\u0f0b \u0f5e\u0f7a\u0f66\u0f0b"], "\u0f66\u0fa1\u0f7a\u0f0b": ["\u0f56 \u0f66\u0f0b \u0f66\u0fa3\u0f44\u0f0b \u0f66\u0f9f\u0f7c\u0f44\u0f0b \u0f62\u0f97\u0f7a\u0f66\u0f0b", "\u0f60\u0f5b\u0f72\u0f53\u0f0b", "\u0f58\u0f7a\u0f51\u0f0b\u0f54 \u0f66\u0f0b \u0f42\u0fb2\u0f7c\u0f63\u0f0b\u0f56\u0f0b \u0f5e\u0f7a\u0f66\u0f0b"], "\u0f66\u0fa3\u0f62\u0f0b": ["\u0f56 \u0f66\u0f0b \u0f66\u0fa3\u0f44\u0f0b \u0f66\u0f9f\u0f7c\u0f44\u0f0b \u0f62\u0f97\u0f7a\u0f66\u0f0b", "\u0f60\u0f5b\u0f72\u0f53\u0f0b\u0f54\u0f0b", "\u0f58\u0f7a\u0f51\u0f0b\u0f54 \u0f66\u0f0b \u0f42\u0fb2\u0f7c\u0f63\u0f0b\u0f56\u0f0b \u0f5e\u0f7a\u0f66\u0f0b"]}]}, {"35": ["dagdra_pa", {"\u0f54\u0f7a\u0f0b": ["\u0f66\u0f94\u0f7c\u0f53\u0f0b \u0f51\u0f74\u0f0b \u0f56\u0f66\u0f90\u0fb1\u0f7a\u0f51\u0f0b\u0f54 \u0f60\u0f72\u0f0b", "\u0f62\u0f72\u0f58\u0f0b", "\u0f51\u0f54\u0f60\u0f0b\u0f56\u0f7c\u0f0b \u0f42\u0f45\u0f72\u0f42\u0f0b\u0f54 \u0f60\u0f58 \u0f0d "], "\u0f66\u0fa1\u0f7a\u0f0b": ["\u0f66\u0f94\u0f7c\u0f53\u0f0b \u0f51\u0f74\u0f0b \u0f56\u0f66\u0f90\u0fb1\u0f7a\u0f51\u0f0b\u0f54 \u0f60\u0f72\u0f0b", "\u0f62\u0f72\u0f58\u0f0b\u0f54\u0f0b", "\u0f51\u0f54\u0f60\u0f0b\u0f56\u0f7c\u0f0b \u0f42\u0f45\u0f72\u0f42\u0f0b\u0f54 \u0f60\u0f58 \u0f0d "], "\u0f66\u0fa3\u0f62\u0f0b": ["\u0f66\u0f94\u0f7c\u0f53\u0f0b \u0f51\u0f74\u0f0b \u0f56\u0f66\u0f90\u0fb1\u0f7a\u0f51\u0f0b\u0f54 \u0f60\u0f72\u0f0b", "\u0f62\u0f72\u0f58\u0f0b\u0f54\u0f0b", "\u0f51\u0f54\u0f60\u0f0b\u0f56\u0f7c\u0f0b \u0f42\u0f45\u0f72\u0f42\u0f0b\u0f54 \u0f60\u0f58 \u0f0d "]}]}]}, "spelling_mistake": {"missing_vowel": [], "nga_da": [], "non_word": {"ill_formed": [], "well_formed": [{"1": [{"\u0f54\u0f7a\u0f0b": ["\u0f51\u0f44 \u0f0b\u0f0d_ \u0f64\u0f7a\u0f66\u0f0b\u0f56\u0fb1\u0f0b \u0f62\u0f44\u0f0b", "#\u0f56\u0f64\u0f72\u0f66\u0f0b", "\u0f63\u0f0b \u0f42\u0f53\u0f66\u0f0b\u0f54\u0f0b \u0f51\u0f44 \u0f0b\u0f0d "], "\u0f66\u0fa1\u0f7a\u0f0b": ["\u0f51\u0f44 \u0f0b\u0f0d_ \u0f64\u0f7a\u0f66\u0f0b\u0f56\u0fb1\u0f0b \u0f62\u0f44\u0f0b", "#\u0f42\u0f64\u0f72\u0f66\u0f0b", "\u0f63\u0f0b \u0f42\u0f53\u0f66\u0f0b\u0f54\u0f0b \u0f51\u0f44 \u0f0b\u0f0d "], "\u0f66\u0fa3\u0f62\u0f0b": ["\u0f51\u0f44 \u0f0b\u0f0d_ \u0f64\u0f7a\u0f66\u0f0b\u0f56\u0fb1\u0f0b \u0f62\u0f44\u0f0b", "#\u0f56\u0f64\u0f72\u0f66\u0f0b", "\u0f63\u0f0b \u0f42\u0f53\u0f66\u0f0b\u0f54\u0f0b \u0f51\u0f44 \u0f0b\u0f0d "]}]}, {"14": [{"\u0f54\u0f7a\u0f0b": ["\u0f56\u0fb1 \u0f60\u0f7c \u0f0d_\u0f0d \u0f64\u0f7a\u0f66\u0f0b\u0f56\u0fb1\u0f0b \u0f62\u0f44\u0f0b", "\u0f56\u0f64\u0f72\u0f42\u0f0b", "\u0f66\u0f92\u0fb2\u0f0b \u0f63\u0f0b \u0f42\u0f53\u0f66\u0f0b\u0f54 \u0f60\u0f72\u0f0b \u0f56\u0f66\u0f58\u0f0b"], "\u0f66\u0fa1\u0f7a\u0f0b": ["\u0f56\u0fb1 \u0f60\u0f7c \u0f0d_\u0f0d \u0f64\u0f7a\u0f66\u0f0b\u0f56\u0fb1\u0f0b \u0f62\u0f44\u0f0b", "#\u0f42\u0f64\u0f72\u0f66\u0f0b", "\u0f66\u0f92\u0fb2\u0f0b \u0f63\u0f0b \u0f42\u0f53\u0f66\u0f0b\u0f54 \u0f60\u0f72\u0f0b \u0f56\u0f66\u0f58\u0f0b"], "\u0f66\u0fa3\u0f62\u0f0b": ["\u0f56\u0fb1 \u0f60\u0f7c \u0f0d_\u0f0d \u0f64\u0f7a\u0f66\u0f0b\u0f56\u0fb1\u0f0b \u0f62\u0f44\u0f0b", "\u0f56\u0f64\u0f72\u0f42\u0f0b", "\u0f66\u0f92\u0fb2\u0f0b \u0f63\u0f0b \u0f42\u0f53\u0f66\u0f0b\u0f54 \u0f60\u0f72\u0f0b \u0f56\u0f66\u0f58\u0f0b"]}]}, {"26": [{"\u0f54\u0f7a\u0f0b": ["\u0f62\u0f44\u0f0b \u0f42\u0f53\u0f66\u0f0b \u0f56\u0f66\u0f58\u0f0b\u0f42\u0f4f\u0f53\u0f0b \u0f58\u0f72\u0f0b", "\u0f42\u0f61\u0f7c\u0f0b\u0f56\u0f0b", "\u0f62\u0f44\u0f0b \u0f50\u0f7c\u0f42\u0f0b \u0f4f\u0f74\u0f0b \u0f66\u0f92\u0fb2\u0f0b \u0f55\u0f56\u0f0b"], "\u0f66\u0fa1\u0f7a\u0f0b": ["\u0f62\u0f44\u0f0b \u0f42\u0f53\u0f66\u0f0b \u0f56\u0f66\u0f58\u0f0b\u0f42\u0f4f\u0f53\u0f0b \u0f58\u0f72\u0f0b", "#\u0f42\u0f61\u0f7c\u0f44\u0f0b", "\u0f62\u0f44\u0f0b \u0f50\u0f7c\u0f42\u0f0b \u0f4f\u0f74\u0f0b \u0f66\u0f92\u0fb2\u0f0b \u0f55\u0f56\u0f0b"], "\u0f66\u0fa3\u0f62\u0f0b": ["\u0f62\u0f44\u0f0b \u0f42\u0f53\u0f66\u0f0b \u0f56\u0f66\u0f58\u0f0b\u0f42\u0f4f\u0f53\u0f0b \u0f58\u0f72\u0f0b", "\u0f42\u0f61\u0f7c\u0f0b\u0f56\u0f0b", "\u0f62\u0f44\u0f0b \u0f50\u0f7c\u0f42\u0f0b \u0f4f\u0f74\u0f0b \u0f66\u0f92\u0fb2\u0f0b \u0f55\u0f56\u0f0b"]}]}]}}, "sskrt": [], "verb_difference": {"diff_tense": [{"4": [["\u300a\u0f56\u0f5f\u0f74\u0f44\u300b\u0f5e\u0f7a\u0f66\u0f0b\u0f54\u0f0d\u3010\u3008\u0f60\u0f5b\u0f72\u0f53\u3009\u0f42\u0f72\u0f0b \u0f60\u0f51\u0f66\u0f0b\u0f54\u0f0d\u3011\u3010\u3008\u0f60\u0f5b\u0f72\u0f53\u3009\u0f42\u0f72\u0f0b \u0f60\u0f51\u0f66\u0f0b\u0f54\u0f0d \u0f50\u0f0b\u0f51\u0f51\u0f0b\u0f54\u0f0d\u3011", "\u300a\u0f42\u0f5f\u0f74\u0f44\u300b\u0f5e\u0f7a\u0f66\u0f0b\u0f54\u0f0d\u3010\u3008\u0f60\u0f5b\u0f72\u0f53\u3009\u0f42\u0f72\u0f0b \u0f58\u0f0b\u0f60\u0f7c\u0f44\u0f66\u0f0b\u0f54\u0f0d\u3011\u3010\u3008\u0f60\u0f5b\u0f72\u0f53\u3009\u0f42\u0f72\u0f0b \u0f58\u0f0b\u0f60\u0f7c\u0f44\u0f66\u0f0b\u0f54\u0f0d \u0f50\u0f0b\u0f51\u0f51\u0f0b\u0f54\u0f0d\u3011"], {"\u0f54\u0f7a\u0f0b": ["\u0f62\u0f90\u0fb1\u0f7a\u0f53\u0f0b \u0f66\u0f92\u0fb2\u0f0b \u0f62\u0f44\u0f0b \u0f66\u0f44\u0f66\u0f0b \u0f44\u0f7c \u0f66\u0f0b", "\u0f56\u0f5f\u0f74\u0f44\u0f0b", "\u0f58\u0f7a\u0f51\u0f0b\u0f54 \u0f62\u0f0b \u0f56\u0f62\u0f97\u0f7c\u0f51\u0f0b\u0f54\u0f0b \u0f58\u0f7a\u0f51\u0f0b"], "\u0f66\u0fa1\u0f7a\u0f0b": ["\u0f62\u0f90\u0fb1\u0f7a\u0f53\u0f0b \u0f66\u0f92\u0fb2\u0f0b \u0f62\u0f44\u0f0b \u0f66\u0f44\u0f66\u0f0b \u0f44\u0f7c \u0f66\u0f0b", "\u0f42\u0f5f\u0f74\u0f44\u0f0b", "\u0f58\u0f7a\u0f51\u0f0b\u0f54 \u0f62\u0f0b \u0f56\u0f62\u0f97\u0f7c\u0f51\u0f0b\u0f54\u0f0b \u0f58\u0f7a\u0f51\u0f0b"], "\u0f66\u0fa3\u0f62\u0f0b": ["\u0f62\u0f90\u0fb1\u0f7a\u0f53\u0f0b \u0f66\u0f92\u0fb2\u0f0b \u0f62\u0f44\u0f0b \u0f66\u0f44\u0f66\u0f0b \u0f44\u0f7c \u0f66\u0f0b", "\u0f56\u0f5f\u0f74\u0f44\u0f0b", "\u0f58\u0f7a\u0f51\u0f0b\u0f54 \u0f62\u0f0b \u0f56\u0f62\u0f97\u0f7c\u0f51\u0f0b\u0f54\u0f0b \u0f58\u0f7a\u0f51\u0f0b"]}]}, {"8": [["\u300a\u0f42\u0fb2\u0f42\u0f66\u300b\u0f5e\u0f7a\u0f66\u0f0b\u0f54\u0f0d\u3010\u3008\u0f42\u0fb2\u0f42\u3009\u0f42\u0f72\u0f0b \u0f60\u0f51\u0f66\u0f0b\u0f54\u0f0d \u0f50\u0f0b\u0f58\u0f72\u0f0b\u0f51\u0f51\u0f0b\u0f54\u0f0d\u3011", "\u300a\u0f42\u0fb2\u0f42\u300b\u0f5e\u0f7a\u0f66\u0f0b\u0f54\u0f0d\u3010\u3008\u0f42\u0fb2\u0f42\u3009\u0f42\u0f72\u0f0b \u0f51\u0f0b\u0f63\u0f9f\u0f0b\u0f56\u0f0d \u0f50\u0f0b\u0f58\u0f72\u0f0b\u0f51\u0f51\u0f0b\u0f54\u0f0d\u3011\u3010\u3008\u0f42\u0fb2\u0f42\u3009\u0f42\u0f72\u0f0b \u0f58\u0f0b\u0f60\u0f7c\u0f44\u0f66\u0f0b\u0f54\u0f0d \u0f50\u0f0b\u0f58\u0f72\u0f0b\u0f51\u0f51\u0f0b\u0f54\u0f0d\u3011"], {"\u0f54\u0f7a\u0f0b": ["\u0f56 \u0f66 \u0f0d_ \u0f44\u0f42\u0f0b \u0f66\u0f92\u0fb2\u0f0b \u0f56\u0f66\u0f92\u0fb1\u0f74\u0f62\u0f0b", "\u0f42\u0fb2\u0f42\u0f66\u0f0b", "\u0f66\u0f9f\u0f7c\u0f44\u0f0b \u0f62\u0f44\u0f0b \u0f61\u0f63\u0f0b\u0f56 \u0f66\u0f0b \u0f56\u0f62\u0f97\u0f7c\u0f51\u0f0b"], "\u0f66\u0fa1\u0f7a\u0f0b": ["\u0f56 \u0f66 \u0f0d_ \u0f44\u0f42\u0f0b \u0f66\u0f92\u0fb2\u0f0b \u0f56\u0f66\u0f92\u0fb1\u0f74\u0f62\u0f0b", "\u0f42\u0fb2\u0f42\u0f0b", "\u0f66\u0f9f\u0f7c\u0f44\u0f0b \u0f62\u0f44\u0f0b \u0f61\u0f63\u0f0b\u0f56 \u0f66\u0f0b \u0f56\u0f62\u0f97\u0f7c\u0f51\u0f0b"], "\u0f66\u0fa3\u0f62\u0f0b": ["\u0f56 \u0f66 \u0f0d_ \u0f44\u0f42\u0f0b \u0f66\u0f92\u0fb2\u0f0b \u0f56\u0f66\u0f92\u0fb1\u0f74\u0f62\u0f0b", "\u0f42\u0fb2\u0f42\u0f66\u0f0b", "\u0f66\u0f9f\u0f7c\u0f44\u0f0b \u0f62\u0f44\u0f0b \u0f61\u0f63\u0f0b\u0f56 \u0f66\u0f0b \u0f56\u0f62\u0f97\u0f7c\u0f51\u0f0b"]}]}, {"10": [["\u300a\u0f56\u0f63\u0f9f\u300b\u0f5e\u0f7a\u0f66\u0f0b\u0f54\u0f0d\u3010\u3008\u0f63\u0f9f\u3009\u0f42\u0f72\u0f0b \u0f58\u0f0b\u0f60\u0f7c\u0f44\u0f66\u0f0b\u0f54\u0f0d\u3011\u3010\u3008\u0f63\u0f9f\u3009\u0f42\u0f72\u0f0b \u0f58\u0f0b\u0f60\u0f7c\u0f44\u0f66\u0f0b\u0f54\u0f0d \u0f50\u0f0b\u0f51\u0f51\u0f0b\u0f54\u0f0d\u3011", "\u300a\u0f63\u0f9f\u300b\u0f5e\u0f7a\u0f66\u0f0b\u0f54\u0f0d\u3010\u3008\u0f63\u0f9f\u3009\u0f42\u0f72\u0f0b \u0f51\u0f0b\u0f63\u0f9f\u0f0b\u0f56\u0f0d\u3011\u3010\u3008\u0f63\u0f9f\u3009\u0f42\u0f72\u0f0b \u0f51\u0f0b\u0f63\u0f9f\u0f0b\u0f56\u0f0d \u0f50\u0f0b\u0f51\u0f51\u0f0b\u0f54\u0f0d\u3011"], {"\u0f54\u0f7a\u0f0b": ["\u0f54\u0f0b \u0f62\u0f44\u0f0b \u0f66\u0f9f\u0f7a\u0f44\u0f0b \u0f51\u0f74\u0f0b \u0f46\u0f7c\u0f51\u0f0b\u0f54 \u0f66\u0f0b", "\u0f56\u0f63\u0f9f\u0f0b\u0f56\u0f0b", "\u0f44\u0f7c \u0f66\u0f0b \u0f42\u0f5f\u0f74\u0f44\u0f0b \u0f51\u0f44\u0f0b \u0f56\u0fb2\u0f63\u0f0b"], "\u0f66\u0fa1\u0f7a\u0f0b": ["\u0f54\u0f0b \u0f62\u0f44\u0f0b \u0f66\u0f9f\u0f7a\u0f44\u0f0b \u0f51\u0f74\u0f0b \u0f46\u0f7c\u0f51\u0f0b\u0f54 \u0f66\u0f0b", "\u0f63\u0f9f\u0f0b\u0f56\u0f0b", "\u0f44\u0f7c \u0f66\u0f0b \u0f42\u0f5f\u0f74\u0f44\u0f0b \u0f51\u0f44\u0f0b \u0f56\u0fb2\u0f63\u0f0b"], "\u0f66\u0fa3\u0f62\u0f0b": ["\u0f54\u0f0b \u0f62\u0f44\u0f0b \u0f66\u0f9f\u0f7a\u0f44\u0f0b \u0f51\u0f74\u0f0b \u0f46\u0f7c\u0f51\u0f0b\u0f54 \u0f66\u0f0b", "\u0f56\u0f63\u0f9f\u0f0b\u0f56\u0f0b", "\u0f44\u0f7c \u0f66\u0f0b \u0f42\u0f5f\u0f74\u0f44\u0f0b \u0f51\u0f44\u0f0b \u0f56\u0fb2\u0f63\u0f0b"]}]}, {"12": [["\u300a\u0f56\u0f5f\u0f74\u0f44\u300b\u0f5e\u0f7a\u0f66\u0f0b\u0f54\u0f0d\u3010\u3008\u0f60\u0f5b\u0f72\u0f53\u3009\u0f42\u0f72\u0f0b \u0f60\u0f51\u0f66\u0f0b\u0f54\u0f0d\u3011\u3010\u3008\u0f60\u0f5b\u0f72\u0f53\u3009\u0f42\u0f72\u0f0b \u0f60\u0f51\u0f66\u0f0b\u0f54\u0f0d \u0f50\u0f0b\u0f51\u0f51\u0f0b\u0f54\u0f0d\u3011", "\u300a\u0f42\u0f5f\u0f74\u0f44\u300b\u0f5e\u0f7a\u0f66\u0f0b\u0f54\u0f0d\u3010\u3008\u0f60\u0f5b\u0f72\u0f53\u3009\u0f42\u0f72\u0f0b \u0f58\u0f0b\u0f60\u0f7c\u0f44\u0f66\u0f0b\u0f54\u0f0d\u3011\u3010\u3008\u0f60\u0f5b\u0f72\u0f53\u3009\u0f42\u0f72\u0f0b \u0f58\u0f0b\u0f60\u0f7c\u0f44\u0f66\u0f0b\u0f54\u0f0d \u0f50\u0f0b\u0f51\u0f51\u0f0b\u0f54\u0f0d\u3011"], {"\u0f54\u0f7a\u0f0b": ["\u0f51\u0f44\u0f0b \u0f56\u0fb2\u0f63\u0f0b\u0f56 \u0f66\u0f0b \u0f63\u0fb7\u0f0b \u0f44\u0f7c \u0f66\u0f0b", "\u0f56\u0f5f\u0f74\u0f44\u0f0b", "\u0f51\u0f44\u0f0b \u0f56\u0fb2\u0f63\u0f0b\u0f56 \u0f60\u0f7c \u0f0d_\u0f0d \u0f66\u0f7a\u0f58\u0f66\u0f0b"], "\u0f66\u0fa1\u0f7a\u0f0b": ["\u0f51\u0f44\u0f0b \u0f56\u0fb2\u0f63\u0f0b\u0f56 \u0f66\u0f0b \u0f63\u0fb7\u0f0b \u0f44\u0f7c \u0f66\u0f0b", "\u0f42\u0f5f\u0f74\u0f44\u0f0b", "\u0f51\u0f44\u0f0b \u0f56\u0fb2\u0f63\u0f0b\u0f56 \u0f60\u0f7c \u0f0d_\u0f0d \u0f66\u0f7a\u0f58\u0f66\u0f0b"], "\u0f66\u0fa3\u0f62\u0f0b": ["\u0f51\u0f44\u0f0b \u0f56\u0fb2\u0f63\u0f0b\u0f56 \u0f66\u0f0b \u0f63\u0fb7\u0f0b \u0f44\u0f7c \u0f66\u0f0b", "\u0f56\u0f5f\u0f74\u0f44\u0f0b", "\u0f51\u0f44\u0f0b \u0f56\u0fb2\u0f63\u0f0b\u0f56 \u0f60\u0f7c \u0f0d_\u0f0d \u0f66\u0f7a\u0f58\u0f66\u0f0b"]}]}, {"15": [["\u300a\u0f56\u0f45\u0f51\u300b\u0f5e\u0f7a\u0f66\u0f0b\u0f54\u0f0d\u3010\u3008\u0f42\u0f45\u0f7c\u0f51\u3009\u0f42\u0f72\u0f0b \u0f60\u0f51\u0f66\u0f0b\u0f54\u0f0d\u3011\u3010\u3008\u0f42\u0f45\u0f7c\u0f51\u3009\u0f42\u0f72\u0f0b \u0f60\u0f51\u0f66\u0f0b\u0f54\u0f0d \u0f50\u0f0b\u0f51\u0f51\u0f0b\u0f54\u0f0d\u3011\u3010\u3008\u0f42\u0f45\u0f7c\u0f51\u3009\u0f42\u0f72\u0f0b \u0f60\u0f51\u0f66\u0f0b\u0f54\u0f0d \u0f50\u0f0b\u0f58\u0f72\u0f0b\u0f51\u0f51\u0f0b\u0f54\u0f0d\u3011", "\u300a\u0f42\u0f45\u0f51\u300b\u0f5e\u0f7a\u0f66\u0f0b\u0f54\u0f0d\u3010\u3008\u0f42\u0f45\u0f7c\u0f51\u3009\u0f42\u0f72\u0f0b \u0f58\u0f0b\u0f60\u0f7c\u0f44\u0f66\u0f0b\u0f54\u0f0d\u3011\u3010\u3008\u0f42\u0f45\u0f7c\u0f51\u3009\u0f42\u0f72\u0f0b \u0f58\u0f0b\u0f60\u0f7c\u0f44\u0f66\u0f0b\u0f54\u0f0d \u0f50\u0f0b\u0f51\u0f51\u0f0b\u0f54\u0f0d\u3011\u3010\u3008\u0f42\u0f45\u0f7c\u0f51\u3009\u0f42\u0f72\u0f0b \u0f58\u0f0b\u0f60\u0f7c\u0f44\u0f66\u0f0b\u0f54\u0f0d \u0f50\u0f0b\u0f58\u0f72\u0f0b\u0f51\u0f51\u0f0b\u0f54\u0f0d\u3011"], {"\u0f54\u0f7a\u0f0b": ["\u0f56\u0f66\u0f58\u0f0b\u0f42\u0f4f\u0f53\u0f0b \u0f53\u0f72 \u0f0d_ #\u0f62\u0fa9\u0f51\u0f0b", "\u0f56\u0f45\u0f51\u0f0b\u0f54 \u0f66\u0f0b", "\u0f63\u0f9f\u0f0b\u0f56\u0f0b \u0f66\u0f9f\u0f7c\u0f44\u0f0b\u0f54\u0f0b"], "\u0f66\u0fa1\u0f7a\u0f0b": ["\u0f56\u0f66\u0f58\u0f0b\u0f42\u0f4f\u0f53\u0f0b \u0f53\u0f72 \u0f0d_ #\u0f62\u0fa9\u0f51\u0f0b", "\u0f42\u0f45\u0f51\u0f0b\u0f54 \u0f66\u0f0b", "\u0f63\u0f9f\u0f0b\u0f56\u0f0b \u0f66\u0f9f\u0f7c\u0f44\u0f0b\u0f54\u0f0b"], "\u0f66\u0fa3\u0f62\u0f0b": ["\u0f56\u0f66\u0f58\u0f0b\u0f42\u0f4f\u0f53\u0f0b \u0f53\u0f72 \u0f0d_ #\u0f62\u0fa9\u0f51\u0f0b", "\u0f56\u0f45\u0f51\u0f0b\u0f54 \u0f66\u0f0b", "\u0f63\u0f9f\u0f0b\u0f56\u0f0b \u0f66\u0f9f\u0f7c\u0f44\u0f0b\u0f54\u0f0b"]}]}, {"25": [["\u300a\u0f42\u0fb2\u0f42\u300b\u0f5e\u0f7a\u0f66\u0f0b\u0f54\u0f0d\u3010\u3008\u0f42\u0fb2\u0f42\u3009\u0f42\u0f72\u0f0b \u0f51\u0f0b\u0f63\u0f9f\u0f0b\u0f56\u0f0d \u0f50\u0f0b\u0f58\u0f72\u0f0b\u0f51\u0f51\u0f0b\u0f54\u0f0d\u3011\u3010\u3008\u0f42\u0fb2\u0f42\u3009\u0f42\u0f72\u0f0b \u0f58\u0f0b\u0f60\u0f7c\u0f44\u0f66\u0f0b\u0f54\u0f0d \u0f50\u0f0b\u0f58\u0f72\u0f0b\u0f51\u0f51\u0f0b\u0f54\u0f0d\u3011", "\u300a\u0f42\u0fb2\u0f42\u0f66\u300b\u0f5e\u0f7a\u0f66\u0f0b\u0f54\u0f0d\u3010\u3008\u0f42\u0fb2\u0f42\u3009\u0f42\u0f72\u0f0b \u0f60\u0f51\u0f66\u0f0b\u0f54\u0f0d \u0f50\u0f0b\u0f58\u0f72\u0f0b\u0f51\u0f51\u0f0b\u0f54\u0f0d\u3011"], {"\u0f54\u0f7a\u0f0b": ["\u0f63\u0fb7\u0f0b \u0f62\u0fa3\u0f58\u0f0b\u0f54\u0f0b \u0f51\u0fb2\u0f74\u0f42\u0f0b \u0f63\u0f0b", "\u0f42\u0fb2\u0f42\u0f0b\u0f54\u0f0b", "\u0f66\u0f92\u0fb2 \u0f60\u0f72\u0f0b \u0f63\u0fb7\u0f0b \u0f63\u0f0b \u0f42\u0f53\u0f66\u0f0b"], "\u0f66\u0fa1\u0f7a\u0f0b": ["\u0f63\u0fb7\u0f0b \u0f62\u0fa3\u0f58\u0f0b\u0f54\u0f0b \u0f51\u0fb2\u0f74\u0f42\u0f0b \u0f63\u0f0b", "\u0f42\u0fb2\u0f42\u0f66\u0f0b\u0f54\u0f0b", "\u0f66\u0f92\u0fb2 \u0f60\u0f72\u0f0b \u0f63\u0fb7\u0f0b \u0f63\u0f0b \u0f42\u0f53\u0f66\u0f0b"], "\u0f66\u0fa3\u0f62\u0f0b": ["\u0f63\u0fb7\u0f0b \u0f62\u0fa3\u0f58\u0f0b\u0f54\u0f0b \u0f51\u0fb2\u0f74\u0f42\u0f0b \u0f63\u0f0b", "\u0f42\u0fb2\u0f42\u0f0b\u0f54\u0f0b", "\u0f66\u0f92\u0fb2 \u0f60\u0f72\u0f0b \u0f63\u0fb7\u0f0b \u0f63\u0f0b \u0f42\u0f53\u0f66\u0f0b"]}]}, {"38": [["\u300a\u0f56\u0f66\u0f92\u0f7c\u0f58\u300b\u0f5e\u0f7a\u0f66\u0f0b\u0f54\u0f0d\u3010\u3008\u0f66\u0f92\u0f7c\u0f58\u3009\u0f42\u0f72\u0f0b \u0f58\u0f0b\u0f60\u0f7c\u0f44\u0f66\u0f0b\u0f54\u0f0d \u0f50\u0f0b\u0f51\u0f51\u0f0b\u0f54\u0f0d\u3011", "\u300a\u0f66\u0f92\u0f7c\u0f58\u300b\u0f5e\u0f7a\u0f66\u0f0b\u0f54\u0f0d\u3010\u3008\u0f66\u0f92\u0f7c\u0f58\u3009\u0f42\u0f72\u0f0b \u0f51\u0f0b\u0f63\u0f9f\u0f0b\u0f56\u0f0d \u0f50\u0f0b\u0f51\u0f51\u0f0b\u0f54\u0f0d\u3011"], {"\u0f54\u0f7a\u0f0b": ["\u0f5e\u0f72\u0f42\u0f0b \u0f63\u0f0b \u0f60\u0f47\u0f7c\u0f63\u0f0b #\u0f49\u0f7c\u0f42\u0f0b \u0f4f\u0f74\u0f0b", "\u0f56\u0f66\u0f92\u0f7c\u0f58\u0f0b", "\u0f51\u0f74\u0f0b \u0f62\u0f74\u0f44\u0f0b\u0f56\u0f0b \u0f61\u0f44\u0f0b \u0f58\u0f0b"], "\u0f66\u0fa1\u0f7a\u0f0b": ["\u0f5e\u0f72\u0f42\u0f0b \u0f63\u0f0b \u0f60\u0f47\u0f7c\u0f63\u0f0b #\u0f49\u0f7c\u0f42\u0f0b \u0f4f\u0f74\u0f0b", "\u0f66\u0f92\u0f7c\u0f58\u0f0b", "\u0f51\u0f74\u0f0b \u0f62\u0f74\u0f44\u0f0b\u0f56\u0f0b \u0f61\u0f44\u0f0b \u0f58\u0f0b"], "\u0f66\u0fa3\u0f62\u0f0b": ["\u0f5e\u0f72\u0f42\u0f0b \u0f63\u0f0b \u0f60\u0f47\u0f7c\u0f63\u0f0b #\u0f49\u0f7c\u0f42\u0f0b \u0f4f\u0f74\u0f0b", "\u0f56\u0f66\u0f92\u0f7c\u0f58\u0f0b", "\u0f51\u0f74\u0f0b \u0f62\u0f74\u0f44\u0f0b\u0f56\u0f0b \u0f61\u0f44\u0f0b \u0f58\u0f0b"]}]}, {"42": [["\u300a\u0f56\u0f4f\u0f44\u300b\u0f5e\u0f7a\u0f66\u0f0b\u0f54\u0f0d\u3010\u3008\u0f42\u0f4f\u0f7c\u0f44\u3009\u0f42\u0f72\u0f0b \u0f60\u0f51\u0f66\u0f0b\u0f54\u0f0d\u3011\u3010\u3008\u0f42\u0f4f\u0f7c\u0f44\u3009\u0f42\u0f72\u0f0b \u0f60\u0f51\u0f66\u0f0b\u0f54\u0f0d \u0f50\u0f0b\u0f51\u0f51\u0f0b\u0f54\u0f0d\u3011", "\u300a\u0f42\u0f4f\u0f44\u300b\u0f5e\u0f7a\u0f66\u0f0b\u0f54\u0f0d\u3010\u3008\u0f42\u0f4f\u0f7c\u0f44\u3009\u0f42\u0f72\u0f0b \u0f58\u0f0b\u0f60\u0f7c\u0f44\u0f66\u0f0b\u0f54\u0f0d\u3011\u3010\u3008\u0f42\u0f4f\u0f7c\u0f44\u3009\u0f42\u0f72\u0f0b \u0f58\u0f0b\u0f60\u0f7c\u0f44\u0f66\u0f0b\u0f54\u0f0d \u0f50\u0f0b\u0f51\u0f51\u0f0b\u0f54\u0f0d\u3011"], {"\u0f54\u0f7a\u0f0b": ["\u0f54\u0f0b \u0f51\u0f44 \u0f0b\u0f0d_ \u0f46\u0f74\u0f0b \u0f66\u0fa6\u0fb1\u0f72\u0f53\u0f0b", "\u0f56\u0f4f\u0f44", "\u0f0b\u0f0d_ \u0f56\u0f5e\u0f72\u0f0b\u0f54\u0f0b \u0f46\u0f7c\u0f66\u0f0b\u0f49\u0f72\u0f51\u0f0b"], "\u0f66\u0fa1\u0f7a\u0f0b": ["\u0f54\u0f0b \u0f51\u0f44 \u0f0b\u0f0d_ \u0f46\u0f74\u0f0b \u0f66\u0fa6\u0fb1\u0f72\u0f53\u0f0b", "\u0f42\u0f4f\u0f44", "\u0f0b\u0f0d_ \u0f56\u0f5e\u0f72\u0f0b\u0f54\u0f0b \u0f46\u0f7c\u0f66\u0f0b\u0f49\u0f72\u0f51\u0f0b"], "\u0f66\u0fa3\u0f62\u0f0b": ["\u0f54\u0f0b \u0f51\u0f44 \u0f0b\u0f0d_ \u0f46\u0f74\u0f0b \u0f66\u0fa6\u0fb1\u0f72\u0f53\u0f0b", "\u0f56\u0f4f\u0f44", "\u0f0b\u0f0d_ \u0f56\u0f5e\u0f72\u0f0b\u0f54\u0f0b \u0f46\u0f7c\u0f66\u0f0b\u0f49\u0f72\u0f51\u0f0b"]}]}], "diff_verb": [], "not_sure": []}}, "dunno": {"long_diff": [{"34": [{"\u0f54\u0f7a\u0f0b": ["\u0f62\u0f9f\u0f7c\u0f42\u0f0b \u0f58\u0f5a\u0f53\u0f0b\u0f58 \u0f60\u0f72\u0f0b \u0f61\u0f72\u0f51", "\u0f0d_\u0f0b  \u0f46\u0f7c\u0f66\u0f0b\u0f49\u0f72\u0f51\u0f0b \u0f5f\u0f56\u0f0b\u0f58\u0f7c \u0f60\u0f72\u0f0b \u0f61\u0f72\u0f51", "\u0f0d_ \u0f46\u0f7c\u0f66\u0f0b\u0f49\u0f72\u0f51\u0f0b \u0f5f\u0f56\u0f0b\u0f58\u0f7c \u0f60\u0f72\u0f0b \u0f66\u0fa4\u0fb1\u0f7c\u0f51\u0f0b"], "\u0f66\u0fa1\u0f7a\u0f0b": ["\u0f62\u0f9f\u0f7c\u0f42\u0f0b \u0f58\u0f5a\u0f53\u0f0b\u0f58 \u0f60\u0f72\u0f0b \u0f61\u0f72\u0f51", "", "\u0f0d_ \u0f46\u0f7c\u0f66\u0f0b\u0f49\u0f72\u0f51\u0f0b \u0f5f\u0f56\u0f0b\u0f58\u0f7c \u0f60\u0f72\u0f0b \u0f66\u0fa4\u0fb1\u0f7c\u0f51\u0f0b"], "\u0f66\u0fa3\u0f62\u0f0b": ["\u0f62\u0f9f\u0f7c\u0f42\u0f0b \u0f58\u0f5a\u0f53\u0f0b\u0f58 \u0f60\u0f72\u0f0b \u0f61\u0f72\u0f51", "\u0f0d_\u0f0b  \u0f46\u0f7c\u0f66\u0f0b\u0f49\u0f72\u0f51\u0f0b \u0f5f\u0f56\u0f0b\u0f58\u0f7c \u0f60\u0f72\u0f0b \u0f61\u0f72\u0f51", "\u0f0d_ \u0f46\u0f7c\u0f66\u0f0b\u0f49\u0f72\u0f51\u0f0b \u0f5f\u0f56\u0f0b\u0f58\u0f7c \u0f60\u0f72\u0f0b \u0f66\u0fa4\u0fb1\u0f7c\u0f51\u0f0b"]}]}], "no_diff": [{"3": [{"\u0f54\u0f7a\u0f0b": [" \u0f0d_ \u0f62\u0f44\u0f0b \u0f66 \u0f62\u0f0b \u0f42\u0fb2\u0f7c\u0f63\u0f0b\u0f56\u0f0b", "\u0f62\u0f90\u0f44\u0f0b", "\u0f66\u0f92\u0fb2\u0f0b \u0f62\u0f44\u0f0b \u0f66\u0f44\u0f66\u0f0b \u0f44\u0f7c \u0f66\u0f0b \u0f42\u0f5f\u0f74\u0f44\u0f0b"], "\u0f66\u0fa1\u0f7a\u0f0b": [" \u0f0d_ \u0f62\u0f44\u0f0b \u0f66 \u0f62\u0f0b \u0f42\u0fb2\u0f7c\u0f63\u0f0b\u0f56\u0f0b", "\u0f62\u0f90\u0fb1\u0f7a\u0f53\u0f0b", "\u0f66\u0f92\u0fb2\u0f0b \u0f62\u0f44\u0f0b \u0f66\u0f44\u0f66\u0f0b \u0f44\u0f7c \u0f66\u0f0b \u0f42\u0f5f\u0f74\u0f44\u0f0b"], "\u0f66\u0fa3\u0f62\u0f0b": [" \u0f0d_ \u0f62\u0f44\u0f0b \u0f66 \u0f62\u0f0b \u0f42\u0fb2\u0f7c\u0f63\u0f0b\u0f56\u0f0b", "\u0f62\u0f90\u0f44\u0f0b", "\u0f66\u0f92\u0fb2\u0f0b \u0f62\u0f44\u0f0b \u0f66\u0f44\u0f66\u0f0b \u0f44\u0f7c \u0f66\u0f0b \u0f42\u0f5f\u0f74\u0f44\u0f0b"]}]}, {"5": [{"\u0f54\u0f7a\u0f0b": ["\u0f56\u0f62\u0f97\u0f7c\u0f51\u0f0b\u0f54\u0f0b \u0f58\u0f7a\u0f51\u0f0b\u0f54 \u0f60\u0f72\u0f0b", "\u0f66\u0f90\u0fb1\u0f7a\u0f0b \u0f58\u0f7a\u0f51\u0f0b", "\u0f51\u0f74\u0f0b \u0f42\u0f4f\u0f53\u0f0b \u0f63\u0f0b \u0f55\u0f7a\u0f56\u0f66\u0f0b \u0f66\u0f7c"], "\u0f66\u0fa1\u0f7a\u0f0b": ["\u0f56\u0f62\u0f97\u0f7c\u0f51\u0f0b\u0f54\u0f0b \u0f58\u0f7a\u0f51\u0f0b\u0f54 \u0f60\u0f72\u0f0b", "\u0f66\u0f90\u0fb1\u0f7a\u0f0b\u0f58\u0f46\u0f7a\u0f51\u0f0b", "\u0f51\u0f74\u0f0b \u0f42\u0f4f\u0f53\u0f0b \u0f63\u0f0b \u0f55\u0f7a\u0f56\u0f66\u0f0b \u0f66\u0f7c"], "\u0f66\u0fa3\u0f62\u0f0b": ["\u0f56\u0f62\u0f97\u0f7c\u0f51\u0f0b\u0f54\u0f0b \u0f58\u0f7a\u0f51\u0f0b\u0f54 \u0f60\u0f72\u0f0b", "\u0f66\u0f90\u0fb1\u0f7a\u0f0b \u0f58\u0f7a\u0f51\u0f0b", "\u0f51\u0f74\u0f0b \u0f42\u0f4f\u0f53\u0f0b \u0f63\u0f0b \u0f55\u0f7a\u0f56\u0f66\u0f0b \u0f66\u0f7c"]}]}, {"7": [{"\u0f54\u0f7a\u0f0b": ["\u0f42\u0f5f\u0f74\u0f44\u0f0b \u0f51\u0f44\u0f0b \u0f56\u0fb2\u0f63\u0f0b\u0f56 \u0f66 \u0f0d_", "", "\u0f66\u0f92\u0fb2\u0f0b \u0f56\u0f66\u0f92\u0fb1\u0f74\u0f62\u0f0b \u0f42\u0fb2\u0f42\u0f0b \u0f66\u0f9f\u0f7c\u0f44\u0f0b \u0f62\u0f44\u0f0b"], "\u0f66\u0fa1\u0f7a\u0f0b": ["\u0f42\u0f5f\u0f74\u0f44\u0f0b \u0f51\u0f44\u0f0b \u0f56\u0fb2\u0f63\u0f0b\u0f56 \u0f66 \u0f0d_", "\u0f44\u0f42\u0f0b", "\u0f66\u0f92\u0fb2\u0f0b \u0f56\u0f66\u0f92\u0fb1\u0f74\u0f62\u0f0b \u0f42\u0fb2\u0f42\u0f0b \u0f66\u0f9f\u0f7c\u0f44\u0f0b \u0f62\u0f44\u0f0b"], "\u0f66\u0fa3\u0f62\u0f0b": ["\u0f42\u0f5f\u0f74\u0f44\u0f0b \u0f51\u0f44\u0f0b \u0f56\u0fb2\u0f63\u0f0b\u0f56 \u0f66 \u0f0d_", "", "\u0f66\u0f92\u0fb2\u0f0b \u0f56\u0f66\u0f92\u0fb1\u0f74\u0f62\u0f0b \u0f42\u0fb2\u0f42\u0f0b \u0f66\u0f9f\u0f7c\u0f44\u0f0b \u0f62\u0f44\u0f0b"]}]}, {"9": [{"\u0f54\u0f7a\u0f0b": ["\u0f61\u0f63\u0f0b\u0f56 \u0f66\u0f0b \u0f56\u0f62\u0f97\u0f7c\u0f51\u0f0b\u0f54\u0f0b \u0f62\u0f44\u0f0b", "\u0f66\u0f9f\u0f7a\u0f44\u0f66\u0f0b \u0f66\u0f74\u0f0b", "\u0f46\u0f7c\u0f51\u0f0b\u0f54 \u0f66\u0f0b \u0f63\u0f9f\u0f0b\u0f56\u0f0b \u0f44\u0f7c \u0f66\u0f0b"], "\u0f66\u0fa1\u0f7a\u0f0b": ["\u0f61\u0f63\u0f0b\u0f56 \u0f66\u0f0b \u0f56\u0f62\u0f97\u0f7c\u0f51\u0f0b\u0f54\u0f0b \u0f62\u0f44\u0f0b", "\u0f66\u0f9f\u0f7a\u0f44\u0f0b \u0f51\u0f74\u0f0b", "\u0f46\u0f7c\u0f51\u0f0b\u0f54 \u0f66\u0f0b \u0f63\u0f9f\u0f0b\u0f56\u0f0b \u0f44\u0f7c \u0f66\u0f0b"], "\u0f66\u0fa3\u0f62\u0f0b": ["\u0f61\u0f63\u0f0b\u0f56 \u0f66\u0f0b \u0f56\u0f62\u0f97\u0f7c\u0f51\u0f0b\u0f54\u0f0b \u0f62\u0f44\u0f0b", "\u0f66\u0f9f\u0f7a\u0f44\u0f66\u0f0b \u0f66\u0f74\u0f0b", "\u0f46\u0f7c\u0f51\u0f0b\u0f54 \u0f66\u0f0b \u0f63\u0f9f\u0f0b\u0f56\u0f0b \u0f44\u0f7c \u0f66\u0f0b"]}]}, {"13": [{"\u0f54\u0f7a\u0f0b": ["\u0f62\u0f92\u0fb1\u0f0b \u0f50\u0f7c\u0f51\u0f0b\u0f62\u0f92\u0f63\u0f0b \u0f51\u0f74\u0f0b \u0f63\u0f0b", "\u0f5f\u0fb3\u0f0b\u0f56\u0f0b", "\u0f5e\u0f7a\u0f66\u0f0b \u0f56\u0fb1 \u0f60\u0f7c \u0f0d_\u0f0d \u0f64\u0f7a\u0f66\u0f0b"], "\u0f66\u0fa1\u0f7a\u0f0b": ["\u0f62\u0f92\u0fb1\u0f0b \u0f50\u0f7c\u0f51\u0f0b\u0f62\u0f92\u0f63\u0f0b \u0f51\u0f74\u0f0b \u0f63\u0f0b", "\u0f56\u0f5f\u0fb3\u0f0b\u0f56\u0f0b", "\u0f5e\u0f7a\u0f66\u0f0b \u0f56\u0fb1 \u0f60\u0f7c \u0f0d_\u0f0d \u0f64\u0f7a\u0f66\u0f0b"], "\u0f66\u0fa3\u0f62\u0f0b": ["\u0f62\u0f92\u0fb1\u0f0b \u0f50\u0f7c\u0f51\u0f0b\u0f62\u0f92\u0f63\u0f0b \u0f51\u0f74\u0f0b \u0f63\u0f0b", "\u0f5f\u0fb3\u0f0b\u0f56\u0f0b", "\u0f5e\u0f7a\u0f66\u0f0b \u0f56\u0fb1 \u0f60\u0f7c \u0f0d_\u0f0d \u0f64\u0f7a\u0f66\u0f0b"]}]}, {"17": [{"\u0f54\u0f7a\u0f0b": ["\u0f62\u0f9f\u0f7c\u0f42\u0f66\u0f0b\u0f54 \u0f60\u0f72\u0f0b \u0f51\u0f74\u0f66\u0f0b \u0f51\u0f44 \u0f0b\u0f0d_", "", "\u0f56\u0f5f\u0fb3\u0f0b\u0f56 \u0f60\u0f72\u0f0b \u0f51\u0f74\u0f66\u0f0b \u0f66\u0f7c\u0f0b \u0f5e\u0f7a\u0f66\u0f0b"], "\u0f66\u0fa1\u0f7a\u0f0b": ["\u0f62\u0f9f\u0f7c\u0f42\u0f66\u0f0b\u0f54 \u0f60\u0f72\u0f0b \u0f51\u0f74\u0f66\u0f0b \u0f51\u0f44 \u0f0b\u0f0d_", "\u0f63\u0f0b", "\u0f56\u0f5f\u0fb3\u0f0b\u0f56 \u0f60\u0f72\u0f0b \u0f51\u0f74\u0f66\u0f0b \u0f66\u0f7c\u0f0b \u0f5e\u0f7a\u0f66\u0f0b"], "\u0f66\u0fa3\u0f62\u0f0b": ["\u0f62\u0f9f\u0f7c\u0f42\u0f66\u0f0b\u0f54 \u0f60\u0f72\u0f0b \u0f51\u0f74\u0f66\u0f0b \u0f51\u0f44 \u0f0b\u0f0d_", "", "\u0f56\u0f5f\u0fb3\u0f0b\u0f56 \u0f60\u0f72\u0f0b \u0f51\u0f74\u0f66\u0f0b \u0f66\u0f7c\u0f0b \u0f5e\u0f7a\u0f66\u0f0b"]}]}, {"18": [{"\u0f54\u0f7a\u0f0b": ["\u0f62\u0f9f\u0f7c\u0f42\u0f66\u0f0b\u0f54 \u0f60\u0f72\u0f0b \u0f51\u0f74\u0f66\u0f0b \u0f53\u0f72\u0f0b \u0f60\u0f41\u0f7c\u0f62\u0f0b", "\u0f62\u0f90\u0fb1\u0f7a\u0f53\u0f0b", "\u0f56\u0f51\u0f42\u0f0b \u0f58\u0f7a\u0f51\u0f0b\u0f54 \u0f60\u0f7c \u0f0d_\u0f0d \u0f63\u0f0b"], "\u0f66\u0fa1\u0f7a\u0f0b": ["\u0f62\u0f9f\u0f7c\u0f42\u0f66\u0f0b\u0f54 \u0f60\u0f72\u0f0b \u0f51\u0f74\u0f66\u0f0b \u0f53\u0f72\u0f0b \u0f60\u0f41\u0f7c\u0f62\u0f0b", "\u0f45\u0f53\u0f0b", "\u0f56\u0f51\u0f42\u0f0b \u0f58\u0f7a\u0f51\u0f0b\u0f54 \u0f60\u0f7c \u0f0d_\u0f0d \u0f63\u0f0b"], "\u0f66\u0fa3\u0f62\u0f0b": ["\u0f62\u0f9f\u0f7c\u0f42\u0f66\u0f0b\u0f54 \u0f60\u0f72\u0f0b \u0f51\u0f74\u0f66\u0f0b \u0f53\u0f72\u0f0b \u0f60\u0f41\u0f7c\u0f62\u0f0b", "\u0f62\u0f90\u0fb1\u0f7a\u0f53\u0f0b", "\u0f56\u0f51\u0f42\u0f0b \u0f58\u0f7a\u0f51\u0f0b\u0f54 \u0f60\u0f7c \u0f0d_\u0f0d \u0f63\u0f0b"]}]}, {"19": [{"\u0f54\u0f7a\u0f0b": ["\u0f56\u0f51\u0f42\u0f0b \u0f58\u0f7a\u0f51\u0f0b\u0f54 \u0f60\u0f7c \u0f0d_\u0f0d \u0f63\u0f0b", "\u0f56\u0f5f\u0fb3\u0f7c \u0f66\u0f0b\u0f54 \u0f60\u0f72\u0f0b", "\u0f51\u0f74\u0f66\u0f0b \u0f53\u0f72\u0f0b \u0f46\u0f7c\u0f66\u0f0b\u0f49\u0f72\u0f51\u0f0b"], "\u0f66\u0fa1\u0f7a\u0f0b": ["\u0f56\u0f51\u0f42\u0f0b \u0f58\u0f7a\u0f51\u0f0b\u0f54 \u0f60\u0f7c \u0f0d_\u0f0d \u0f63\u0f0b", "\u0f5f\u0fb3\u0f7c\u0f66\u0f0b\u0f54 \u0f60\u0f72\u0f0b", "\u0f51\u0f74\u0f66\u0f0b \u0f53\u0f72\u0f0b \u0f46\u0f7c\u0f66\u0f0b\u0f49\u0f72\u0f51\u0f0b"], "\u0f66\u0fa3\u0f62\u0f0b": ["\u0f56\u0f51\u0f42\u0f0b \u0f58\u0f7a\u0f51\u0f0b\u0f54 \u0f60\u0f7c \u0f0d_\u0f0d \u0f63\u0f0b", "\u0f56\u0f5f\u0fb3\u0f7c \u0f66\u0f0b\u0f54 \u0f60\u0f72\u0f0b", "\u0f51\u0f74\u0f66\u0f0b \u0f53\u0f72\u0f0b \u0f46\u0f7c\u0f66\u0f0b\u0f49\u0f72\u0f51\u0f0b"]}]}, {"22": [{"\u0f54\u0f7a\u0f0b": ["\u0f54 \u0f60\u0f72\u0f0b \u0f56\u0f66\u0f58\u0f0b\u0f42\u0f4f\u0f53\u0f0b \u0f53\u0f72 \u0f0d_", "\u0f63\u0f0b", "#\u0f42\u0f53\u0f51\u0f0b \u0f63\u0f0b \u0f55\u0f56\u0f0b\u0f54 \u0f66\u0f0b \u0f66\u0f90\u0fb1\u0f7a\u0f0b"], "\u0f66\u0fa1\u0f7a\u0f0b": ["\u0f54 \u0f60\u0f72\u0f0b \u0f56\u0f66\u0f58\u0f0b\u0f42\u0f4f\u0f53\u0f0b \u0f53\u0f72 \u0f0d_", "\u0f63\u0f74\u0f66\u0f0b", "#\u0f42\u0f53\u0f51\u0f0b \u0f63\u0f0b \u0f55\u0f56\u0f0b\u0f54 \u0f66\u0f0b \u0f66\u0f90\u0fb1\u0f7a\u0f0b"], "\u0f66\u0fa3\u0f62\u0f0b": ["\u0f54 \u0f60\u0f72\u0f0b \u0f56\u0f66\u0f58\u0f0b\u0f42\u0f4f\u0f53\u0f0b \u0f53\u0f72 \u0f0d_", "\u0f63\u0f0b", "#\u0f42\u0f53\u0f51\u0f0b \u0f63\u0f0b \u0f55\u0f56\u0f0b\u0f54 \u0f66\u0f0b \u0f66\u0f90\u0fb1\u0f7a\u0f0b"]}]}, {"23": [{"\u0f54\u0f7a\u0f0b": ["\u0f62\u0f7a\u0f0b\u0f56\u0f0b \u0f58\u0f7a\u0f51\u0f0b\u0f54 \u0f60\u0f7c \u0f0d_\u0f0d", "\u0f55\u0fb2\u0f7a\u0f44\u0f0b\u0f56 \u0f60\u0f72\u0f0b", "\u0f66\u0f92\u0fb2\u0f0b \u0f63\u0f0b \u0f63\u0f94\u0f0b \u0f66\u0f9f\u0f7a \u0f0d "], "\u0f66\u0fa1\u0f7a\u0f0b": ["\u0f62\u0f7a\u0f0b\u0f56\u0f0b \u0f58\u0f7a\u0f51\u0f0b\u0f54 \u0f60\u0f7c \u0f0d_\u0f0d", "\u0f55\u0fb2\u0f51\u0f0b\u0f54 \u0f60\u0f72\u0f0b", "\u0f66\u0f92\u0fb2\u0f0b \u0f63\u0f0b \u0f63\u0f94\u0f0b \u0f66\u0f9f\u0f7a \u0f0d "], "\u0f66\u0fa3\u0f62\u0f0b": ["\u0f62\u0f7a\u0f0b\u0f56\u0f0b \u0f58\u0f7a\u0f51\u0f0b\u0f54 \u0f60\u0f7c \u0f0d_\u0f0d", "\u0f55\u0fb2\u0f7a\u0f44\u0f0b\u0f56 \u0f60\u0f72\u0f0b", "\u0f66\u0f92\u0fb2\u0f0b \u0f63\u0f0b \u0f63\u0f94\u0f0b \u0f66\u0f9f\u0f7a \u0f0d "]}]}, {"24": [{"\u0f54\u0f7a\u0f0b": ["\u0f42\u0f53\u0f66\u0f0b\u0f54 \u0f62\u0f0b \u0f56\u0fb1\u0f7a\u0f51\u0f0b\u0f54 \u0f60\u0f72\u0f0b \u0f63\u0f74\u0f66\u0f0b", "\u0f42\u0f44\u0f0b", "\u0f42\u0f72\u0f0b \u0f60\u0f41\u0f7c\u0f62\u0f0b\u0f63\u0f7c\u0f0b \u0f55\u0fb2\u0f7a\u0f44\u0f0b\u0f56\u0f0b"], "\u0f66\u0fa1\u0f7a\u0f0b": ["\u0f42\u0f53\u0f66\u0f0b\u0f54 \u0f62\u0f0b \u0f56\u0fb1\u0f7a\u0f51\u0f0b\u0f54 \u0f60\u0f72\u0f0b \u0f63\u0f74\u0f66\u0f0b", "\u0f44\u0f42\u0f0b", "\u0f42\u0f72\u0f0b \u0f60\u0f41\u0f7c\u0f62\u0f0b\u0f63\u0f7c\u0f0b \u0f55\u0fb2\u0f7a\u0f44\u0f0b\u0f56\u0f0b"], "\u0f66\u0fa3\u0f62\u0f0b": ["\u0f42\u0f53\u0f66\u0f0b\u0f54 \u0f62\u0f0b \u0f56\u0fb1\u0f7a\u0f51\u0f0b\u0f54 \u0f60\u0f72\u0f0b \u0f63\u0f74\u0f66\u0f0b", "\u0f42\u0f44\u0f0b", "\u0f42\u0f72\u0f0b \u0f60\u0f41\u0f7c\u0f62\u0f0b\u0f63\u0f7c\u0f0b \u0f55\u0fb2\u0f7a\u0f44\u0f0b\u0f56\u0f0b"]}]}, {"28": [{"\u0f54\u0f7a\u0f0b": ["\u0f40\u0fb1\u0f72\u0f0b \u0f49\u0f58\u0f66\u0f0b \u0f66\u0f74\u0f0b \u0f64\u0f62\u0f0b\u0f56 \u0f66\u0f0b", "", "\u0f66\u0fb3\u0f7c\u0f56\u0f0b\u0f58\u0f0b \u0f63\u0f0b \u0f44\u0f7a\u0f66\u0f0b \u0f64\u0f7a\u0f66\u0f0b"], "\u0f66\u0fa1\u0f7a\u0f0b": ["\u0f40\u0fb1\u0f72\u0f0b \u0f49\u0f58\u0f66\u0f0b \u0f66\u0f74\u0f0b \u0f64\u0f62\u0f0b\u0f56 \u0f66\u0f0b", "\u0f53\u0f0b", "\u0f66\u0fb3\u0f7c\u0f56\u0f0b\u0f58\u0f0b \u0f63\u0f0b \u0f44\u0f7a\u0f66\u0f0b \u0f64\u0f7a\u0f66\u0f0b"], "\u0f66\u0fa3\u0f62\u0f0b": ["\u0f40\u0fb1\u0f72\u0f0b \u0f49\u0f58\u0f66\u0f0b \u0f66\u0f74\u0f0b \u0f64\u0f62\u0f0b\u0f56 \u0f66\u0f0b", "", "\u0f66\u0fb3\u0f7c\u0f56\u0f0b\u0f58\u0f0b \u0f63\u0f0b \u0f44\u0f7a\u0f66\u0f0b \u0f64\u0f7a\u0f66\u0f0b"]}]}, {"41": [{"\u0f54\u0f7a\u0f0b": ["\u0f42\u0f66\u0f74\u0f58\u0f0b\u0f54 \u0f66\u0f0b \u0f46\u0f7c\u0f66\u0f0b \u0f66\u0f90\u0f74\u0f0b", "\u0f50\u0f7c\u0f56\u0f0b\u0f54 \u0f60\u0f7c", "\u0f0d_\u0f0d #\u0f67\u0f71\u0f74\u0f7e\u0f0b \u0f42\u0f72\u0f0b \u0f60\u0f7c\u0f51\u0f0b \u0f5f\u0f7a\u0f62\u0f0b"], "\u0f66\u0fa1\u0f7a\u0f0b": ["\u0f42\u0f66\u0f74\u0f58\u0f0b\u0f54 \u0f66\u0f0b \u0f46\u0f7c\u0f66\u0f0b \u0f66\u0f90\u0f74\u0f0b", "\u0f50\u0f7c\u0f56\u0f0b \u0f56\u0f7c", "\u0f0d_\u0f0d #\u0f67\u0f71\u0f74\u0f7e\u0f0b \u0f42\u0f72\u0f0b \u0f60\u0f7c\u0f51\u0f0b \u0f5f\u0f7a\u0f62\u0f0b"], "\u0f66\u0fa3\u0f62\u0f0b": ["\u0f42\u0f66\u0f74\u0f58\u0f0b\u0f54 \u0f66\u0f0b \u0f46\u0f7c\u0f66\u0f0b \u0f66\u0f90\u0f74\u0f0b", "\u0f50\u0f7c\u0f56\u0f0b\u0f54 \u0f60\u0f7c", "\u0f0d_\u0f0d #\u0f67\u0f71\u0f74\u0f7e\u0f0b \u0f42\u0f72\u0f0b \u0f60\u0f7c\u0f51\u0f0b \u0f5f\u0f7a\u0f62\u0f0b"]}]}, {"43": [{"\u0f54\u0f7a\u0f0b": [" \u0f0d_ \u0f42\u0f49\u0f72\u0f66\u0f0b\u0f54\u0f0b \u0f63\u0f0b \u0f46\u0f74\u0f0b", "", "\u0f63\u0f9f\u0f0b\u0f56\u0f74 \u0f62\u0f0b \u0f51\u0f58\u0f72\u0f42\u0f66 \u0f0d_ \u0f42\u0f66\u0f74\u0f58\u0f0b"], "\u0f66\u0fa1\u0f7a\u0f0b": [" \u0f0d_ \u0f42\u0f49\u0f72\u0f66\u0f0b\u0f54\u0f0b \u0f63\u0f0b \u0f46\u0f74\u0f0b", "\u0f5f\u0fb3\u0f0b", "\u0f63\u0f9f\u0f0b\u0f56\u0f74 \u0f62\u0f0b \u0f51\u0f58\u0f72\u0f42\u0f66 \u0f0d_ \u0f42\u0f66\u0f74\u0f58\u0f0b"], "\u0f66\u0fa3\u0f62\u0f0b": [" \u0f0d_ \u0f42\u0f49\u0f72\u0f66\u0f0b\u0f54\u0f0b \u0f63\u0f0b \u0f46\u0f74\u0f0b", "", "\u0f63\u0f9f\u0f0b\u0f56\u0f74 \u0f62\u0f0b \u0f51\u0f58\u0f72\u0f42\u0f66 \u0f0d_ \u0f42\u0f66\u0f74\u0f58\u0f0b"]}]}], "short_diff": [{"6": [{"\u0f54\u0f7a\u0f0b": ["\u0f45\u0f72 \u0f66\u0f0b \u0f64\u0f7a\u0f66\u0f0b \u0f53 \u0f0d_", "\u0f66\u0f7a\u0f58\u0f66\u0f0b\u0f45\u0f53\u0f0b", "\u0f63\u0f0b #\u0f42\u0f51\u0f7c\u0f66\u0f0b\u0f54\u0f0b \u0f58\u0f7a\u0f51\u0f0b\u0f54 \u0f66\u0f0b"], "\u0f66\u0fa1\u0f7a\u0f0b": ["\u0f45\u0f72 \u0f66\u0f0b \u0f64\u0f7a\u0f66\u0f0b \u0f53 \u0f0d_", "\u0f66\u0f7a\u0f58\u0f66\u0f0b", "\u0f63\u0f0b #\u0f42\u0f51\u0f7c\u0f66\u0f0b\u0f54\u0f0b \u0f58\u0f7a\u0f51\u0f0b\u0f54 \u0f66\u0f0b"], "\u0f66\u0fa3\u0f62\u0f0b": ["\u0f45\u0f72 \u0f66\u0f0b \u0f64\u0f7a\u0f66\u0f0b \u0f53 \u0f0d_", "\u0f66\u0f7a\u0f58\u0f66\u0f0b\u0f45\u0f53\u0f0b", "\u0f63\u0f0b #\u0f42\u0f51\u0f7c\u0f66\u0f0b\u0f54\u0f0b \u0f58\u0f7a\u0f51\u0f0b\u0f54 \u0f66\u0f0b"]}]}, {"11": [{"\u0f54\u0f7a\u0f0b": ["\u0f42\u0f4f\u0f53\u0f0b \u0f53\u0f72 \u0f0d_ \u0f61\u0f74\u0f63\u0f0b", "\u0f56\u0fb1\u0f74\u0f44\u0f0b", "\u0f56\u0f4f\u0f56\u0f0b\u0f54 \u0f66\u0f0b \u0f66\u0f92\u0fb2\u0f0b \u0f42\u0f53\u0f66\u0f0b\u0f54\u0f0b"], "\u0f66\u0fa1\u0f7a\u0f0b": ["\u0f42\u0f4f\u0f53\u0f0b \u0f53\u0f72 \u0f0d_ \u0f61\u0f74\u0f63\u0f0b", "\u0f56\u0fb1\u0f74\u0f44\u0f0b\u0f56\u0f0b", "\u0f56\u0f4f\u0f56\u0f0b\u0f54 \u0f66\u0f0b \u0f66\u0f92\u0fb2\u0f0b \u0f42\u0f53\u0f66\u0f0b\u0f54\u0f0b"], "\u0f66\u0fa3\u0f62\u0f0b": ["\u0f42\u0f4f\u0f53\u0f0b \u0f53\u0f72 \u0f0d_ \u0f61\u0f74\u0f63\u0f0b", "\u0f56\u0fb1\u0f74\u0f44\u0f0b", "\u0f56\u0f4f\u0f56\u0f0b\u0f54 \u0f66\u0f0b \u0f66\u0f92\u0fb2\u0f0b \u0f42\u0f53\u0f66\u0f0b\u0f54\u0f0b"]}]}, {"32": [{"\u0f54\u0f7a\u0f0b": ["\u0f63\u0f42\u0f0b\u0f54\u0f0b \u0f58\u0f49\u0f58\u0f0b \u0f42\u0f5e\u0f42\u0f0b \u0f4f\u0f74\u0f0b", "\u0f56\u0f45\u0f66\u0f0b \u0f63", "\u0f0d_ \u0f58\u0f72\u0f42\u0f0b \u0f66\u0fa3\u0f0b \u0f62\u0fa9\u0f7a \u0f62\u0f0b \u0f55\u0f56\u0f0b"], "\u0f66\u0fa1\u0f7a\u0f0b": ["\u0f63\u0f42\u0f0b\u0f54\u0f0b \u0f58\u0f49\u0f58\u0f0b \u0f42\u0f5e\u0f42\u0f0b \u0f4f\u0f74\u0f0b", "\u0f56\u0f45\u0f66", "\u0f0d_ \u0f58\u0f72\u0f42\u0f0b \u0f66\u0fa3\u0f0b \u0f62\u0fa9\u0f7a \u0f62\u0f0b \u0f55\u0f56\u0f0b"], "\u0f66\u0fa3\u0f62\u0f0b": ["\u0f63\u0f42\u0f0b\u0f54\u0f0b \u0f58\u0f49\u0f58\u0f0b \u0f42\u0f5e\u0f42\u0f0b \u0f4f\u0f74\u0f0b", "\u0f56\u0f45\u0f66\u0f0b \u0f63", "\u0f0d_ \u0f58\u0f72\u0f42\u0f0b \u0f66\u0fa3\u0f0b \u0f62\u0fa9\u0f7a \u0f62\u0f0b \u0f55\u0f56\u0f0b"]}]}, {"33": [{"\u0f54\u0f7a\u0f0b": ["\u0f56 \u0f66\u0f0b \u0f66\u0fa3\u0f44\u0f0b \u0f66\u0f9f\u0f7c\u0f44\u0f0b \u0f62\u0f97\u0f7a\u0f66\u0f0b", "\u0f60\u0f5b\u0f72\u0f53\u0f0b\u0f54\u0f0b", "\u0f58\u0f7a\u0f51\u0f0b\u0f54 \u0f66\u0f0b \u0f42\u0fb2\u0f7c\u0f63\u0f0b\u0f56\u0f0b \u0f5e\u0f7a\u0f66\u0f0b"], "\u0f66\u0fa1\u0f7a\u0f0b": ["\u0f56 \u0f66\u0f0b \u0f66\u0fa3\u0f44\u0f0b \u0f66\u0f9f\u0f7c\u0f44\u0f0b \u0f62\u0f97\u0f7a\u0f66\u0f0b", "\u0f60\u0f5b\u0f72\u0f53\u0f0b", "\u0f58\u0f7a\u0f51\u0f0b\u0f54 \u0f66\u0f0b \u0f42\u0fb2\u0f7c\u0f63\u0f0b\u0f56\u0f0b \u0f5e\u0f7a\u0f66\u0f0b"], "\u0f66\u0fa3\u0f62\u0f0b": ["\u0f56 \u0f66\u0f0b \u0f66\u0fa3\u0f44\u0f0b \u0f66\u0f9f\u0f7c\u0f44\u0f0b \u0f62\u0f97\u0f7a\u0f66\u0f0b", "\u0f60\u0f5b\u0f72\u0f53\u0f0b\u0f54\u0f0b", "\u0f58\u0f7a\u0f51\u0f0b\u0f54 \u0f66\u0f0b \u0f42\u0fb2\u0f7c\u0f63\u0f0b\u0f56\u0f0b \u0f5e\u0f7a\u0f66\u0f0b"]}]}, {"35": [{"\u0f54\u0f7a\u0f0b": ["\u0f66\u0f94\u0f7c\u0f53\u0f0b \u0f51\u0f74\u0f0b \u0f56\u0f66\u0f90\u0fb1\u0f7a\u0f51\u0f0b\u0f54 \u0f60\u0f72\u0f0b", "\u0f62\u0f72\u0f58\u0f0b", "\u0f51\u0f54\u0f60\u0f0b\u0f56\u0f7c\u0f0b \u0f42\u0f45\u0f72\u0f42\u0f0b\u0f54 \u0f60\u0f58 \u0f0d "], "\u0f66\u0fa1\u0f7a\u0f0b": ["\u0f66\u0f94\u0f7c\u0f53\u0f0b \u0f51\u0f74\u0f0b \u0f56\u0f66\u0f90\u0fb1\u0f7a\u0f51\u0f0b\u0f54 \u0f60\u0f72\u0f0b", "\u0f62\u0f72\u0f58\u0f0b\u0f54\u0f0b", "\u0f51\u0f54\u0f60\u0f0b\u0f56\u0f7c\u0f0b \u0f42\u0f45\u0f72\u0f42\u0f0b\u0f54 \u0f60\u0f58 \u0f0d "], "\u0f66\u0fa3\u0f62\u0f0b": ["\u0f66\u0f94\u0f7c\u0f53\u0f0b \u0f51\u0f74\u0f0b \u0f56\u0f66\u0f90\u0fb1\u0f7a\u0f51\u0f0b\u0f54 \u0f60\u0f72\u0f0b", "\u0f62\u0f72\u0f58\u0f0b\u0f54\u0f0b", "\u0f51\u0f54\u0f60\u0f0b\u0f56\u0f7c\u0f0b \u0f42\u0f45\u0f72\u0f42\u0f0b\u0f54 \u0f60\u0f58 \u0f0d "]}]}, {"37": [{"\u0f54\u0f7a\u0f0b": ["\u0f51\u0f7a\u0f0b \u0f42\u0f0b \u0f63\u0f9f\u0f62\u0f0b \u0f55\u0fb1\u0f7a\u0f0b \u0f63\u0f0b", "\u0f58\u0f0b \u0f63\u0f0b \u0f66\u0f92\u0f7c\u0f58\u0f0b", "\u0f58\u0f7c \u0f0d_\u0f0d \u0f51\u0f7a\u0f0b\u0f63\u0f9f\u0f62\u0f0b \u0f56\u0fb1\u0f66\u0f0b"], "\u0f66\u0fa1\u0f7a\u0f0b": ["\u0f51\u0f7a\u0f0b \u0f42\u0f0b \u0f63\u0f9f\u0f62\u0f0b \u0f55\u0fb1\u0f7a\u0f0b \u0f63\u0f0b", "\u0f56\u0f66\u0f92\u0f7c\u0f58\u0f0b", "\u0f58\u0f7c \u0f0d_\u0f0d \u0f51\u0f7a\u0f0b\u0f63\u0f9f\u0f62\u0f0b \u0f56\u0fb1\u0f66\u0f0b"], "\u0f66\u0fa3\u0f62\u0f0b": ["\u0f51\u0f7a\u0f0b \u0f42\u0f0b \u0f63\u0f9f\u0f62\u0f0b \u0f55\u0fb1\u0f7a\u0f0b \u0f63\u0f0b", "\u0f58\u0f0b \u0f63\u0f0b \u0f66\u0f92\u0f7c\u0f58\u0f0b", "\u0f58\u0f7c \u0f0d_\u0f0d \u0f51\u0f7a\u0f0b\u0f63\u0f9f\u0f62\u0f0b \u0f56\u0fb1\u0f66\u0f0b"]}]}, {"40": [{"\u0f54\u0f7a\u0f0b": [" \u0f0d_ \u0f42\u0f49\u0f72\u0f66\u0f0b\u0f54 \u0f66\u0f0b \u0f63\u0f7c\u0f44\u0f66\u0f0b \u0f66\u0f90\u0f74\u0f0b", "\u0f50\u0f7c\u0f56\u0f0b \u0f63", "\u0f0d_ \u0f42\u0f66\u0f74\u0f58\u0f0b\u0f54 \u0f66\u0f0b \u0f46\u0f7c\u0f66\u0f0b \u0f66\u0f90\u0f74\u0f0b"], "\u0f66\u0fa1\u0f7a\u0f0b": [" \u0f0d_ \u0f42\u0f49\u0f72\u0f66\u0f0b\u0f54 \u0f66\u0f0b \u0f63\u0f7c\u0f44\u0f66\u0f0b \u0f66\u0f90\u0f74\u0f0b", "\u0f50\u0f7c\u0f56", "\u0f0d_ \u0f42\u0f66\u0f74\u0f58\u0f0b\u0f54 \u0f66\u0f0b \u0f46\u0f7c\u0f66\u0f0b \u0f66\u0f90\u0f74\u0f0b"], "\u0f66\u0fa3\u0f62\u0f0b": [" \u0f0d_ \u0f42\u0f49\u0f72\u0f66\u0f0b\u0f54 \u0f66\u0f0b \u0f63\u0f7c\u0f44\u0f66\u0f0b \u0f66\u0f90\u0f74\u0f0b", "\u0f50\u0f7c\u0f56\u0f0b \u0f63", "\u0f0d_ \u0f42\u0f66\u0f74\u0f58\u0f0b\u0f54 \u0f66\u0f0b \u0f46\u0f7c\u0f66\u0f0b \u0f66\u0f90\u0f74\u0f0b"]}]}]}, "empty_notes": [{"20": [{"\u0f54\u0f7a\u0f0b": ["\u0f42\u0f5e\u0f72\u0f0b \u0f50\u0f7c\u0f42\u0f0b \u0f4f\u0f74\u0f0b \u0f55\u0f7a\u0f56\u0f66\u0f0b\u0f54 \u0f60\u0f7c", "\u0f0d\u0f0d_\u0f0d\u0f0d\u0f0d_\u0f0d", "\u0f62\u0f44\u0f0b \u0f42\u0f72\u0f0b \u0f60\u0f42\u0fb1\u0f74\u0f62\u0f0b \u0f56\u0fb1\u0f7a\u0f51\u0f0b \u0f66\u0f92\u0fb2\u0f0b"], "\u0f66\u0fa1\u0f7a\u0f0b": ["\u0f42\u0f5e\u0f72\u0f0b \u0f50\u0f7c\u0f42\u0f0b \u0f4f\u0f74\u0f0b \u0f55\u0f7a\u0f56\u0f66\u0f0b\u0f54 \u0f60\u0f7c", "\u0f0d_\u0f0d", "\u0f62\u0f44\u0f0b \u0f42\u0f72\u0f0b \u0f60\u0f42\u0fb1\u0f74\u0f62\u0f0b \u0f56\u0fb1\u0f7a\u0f51\u0f0b \u0f66\u0f92\u0fb2\u0f0b"], "\u0f66\u0fa3\u0f62\u0f0b": ["\u0f42\u0f5e\u0f72\u0f0b \u0f50\u0f7c\u0f42\u0f0b \u0f4f\u0f74\u0f0b \u0f55\u0f7a\u0f56\u0f66\u0f0b\u0f54 \u0f60\u0f7c", "\u0f0d\u0f0d_\u0f0d\u0f0d\u0f0d_\u0f0d", "\u0f62\u0f44\u0f0b \u0f42\u0f72\u0f0b \u0f60\u0f42\u0fb1\u0f74\u0f62\u0f0b \u0f56\u0fb1\u0f7a\u0f51\u0f0b \u0f66\u0f92\u0fb2\u0f0b"]}]}, {"29": [{"\u0f54\u0f7a\u0f0b": ["\u0f66\u0fb3\u0f7c\u0f56\u0f0b\u0f58\u0f0b \u0f63\u0f0b \u0f44\u0f7a\u0f66\u0f0b \u0f64\u0f7a\u0f66\u0f0b \u0f66\u0f90\u0fb1\u0f7a\u0f0b\u0f56 \u0f60\u0f7c \u0f0d_\u0f0d \u0f56\u0f66\u0f90\u0fb1\u0f7a\u0f51\u0f0b\u0f54 \u0f60\u0f72\u0f0b", "", ""], "\u0f66\u0fa1\u0f7a\u0f0b": ["\u0f66\u0fb3\u0f7c\u0f56\u0f0b\u0f58\u0f0b \u0f63\u0f0b \u0f44\u0f7a\u0f66\u0f0b \u0f64\u0f7a\u0f66\u0f0b \u0f66\u0f90\u0fb1\u0f7a\u0f0b\u0f56 \u0f60\u0f7c \u0f0d_\u0f0d \u0f56\u0f66\u0f90\u0fb1\u0f7a\u0f51\u0f0b\u0f54 \u0f60\u0f72\u0f0b", "", ""], "\u0f66\u0fa3\u0f62\u0f0b": ["\u0f66\u0fb3\u0f7c\u0f56\u0f0b\u0f58\u0f0b \u0f63\u0f0b \u0f44\u0f7a\u0f66\u0f0b \u0f64\u0f7a\u0f66\u0f0b \u0f66\u0f90\u0fb1\u0f7a\u0f0b\u0f56 \u0f60\u0f7c \u0f0d_\u0f0d \u0f56\u0f66\u0f90\u0fb1\u0f7a\u0f51\u0f0b\u0f54 \u0f60\u0f72\u0f0b", "", ""]}]}, {"30": [{"\u0f54\u0f7a\u0f0b": ["\u0f44\u0f7a\u0f66\u0f0b \u0f64\u0f7a\u0f66\u0f0b \u0f66\u0f90\u0fb1\u0f7a\u0f0b\u0f56 \u0f60\u0f7c", "\u0f0d\u0f0d_\u0f0d\u0f0d\u0f0d_\u0f0d", "\u0f56\u0f66\u0f90\u0fb1\u0f7a\u0f51\u0f0b\u0f54 \u0f60\u0f72\u0f0b \u0f51\u0f74\u0f66\u0f0b \u0f56\u0f5e\u0f72\u0f53\u0f0b \u0f51\u0f74\u0f0b"], "\u0f66\u0fa1\u0f7a\u0f0b": ["\u0f44\u0f7a\u0f66\u0f0b \u0f64\u0f7a\u0f66\u0f0b \u0f66\u0f90\u0fb1\u0f7a\u0f0b\u0f56 \u0f60\u0f7c", "\u0f0d_\u0f0d", "\u0f56\u0f66\u0f90\u0fb1\u0f7a\u0f51\u0f0b\u0f54 \u0f60\u0f72\u0f0b \u0f51\u0f74\u0f66\u0f0b \u0f56\u0f5e\u0f72\u0f53\u0f0b \u0f51\u0f74\u0f0b"], "\u0f66\u0fa3\u0f62\u0f0b": ["\u0f44\u0f7a\u0f66\u0f0b \u0f64\u0f7a\u0f66\u0f0b \u0f66\u0f90\u0fb1\u0f7a\u0f0b\u0f56 \u0f60\u0f7c", "\u0f0d\u0f0d_\u0f0d\u0f0d\u0f0d_\u0f0d", "\u0f56\u0f66\u0f90\u0fb1\u0f7a\u0f51\u0f0b\u0f54 \u0f60\u0f72\u0f0b \u0f51\u0f74\u0f66\u0f0b \u0f56\u0f5e\u0f72\u0f53\u0f0b \u0f51\u0f74\u0f0b"]}]}, {"31": [{"\u0f54\u0f7a\u0f0b": ["\u0f42\u0fb1\u0f72\u0f0b \u0f51\u0f7c\u0f53\u0f0b \u0f51\u0f74\u0f0b \u0f56\u0fb1\u0f74\u0f44\u0f0b\u0f56 \u0f60\u0f7c", "\u0f0d\u0f0d_\u0f0d\u0f0d\u0f0d_\u0f0d", "\u0f61\u0f72\u0f0b\u0f42\u0f7a\u0f0b \u0f60\u0f56\u0fb2\u0f74\u0f0b \u0f62\u0fa3\u0f58\u0f66\u0f0b \u0f58\u0f0b"], "\u0f66\u0fa1\u0f7a\u0f0b": ["\u0f42\u0fb1\u0f72\u0f0b \u0f51\u0f7c\u0f53\u0f0b \u0f51\u0f74\u0f0b \u0f56\u0fb1\u0f74\u0f44\u0f0b\u0f56 \u0f60\u0f7c", "\u0f0d_\u0f0d", "\u0f61\u0f72\u0f0b\u0f42\u0f7a\u0f0b \u0f60\u0f56\u0fb2\u0f74\u0f0b \u0f62\u0fa3\u0f58\u0f66\u0f0b \u0f58\u0f0b"], "\u0f66\u0fa3\u0f62\u0f0b": ["\u0f42\u0fb1\u0f72\u0f0b \u0f51\u0f7c\u0f53\u0f0b \u0f51\u0f74\u0f0b \u0f56\u0fb1\u0f74\u0f44\u0f0b\u0f56 \u0f60\u0f7c", "\u0f0d\u0f0d_\u0f0d\u0f0d\u0f0d_\u0f0d", "\u0f61\u0f72\u0f0b\u0f42\u0f7a\u0f0b \u0f60\u0f56\u0fb2\u0f74\u0f0b \u0f62\u0fa3\u0f58\u0f66\u0f0b \u0f58\u0f0b"]}]}, {"44": [{"\u0f54\u0f7a\u0f0b": ["\u0f58\u0f5b\u0f51\u0f0b\u0f54\u0f0b \u0f62\u0fab\u0f7c\u0f42\u0f66\u0f0b \u0f66\u0f7c \u0f0d\u0f0d_\u0f0d\u0f0d ", "", ""], "\u0f66\u0fa1\u0f7a\u0f0b": ["\u0f58\u0f5b\u0f51\u0f0b\u0f54\u0f0b \u0f62\u0fab\u0f7c\u0f42\u0f66\u0f0b \u0f66\u0f7c \u0f0d\u0f0d_\u0f0d\u0f0d ", "", ""], "\u0f66\u0fa3\u0f62\u0f0b": ["\u0f58\u0f5b\u0f51\u0f0b\u0f54\u0f0b \u0f62\u0fab\u0f7c\u0f42\u0f66\u0f0b \u0f66\u0f7c \u0f0d\u0f0d_\u0f0d\u0f0d ", "", ""]}]}], "manual_categorisation": {"long_difference": {"differing_formulation": [], "major_modification": []}, "manual_evaluation": {"derge_correct": [], "meaning_difference": {"great_diff": [], "medium_diff": [], "small_diff": []}}}, "ngram_freq": {"1": {"\u0f54\u0f7a\u0f0b": [], "\u0f66\u0fa1\u0f7a\u0f0b": [["\u0f42\u0f64\u0f72\u0f66", "51"]], "\u0f66\u0fa3\u0f62\u0f0b": []}, "10": {"\u0f54\u0f7a\u0f0b": [["\u0f56\u0f63\u0f9f\u0f0b\u0f56", "834"]], "\u0f66\u0fa1\u0f7a\u0f0b": [["\u0f63\u0f9f\u0f0b\u0f56", "239"]], "\u0f66\u0fa3\u0f62\u0f0b": [["\u0f56\u0f63\u0f9f\u0f0b\u0f56", "834"]]}, "11": {"\u0f54\u0f7a\u0f0b": [["\u0f56\u0fb1\u0f74\u0f44", "27"]], "\u0f66\u0fa1\u0f7a\u0f0b": [["\u0f56\u0fb1\u0f74\u0f44\u0f0b\u0f56", "1119"]], "\u0f66\u0fa3\u0f62\u0f0b": [["\u0f56\u0fb1\u0f74\u0f44", "27"]]}, "12": {"\u0f54\u0f7a\u0f0b": [["\u0f56\u0f5f\u0f74\u0f44", "11"], ["\u0f56\u0f5f\u0f74\u0f44\u0f0b\u0f51\u0f44", "50"]], "\u0f66\u0fa1\u0f7a\u0f0b": [["\u0f42\u0f5f\u0f74\u0f44", "5"], ["\u0f42\u0f5f\u0f74\u0f44\u0f0b\u0f51\u0f44", "108"]], "\u0f66\u0fa3\u0f62\u0f0b": [["\u0f56\u0f5f\u0f74\u0f44", "11"], ["\u0f56\u0f5f\u0f74\u0f44\u0f0b\u0f51\u0f44", "50"]]}, "13": {"\u0f54\u0f7a\u0f0b": [["\u0f5f\u0fb3\u0f0b\u0f56", "7608"], ["\u0f63\u0f0b\u0f5f\u0fb3\u0f0b\u0f56", "280"], ["\u0f5f\u0fb3\u0f0b\u0f56\u0f0b\u0f5e\u0f7a\u0f66", "171"]], "\u0f66\u0fa1\u0f7a\u0f0b": [["\u0f56\u0f5f\u0fb3\u0f0b\u0f56", "51"]], "\u0f66\u0fa3\u0f62\u0f0b": [["\u0f5f\u0fb3\u0f0b\u0f56", "7608"], ["\u0f63\u0f0b\u0f5f\u0fb3\u0f0b\u0f56", "280"], ["\u0f5f\u0fb3\u0f0b\u0f56\u0f0b\u0f5e\u0f7a\u0f66", "171"]]}, "14": {"\u0f54\u0f7a\u0f0b": [["\u0f56\u0f64\u0f72\u0f42", "89"]], "\u0f66\u0fa1\u0f7a\u0f0b": [["\u0f42\u0f64\u0f72\u0f66", "51"]], "\u0f66\u0fa3\u0f62\u0f0b": [["\u0f56\u0f64\u0f72\u0f42", "89"]]}, "15": {"\u0f54\u0f7a\u0f0b": [["\u0f56\u0f45\u0f51\u0f0b\u0f54\u0f66", "330"]], "\u0f66\u0fa1\u0f7a\u0f0b": [], "\u0f66\u0fa3\u0f62\u0f0b": [["\u0f56\u0f45\u0f51\u0f0b\u0f54\u0f66", "330"]]}, "16": {"\u0f54\u0f7a\u0f0b": [["\u0f63\u0f66", "5885"], ["\u0f63\u0f66\u0f0b\u0f58\u0f72", "1612"]], "\u0f66\u0fa1\u0f7a\u0f0b": [["\u0f63", "33965"], ["\u0f63\u0f0b\u0f58\u0f72", "7899"], ["\u0f55\u0fb2\u0f7a\u0f44\u0f0b\u0f56\u0f0b\u0f63", "108"]], "\u0f66\u0fa3\u0f62\u0f0b": [["\u0f63\u0f66", "5885"], ["\u0f63\u0f66\u0f0b\u0f58\u0f72", "1612"]]}, "17": {"\u0f54\u0f7a\u0f0b": [["", "1"], ["\u0f0d_", "47"], ["\u0f56\u0f5f\u0fb3\u0f0b\u0f56", "51"]], "\u0f66\u0fa1\u0f7a\u0f0b": [["\u0f63", "33965"], ["\u0f0d_\u0f63", "1773"]], "\u0f66\u0fa3\u0f62\u0f0b": [["", "1"], ["\u0f0d_", "47"], ["\u0f56\u0f5f\u0fb3\u0f0b\u0f56", "51"]]}, "18": {"\u0f54\u0f7a\u0f0b": [["\u0f62\u0f90\u0fb1\u0f7a\u0f53", "54"]], "\u0f66\u0fa1\u0f7a\u0f0b": [["\u0f45\u0f53", "5389"], ["\u0f45\u0f53\u0f0b\u0f56\u0f51\u0f42", "94"], ["\u0f60\u0f41\u0f7c\u0f62\u0f0b\u0f45\u0f53", "65"]], "\u0f66\u0fa3\u0f62\u0f0b": [["\u0f62\u0f90\u0fb1\u0f7a\u0f53", "54"]]}, "19": {"\u0f54\u0f7a\u0f0b": [], "\u0f66\u0fa1\u0f7a\u0f0b": [["\u0f5f\u0fb3\u0f7c\u0f66\u0f0b\u0f54\u0f60\u0f72", "49"]], "\u0f66\u0fa3\u0f62\u0f0b": []}, "2": {"\u0f54\u0f7a\u0f0b": [["\u0f56\u0f66\u0f9f\u0f53\u0f0b\u0f4f\u0f7a", "226"], ["\u0f56\u0f66\u0f9f\u0f53\u0f0b\u0f4f\u0f7a\u0f0d_", "844"]], "\u0f66\u0fa1\u0f7a\u0f0b": [["\u0f56\u0f66\u0f9f\u0f53", "2152"], ["\u0f56\u0f66\u0f9f\u0f53\u0f0d_", "518"], ["\u0f51\u0f74\u0f0b\u0f56\u0f66\u0f9f\u0f53", "96"]], "\u0f66\u0fa3\u0f62\u0f0b": [["\u0f56\u0f66\u0f9f\u0f53\u0f0b\u0f4f\u0f7a", "226"], ["\u0f56\u0f66\u0f9f\u0f53\u0f0b\u0f4f\u0f7a\u0f0d_", "844"]]}, "20": {"\u0f54\u0f7a\u0f0b": [], "\u0f66\u0fa1\u0f7a\u0f0b": [["\u0f0d_\u0f0d", "997103"], ["\u0f60\u0f7c\u0f0d_\u0f0d", "419"], ["\u0f0d_\u0f0d\u0f62\u0f44", "7417"]], "\u0f66\u0fa3\u0f62\u0f0b": []}, "21": {"\u0f54\u0f7a\u0f0b": [["", "1"], ["\u0f62\u0f44", "1"], ["\u0f60\u0f42\u0fb1\u0f74\u0f62", "31151"]], "\u0f66\u0fa1\u0f7a\u0f0b": [["\u0f42\u0f72", "1276"], ["\u0f62\u0f44\u0f0b\u0f42\u0f72", "12122"]], "\u0f66\u0fa3\u0f62\u0f0b": [["", "1"], ["\u0f62\u0f44", "1"], ["\u0f60\u0f42\u0fb1\u0f74\u0f62", "31151"]]}, "22": {"\u0f54\u0f7a\u0f0b": [["\u0f63", "33965"], ["\u0f0d_\u0f63", "1773"]], "\u0f66\u0fa1\u0f7a\u0f0b": [["\u0f63\u0f74\u0f66", "295"], ["\u0f0d_\u0f63\u0f74\u0f66", "6719"]], "\u0f66\u0fa3\u0f62\u0f0b": [["\u0f63", "33965"], ["\u0f0d_\u0f63", "1773"]]}, "23": {"\u0f54\u0f7a\u0f0b": [["\u0f55\u0fb2\u0f7a\u0f44\u0f0b\u0f56\u0f60\u0f72", "490"]], "\u0f66\u0fa1\u0f7a\u0f0b": [["\u0f55\u0fb2\u0f51\u0f0b\u0f54\u0f60\u0f72", "103"]], "\u0f66\u0fa3\u0f62\u0f0b": [["\u0f55\u0fb2\u0f7a\u0f44\u0f0b\u0f56\u0f60\u0f72", "490"]]}, "24": {"\u0f54\u0f7a\u0f0b": [["\u0f42\u0f44", "44"], ["\u0f42\u0f44\u0f0b\u0f42\u0f72", "8014"], ["\u0f63\u0f74\u0f66\u0f0b\u0f42\u0f44", "120"]], "\u0f66\u0fa1\u0f7a\u0f0b": [["\u0f44\u0f42", "24"], ["\u0f44\u0f42\u0f0b\u0f42\u0f72", "1192"], ["\u0f63\u0f74\u0f66\u0f0b\u0f44\u0f42", "210"]], "\u0f66\u0fa3\u0f62\u0f0b": [["\u0f42\u0f44", "44"], ["\u0f42\u0f44\u0f0b\u0f42\u0f72", "8014"], ["\u0f63\u0f74\u0f66\u0f0b\u0f42\u0f44", "120"]]}, "25": {"\u0f54\u0f7a\u0f0b": [["\u0f42\u0fb2\u0f42\u0f0b\u0f54", "138"]], "\u0f66\u0fa1\u0f7a\u0f0b": [["\u0f42\u0fb2\u0f42\u0f66\u0f0b\u0f54", "201"]], "\u0f66\u0fa3\u0f62\u0f0b": [["\u0f42\u0fb2\u0f42\u0f0b\u0f54", "138"]]}, "26": {"\u0f54\u0f7a\u0f0b": [["\u0f42\u0f61\u0f7c\u0f0b\u0f56", "129"], ["\u0f58\u0f72\u0f0b\u0f42\u0f61\u0f7c\u0f0b\u0f56", "105"]], "\u0f66\u0fa1\u0f7a\u0f0b": [["\u0f42\u0f61\u0f7c\u0f44", "1"]], "\u0f66\u0fa3\u0f62\u0f0b": [["\u0f42\u0f61\u0f7c\u0f0b\u0f56", "129"], ["\u0f58\u0f72\u0f0b\u0f42\u0f61\u0f7c\u0f0b\u0f56", "105"]]}, "27": {"\u0f54\u0f7a\u0f0b": [["", "1"], ["\u0f51\u0f44", "18517"], ["\u0f56\u0fb1\u0f74\u0f44", "27"], ["\u0f56\u0fb1\u0f74\u0f44\u0f0b\u0f51\u0f44", "130"]], "\u0f66\u0fa1\u0f7a\u0f0b": [["\u0f42\u0f72", "1276"], ["\u0f42\u0f72\u0f0b\u0f51\u0f44", "214"], ["\u0f56\u0fb1\u0f74\u0f44\u0f0b\u0f42\u0f72", "190"]], "\u0f66\u0fa3\u0f62\u0f0b": [["", "1"], ["\u0f51\u0f44", "18517"], ["\u0f56\u0fb1\u0f74\u0f44", "27"], ["\u0f56\u0fb1\u0f74\u0f44\u0f0b\u0f51\u0f44", "130"]]}, "28": {"\u0f54\u0f7a\u0f0b": [["", "1"], ["\u0f66", "542"], ["\u0f66\u0fb3\u0f7c\u0f56\u0f0b\u0f58", "1668"]], "\u0f66\u0fa1\u0f7a\u0f0b": [["\u0f53", "73509"], ["\u0f66\u0f0b\u0f53", "194"]], "\u0f66\u0fa3\u0f62\u0f0b": [["", "1"], ["\u0f66", "542"], ["\u0f66\u0fb3\u0f7c\u0f56\u0f0b\u0f58", "1668"]]}, "29": {"\u0f54\u0f7a\u0f0b": [["", "1"], ["\u0f60\u0f72", "44"], ["\u0f56\u0f66\u0f90\u0fb1\u0f7a\u0f51\u0f0b\u0f54\u0f60\u0f72", "1170"], ["\u0f0d_\u0f0d\u0f56\u0f66\u0f90\u0fb1\u0f7a\u0f51\u0f0b\u0f54\u0f60\u0f72", "51"]], "\u0f66\u0fa1\u0f7a\u0f0b": [["", "1"], ["\u0f60\u0f72", "44"], ["\u0f56\u0f66\u0f90\u0fb1\u0f7a\u0f51\u0f0b\u0f54\u0f60\u0f72", "1170"], ["\u0f0d_\u0f0d\u0f56\u0f66\u0f90\u0fb1\u0f7a\u0f51\u0f0b\u0f54\u0f60\u0f72", "51"]], "\u0f66\u0fa3\u0f62\u0f0b": [["", "1"], ["\u0f60\u0f72", "44"], ["\u0f56\u0f66\u0f90\u0fb1\u0f7a\u0f51\u0f0b\u0f54\u0f60\u0f72", "1170"], ["\u0f0d_\u0f0d\u0f56\u0f66\u0f90\u0fb1\u0f7a\u0f51\u0f0b\u0f54\u0f60\u0f72", "51"]]}, "3": {"\u0f54\u0f7a\u0f0b": [["\u0f62\u0f90\u0f44", "9279"]], "\u0f66\u0fa1\u0f7a\u0f0b": [["\u0f62\u0f90\u0fb1\u0f7a\u0f53", "54"]], "\u0f66\u0fa3\u0f62\u0f0b": [["\u0f62\u0f90\u0f44", "9279"]]}, "30": {"\u0f54\u0f7a\u0f0b": [], "\u0f66\u0fa1\u0f7a\u0f0b": [["\u0f0d_\u0f0d", "997103"], ["\u0f60\u0f7c\u0f0d_\u0f0d", "419"], ["\u0f0d_\u0f0d\u0f56\u0f66\u0f90\u0fb1\u0f7a\u0f51\u0f0b\u0f54", "42"]], "\u0f66\u0fa3\u0f62\u0f0b": []}, "31": {"\u0f54\u0f7a\u0f0b": [], "\u0f66\u0fa1\u0f7a\u0f0b": [["\u0f0d_\u0f0d", "997103"], ["\u0f60\u0f7c\u0f0d_\u0f0d", "419"], ["\u0f0d_\u0f0d\u0f61\u0f72\u0f0b\u0f42\u0f7a", "1410"]], "\u0f66\u0fa3\u0f62\u0f0b": []}, "32": {"\u0f54\u0f7a\u0f0b": [["\u0f56\u0f45\u0f66\u0f0b\u0f63", "55"]], "\u0f66\u0fa1\u0f7a\u0f0b": [["\u0f56\u0f45\u0f66", "2049"], ["\u0f56\u0f45\u0f66\u0f0d_", "641"], ["\u0f4f\u0f74\u0f0b\u0f56\u0f45\u0f66", "74"]], "\u0f66\u0fa3\u0f62\u0f0b": [["\u0f56\u0f45\u0f66\u0f0b\u0f63", "55"]]}, "33": {"\u0f54\u0f7a\u0f0b": [["\u0f60\u0f5b\u0f72\u0f53\u0f0b\u0f54", "787"], ["\u0f60\u0f5b\u0f72\u0f53\u0f0b\u0f54\u0f0b\u0f58\u0f7a\u0f51\u0f0b\u0f54", "139"]], "\u0f66\u0fa1\u0f7a\u0f0b": [["\u0f60\u0f5b\u0f72\u0f53", "1720"]], "\u0f66\u0fa3\u0f62\u0f0b": [["\u0f60\u0f5b\u0f72\u0f53\u0f0b\u0f54", "787"], ["\u0f60\u0f5b\u0f72\u0f53\u0f0b\u0f54\u0f0b\u0f58\u0f7a\u0f51\u0f0b\u0f54", "139"]]}, "34": {"\u0f54\u0f7a\u0f0b": [], "\u0f66\u0fa1\u0f7a\u0f0b": [["", "1"], ["\u0f0d_", "47"], ["\u0f61\u0f72\u0f51", "168"]], "\u0f66\u0fa3\u0f62\u0f0b": []}, "35": {"\u0f54\u0f7a\u0f0b": [["\u0f62\u0f72\u0f58", "78"]], "\u0f66\u0fa1\u0f7a\u0f0b": [["\u0f62\u0f72\u0f58\u0f0b\u0f54", "1708"]], "\u0f66\u0fa3\u0f62\u0f0b": [["\u0f62\u0f72\u0f58\u0f0b\u0f54", "1708"]]}, "36": {"\u0f54\u0f7a\u0f0b": [["\u0f40\u0fb1\u0f72\u0f66", "6156"], ["\u0f40\u0fb1\u0f72\u0f66\u0f0b\u0f56\u0f62", "146"], ["\u0f61\u0f72\u0f51\u0f0b\u0f40\u0fb1\u0f72\u0f66", "133"]], "\u0f66\u0fa1\u0f7a\u0f0b": [["\u0f40\u0fb1\u0f72", "5256"], ["\u0f40\u0fb1\u0f72\u0f0b\u0f56\u0f62", "52"], ["\u0f61\u0f72\u0f51\u0f0b\u0f40\u0fb1\u0f72", "6835"], ["\u0f61\u0f72\u0f51\u0f0b\u0f40\u0fb1\u0f72\u0f0b\u0f56\u0f62", "70"]], "\u0f66\u0fa3\u0f62\u0f0b": [["\u0f40\u0fb1\u0f72\u0f66", "6156"], ["\u0f40\u0fb1\u0f72\u0f66\u0f0b\u0f56\u0f62", "146"], ["\u0f61\u0f72\u0f51\u0f0b\u0f40\u0fb1\u0f72\u0f66", "133"]]}, "37": {"\u0f54\u0f7a\u0f0b": [], "\u0f66\u0fa1\u0f7a\u0f0b": [["\u0f56\u0f66\u0f92\u0f7c\u0f58", "1273"], ["\u0f63\u0f0b\u0f56\u0f66\u0f92\u0f7c\u0f58", "180"], ["\u0f56\u0f66\u0f92\u0f7c\u0f58\u0f0b\u0f58\u0f7c", "92"]], "\u0f66\u0fa3\u0f62\u0f0b": []}, "38": {"\u0f54\u0f7a\u0f0b": [["\u0f56\u0f66\u0f92\u0f7c\u0f58", "1273"], ["\u0f4f\u0f74\u0f0b\u0f56\u0f66\u0f92\u0f7c\u0f58", "122"], ["\u0f56\u0f66\u0f92\u0f7c\u0f58\u0f0b\u0f51\u0f74", "56"]], "\u0f66\u0fa1\u0f7a\u0f0b": [["\u0f66\u0f92\u0f7c\u0f58", "123"]], "\u0f66\u0fa3\u0f62\u0f0b": [["\u0f56\u0f66\u0f92\u0f7c\u0f58", "1273"], ["\u0f4f\u0f74\u0f0b\u0f56\u0f66\u0f92\u0f7c\u0f58", "122"], ["\u0f56\u0f66\u0f92\u0f7c\u0f58\u0f0b\u0f51\u0f74", "56"]]}, "39": {"\u0f54\u0f7a\u0f0b": [["\u0f56\u0f66\u0f90\u0f7c\u0f62\u0f0b\u0f56", "553"], ["\u0f56\u0f66\u0f90\u0f7c\u0f62\u0f0b\u0f56\u0f0d_", "488"], ["\u0f66\u0f74\u0f0b\u0f56\u0f66\u0f90\u0f7c\u0f62\u0f0b\u0f56", "292"], ["\u0f66\u0f74\u0f0b\u0f56\u0f66\u0f90\u0f7c\u0f62\u0f0b\u0f56\u0f0d_", "290"]], "\u0f66\u0fa1\u0f7a\u0f0b": [["\u0f56\u0f66\u0f90\u0f7c\u0f62\u0f0b\u0f56\u0f66", "153"]], "\u0f66\u0fa3\u0f62\u0f0b": [["\u0f56\u0f66\u0f90\u0f7c\u0f62\u0f0b\u0f56", "553"], ["\u0f56\u0f66\u0f90\u0f7c\u0f62\u0f0b\u0f56\u0f0d_", "488"], ["\u0f66\u0f74\u0f0b\u0f56\u0f66\u0f90\u0f7c\u0f62\u0f0b\u0f56", "292"], ["\u0f66\u0f74\u0f0b\u0f56\u0f66\u0f90\u0f7c\u0f62\u0f0b\u0f56\u0f0d_", "290"]]}, "4": {"\u0f54\u0f7a\u0f0b": [["\u0f56\u0f5f\u0f74\u0f44", "11"]], "\u0f66\u0fa1\u0f7a\u0f0b": [["\u0f42\u0f5f\u0f74\u0f44", "5"]], "\u0f66\u0fa3\u0f62\u0f0b": [["\u0f56\u0f5f\u0f74\u0f44", "11"]]}, "40": {"\u0f54\u0f7a\u0f0b": [["\u0f50\u0f7c\u0f56\u0f0b\u0f63", "48"]], "\u0f66\u0fa1\u0f7a\u0f0b": [["\u0f50\u0f7c\u0f56", "930"], ["\u0f50\u0f7c\u0f56\u0f0d_", "141"]], "\u0f66\u0fa3\u0f62\u0f0b": [["\u0f50\u0f7c\u0f56\u0f0b\u0f63", "48"]]}, "41": {"\u0f54\u0f7a\u0f0b": [["\u0f50\u0f7c\u0f56\u0f0b\u0f54\u0f60\u0f7c", "180"], ["\u0f50\u0f7c\u0f56\u0f0b\u0f54\u0f60\u0f7c\u0f0d_\u0f0d", "178"]], "\u0f66\u0fa1\u0f7a\u0f0b": [["\u0f50\u0f7c\u0f56\u0f0b\u0f56\u0f7c", "970"], ["\u0f50\u0f7c\u0f56\u0f0b\u0f56\u0f7c\u0f0d_\u0f0d", "941"]], "\u0f66\u0fa3\u0f62\u0f0b": [["\u0f50\u0f7c\u0f56\u0f0b\u0f54\u0f60\u0f7c", "180"], ["\u0f50\u0f7c\u0f56\u0f0b\u0f54\u0f60\u0f7c\u0f0d_\u0f0d", "178"]]}, "42": {"\u0f54\u0f7a\u0f0b": [["\u0f56\u0f4f\u0f44", "4"], ["\u0f56\u0f4f\u0f44\u0f0b\u0f0d_", "49"]], "\u0f66\u0fa1\u0f7a\u0f0b": [["\u0f42\u0f4f\u0f44", "4"]], "\u0f66\u0fa3\u0f62\u0f0b": [["\u0f56\u0f4f\u0f44", "4"], ["\u0f56\u0f4f\u0f44\u0f0b\u0f0d_", "49"]]}, "43": {"\u0f54\u0f7a\u0f0b": [["", "1"], ["\u0f46\u0f74", "123"], ["\u0f63\u0f9f\u0f0b\u0f56\u0f74", "1179"]], "\u0f66\u0fa1\u0f7a\u0f0b": [["\u0f5f\u0fb3", "17"], ["\u0f46\u0f74\u0f0b\u0f5f\u0fb3", "220"]], "\u0f66\u0fa3\u0f62\u0f0b": [["", "1"], ["\u0f46\u0f74", "123"], ["\u0f63\u0f9f\u0f0b\u0f56\u0f74", "1179"]]}, "44": {"\u0f54\u0f7a\u0f0b": [["", "1"], ["\u0f0d\u0f0d_\u0f0d\u0f0d", "7586"], ["\u0f66\u0f7c\u0f0d\u0f0d_\u0f0d\u0f0d", "1472"], ["\u0f62\u0fab\u0f7c\u0f42\u0f66\u0f0b\u0f66\u0f7c\u0f0d\u0f0d_\u0f0d\u0f0d", "1081"]], "\u0f66\u0fa1\u0f7a\u0f0b": [["", "1"], ["\u0f0d\u0f0d_\u0f0d\u0f0d", "7586"], ["\u0f66\u0f7c\u0f0d\u0f0d_\u0f0d\u0f0d", "1472"], ["\u0f62\u0fab\u0f7c\u0f42\u0f66\u0f0b\u0f66\u0f7c\u0f0d\u0f0d_\u0f0d\u0f0d", "1081"]], "\u0f66\u0fa3\u0f62\u0f0b": [["", "1"], ["\u0f0d\u0f0d_\u0f0d\u0f0d", "7586"], ["\u0f66\u0f7c\u0f0d\u0f0d_\u0f0d\u0f0d", "1472"], ["\u0f62\u0fab\u0f7c\u0f42\u0f66\u0f0b\u0f66\u0f7c\u0f0d\u0f0d_\u0f0d\u0f0d", "1081"]]}, "5": {"\u0f54\u0f7a\u0f0b": [["\u0f66\u0f90\u0fb1\u0f7a\u0f0b\u0f58\u0f7a\u0f51", "256"]], "\u0f66\u0fa1\u0f7a\u0f0b": [["\u0f66\u0f90\u0fb1\u0f7a\u0f0b\u0f58\u0f46\u0f7a\u0f51", "6033"], ["\u0f66\u0f90\u0fb1\u0f7a\u0f0b\u0f58\u0f46\u0f7a\u0f51\u0f0b\u0f51\u0f74", "152"]], "\u0f66\u0fa3\u0f62\u0f0b": [["\u0f66\u0f90\u0fb1\u0f7a\u0f0b\u0f58\u0f7a\u0f51", "256"]]}, "6": {"\u0f54\u0f7a\u0f0b": [["\u0f66\u0f7a\u0f58\u0f66\u0f0b\u0f45\u0f53", "56510"], ["\u0f66\u0f7a\u0f58\u0f66\u0f0b\u0f45\u0f53\u0f0b\u0f63", "92"], ["\u0f0d_\u0f66\u0f7a\u0f58\u0f66\u0f0b\u0f45\u0f53", "12113"], ["\u0f0d_\u0f66\u0f7a\u0f58\u0f66\u0f0b\u0f45\u0f53\u0f0b\u0f63", "227"]], "\u0f66\u0fa1\u0f7a\u0f0b": [["\u0f66\u0f7a\u0f58\u0f66", "4229"], ["\u0f0d_\u0f66\u0f7a\u0f58\u0f66", "16502"], ["\u0f66\u0f7a\u0f58\u0f66\u0f0b\u0f63", "101"], ["\u0f0d_\u0f66\u0f7a\u0f58\u0f66\u0f0b\u0f63", "181"]], "\u0f66\u0fa3\u0f62\u0f0b": [["\u0f66\u0f7a\u0f58\u0f66\u0f0b\u0f45\u0f53", "56510"], ["\u0f66\u0f7a\u0f58\u0f66\u0f0b\u0f45\u0f53\u0f0b\u0f63", "92"], ["\u0f0d_\u0f66\u0f7a\u0f58\u0f66\u0f0b\u0f45\u0f53", "12113"], ["\u0f0d_\u0f66\u0f7a\u0f58\u0f66\u0f0b\u0f45\u0f53\u0f0b\u0f63", "227"]]}, "7": {"\u0f54\u0f7a\u0f0b": [["", "1"], ["\u0f0d_", "47"], ["\u0f66\u0f92\u0fb2", "261"], ["\u0f0d_\u0f66\u0f92\u0fb2", "2195"]], "\u0f66\u0fa1\u0f7a\u0f0b": [["\u0f44\u0f42", "24"], ["\u0f0d_\u0f44\u0f42", "1108"]], "\u0f66\u0fa3\u0f62\u0f0b": [["", "1"], ["\u0f0d_", "47"], ["\u0f66\u0f92\u0fb2", "261"], ["\u0f0d_\u0f66\u0f92\u0fb2", "2195"]]}, "8": {"\u0f54\u0f7a\u0f0b": [["\u0f42\u0fb2\u0f42\u0f66", "882"]], "\u0f66\u0fa1\u0f7a\u0f0b": [["\u0f42\u0fb2\u0f42", "56"]], "\u0f66\u0fa3\u0f62\u0f0b": [["\u0f42\u0fb2\u0f42\u0f66", "882"]]}, "9": {"\u0f54\u0f7a\u0f0b": [["\u0f66\u0f9f\u0f7a\u0f44\u0f66\u0f0b\u0f66\u0f74", "47"]], "\u0f66\u0fa1\u0f7a\u0f0b": [["\u0f66\u0f9f\u0f7a\u0f44\u0f0b\u0f51\u0f74", "3472"]], "\u0f66\u0fa3\u0f62\u0f0b": [["\u0f66\u0f9f\u0f7a\u0f44\u0f66\u0f0b\u0f66\u0f74", "47"]]}}, "non_standard_notes": [], "profile": {"1": ["\u0f54\u0f7a\u0f0b=\u0f66\u0fa3\u0f62\u0f0b \u0f66\u0fa1\u0f7a\u0f0b", "93.18%"], "10": ["\u0f54\u0f7a\u0f0b=\u0f66\u0fa3\u0f62\u0f0b \u0f66\u0fa1\u0f7a\u0f0b", "93.18%"], "11": ["\u0f54\u0f7a\u0f0b=\u0f66\u0fa3\u0f62\u0f0b \u0f66\u0fa1\u0f7a\u0f0b", "93.18%"], "12": ["\u0f54\u0f7a\u0f0b=\u0f66\u0fa3\u0f62\u0f0b \u0f66\u0fa1\u0f7a\u0f0b", "93.18%"], "13": ["\u0f54\u0f7a\u0f0b=\u0f66\u0fa3\u0f62\u0f0b \u0f66\u0fa1\u0f7a\u0f0b", "93.18%"], "14": ["\u0f54\u0f7a\u0f0b=\u0f66\u0fa3\u0f62\u0f0b \u0f66\u0fa1\u0f7a\u0f0b", "93.18%"], "15": ["\u0f54\u0f7a\u0f0b=\u0f66\u0fa3\u0f62\u0f0b \u0f66\u0fa1\u0f7a\u0f0b", "93.18%"], "16": ["\u0f54\u0f7a\u0f0b=\u0f66\u0fa3\u0f62\u0f0b \u0f66\u0fa1\u0f7a\u0f0b", "93.18%"], "17": ["\u0f54\u0f7a\u0f0b=\u0f66\u0fa3\u0f62\u0f0b \u0f66\u0fa1\u0f7a\u0f0b", "93.18%"], "18": ["\u0f54\u0f7a\u0f0b=\u0f66\u0fa3\u0f62\u0f0b \u0f66\u0fa1\u0f7a\u0f0b", "93.18%"], "19": ["\u0f54\u0f7a\u0f0b=\u0f66\u0fa3\u0f62\u0f0b \u0f66\u0fa1\u0f7a\u0f0b", "93.18%"], "2": ["\u0f54\u0f7a\u0f0b=\u0f66\u0fa3\u0f62\u0f0b \u0f66\u0fa1\u0f7a\u0f0b", "93.18%"], "20": ["\u0f54\u0f7a\u0f0b=\u0f66\u0fa3\u0f62\u0f0b \u0f66\u0fa1\u0f7a\u0f0b", "93.18%"], "21": ["\u0f54\u0f7a\u0f0b=\u0f66\u0fa3\u0f62\u0f0b \u0f66\u0fa1\u0f7a\u0f0b", "93.18%"], "22": ["\u0f54\u0f7a\u0f0b=\u0f66\u0fa3\u0f62\u0f0b \u0f66\u0fa1\u0f7a\u0f0b", "93.18%"], "23": ["\u0f54\u0f7a\u0f0b=\u0f66\u0fa3\u0f62\u0f0b \u0f66\u0fa1\u0f7a\u0f0b", "93.18%"], "24": ["\u0f54\u0f7a\u0f0b=\u0f66\u0fa3\u0f62\u0f0b \u0f66\u0fa1\u0f7a\u0f0b", "93.18%"], "25": ["\u0f54\u0f7a\u0f0b=\u0f66\u0fa3\u0f62\u0f0b \u0f66\u0fa1\u0f7a\u0f0b", "93.18%"], "26": ["\u0f54\u0f7a\u0f0b=\u0f66\u0fa3\u0f62\u0f0b \u0f66\u0fa1\u0f7a\u0f0b", "93.18%"], "27": ["\u0f54\u0f7a\u0f0b=\u0f66\u0fa3\u0f62\u0f0b \u0f66\u0fa1\u0f7a\u0f0b", "93.18%"], "28": ["\u0f54\u0f7a\u0f0b=\u0f66\u0fa3\u0f62\u0f0b \u0f66\u0fa1\u0f7a\u0f0b", "93.18%"], "29": ["\u0f54\u0f7a\u0f0b=\u0f66\u0fa1\u0f7a\u0f0b=\u0f66\u0fa3\u0f62\u0f0b", "4.55%"], "3": ["\u0f54\u0f7a\u0f0b=\u0f66\u0fa3\u0f62\u0f0b \u0f66\u0fa1\u0f7a\u0f0b", "93.18%"], "30": ["\u0f54\u0f7a\u0f0b=\u0f66\u0fa3\u0f62\u0f0b \u0f66\u0fa1\u0f7a\u0f0b", "93.18%"], "31": ["\u0f54\u0f7a\u0f0b=\u0f66\u0fa3\u0f62\u0f0b \u0f66\u0fa1\u0f7a\u0f0b", "93.18%"], "32": ["\u0f54\u0f7a\u0f0b=\u0f66\u0fa3\u0f62\u0f0b \u0f66\u0fa1\u0f7a\u0f0b", "93.18%"], "33": ["\u0f54\u0f7a\u0f0b=\u0f66\u0fa3\u0f62\u0f0b \u0f66\u0fa1\u0f7a\u0f0b", "93.18%"], "34": ["\u0f54\u0f7a\u0f0b=\u0f66\u0fa3\u0f62\u0f0b \u0f66\u0fa1\u0f7a\u0f0b", "93.18%"], "35": ["\u0f54\u0f7a\u0f0b \u0f66\u0fa1\u0f7a\u0f0b=\u0f66\u0fa3\u0f62\u0f0b", "2.27%"], "36": ["\u0f54\u0f7a\u0f0b=\u0f66\u0fa3\u0f62\u0f0b \u0f66\u0fa1\u0f7a\u0f0b", "93.18%"], "37": ["\u0f54\u0f7a\u0f0b=\u0f66\u0fa3\u0f62\u0f0b \u0f66\u0fa1\u0f7a\u0f0b", "93.18%"], "38": ["\u0f54\u0f7a\u0f0b=\u0f66\u0fa3\u0f62\u0f0b \u0f66\u0fa1\u0f7a\u0f0b", "93.18%"], "39": ["\u0f54\u0f7a\u0f0b=\u0f66\u0fa3\u0f62\u0f0b \u0f66\u0fa1\u0f7a\u0f0b", "93.18%"], "4": ["\u0f54\u0f7a\u0f0b=\u0f66\u0fa3\u0f62\u0f0b \u0f66\u0fa1\u0f7a\u0f0b", "93.18%"], "40": ["\u0f54\u0f7a\u0f0b=\u0f66\u0fa3\u0f62\u0f0b \u0f66\u0fa1\u0f7a\u0f0b", "93.18%"], "41": ["\u0f54\u0f7a\u0f0b=\u0f66\u0fa3\u0f62\u0f0b \u0f66\u0fa1\u0f7a\u0f0b", "93.18%"], "42": ["\u0f54\u0f7a\u0f0b=\u0f66\u0fa3\u0f62\u0f0b \u0f66\u0fa1\u0f7a\u0f0b", "93.18%"], "43": ["\u0f54\u0f7a\u0f0b=\u0f66\u0fa3\u0f62\u0f0b \u0f66\u0fa1\u0f7a\u0f0b", "93.18%"], "44": ["\u0f54\u0f7a\u0f0b=\u0f66\u0fa1\u0f7a\u0f0b=\u0f66\u0fa3\u0f62\u0f0b", "4.55%"], "5": ["\u0f54\u0f7a\u0f0b=\u0f66\u0fa3\u0f62\u0f0b \u0f66\u0fa1\u0f7a\u0f0b", "93.18%"], "6": ["\u0f54\u0f7a\u0f0b=\u0f66\u0fa3\u0f62\u0f0b \u0f66\u0fa1\u0f7a\u0f0b", "93.18%"], "7": ["\u0f54\u0f7a\u0f0b=\u0f66\u0fa3\u0f62\u0f0b \u0f66\u0fa1\u0f7a\u0f0b", "93.18%"], "8": ["\u0f54\u0f7a\u0f0b=\u0f66\u0fa3\u0f62\u0f0b \u0f66\u0fa1\u0f7a\u0f0b", "93.18%"], "9": ["\u0f54\u0f7a\u0f0b=\u0f66\u0fa3\u0f62\u0f0b \u0f66\u0fa1\u0f7a\u0f0b", "93.18%"]}}